Workbook

Sheet T_Base
H1: Exit Cap | N1: Rent Growth | V1: Unlevered Prop Level | Y1: Levered Prop Level | AB1: Gross Fund Level Ret | AE1: Net Fund Level Ret | AH1: Rent Growth | AQ1: Exit Cap vs. 10 YR | BQ1: 3 YR Portfolio | BX1: 6 YR Portfolio | CU1: Exit cap rate caln
A2: SectorIdentifier | B2: Region | C2: Profile | D2: Nom Cap Rate | E2: Capex | F2: Econ Cap Rate | H2: YR 3 Eco Exit Cap | I2: YR 6 Eco Exit Cap | K2: YR 3 Exit Cap | L2: YR 6 Exit Cap | N2: Yr 1 | O2: Yr 2 | P2: Yr 3 | Q2: Yr 4 | R2: Yr 5 | S2: Yr 6 | T2: 3 YR CAGR | U2: 6 YR CAGR | V2: 3 YR IRR | W2: 6 YR IRR | Y2: 3 YR Lev IRR | Z2: 6 YR Lev IRR | AB2: 3 YR IRR | AC2: 6 YR IRR | AE2: 3 YR IRR | AF2: 6 YR IRR | AH2: Yr 1 | AI2: Yr 2 | AJ2: Yr 3 | AK2: Yr 4 | AL2: Yr 5 | AM2: Yr 6 | AN2: 3 YR CAGR | AO2: 6 YR CAGR | AQ2: YR 3 Exit Cap | AR2: YR 6 Exit Cap | AT2: Std Dev | AW2: Yr 1 | AX2: Yr 2 | AY2: Yr 3 | BB2: Yr 1 | BC2: Yr 2 | BD2: Yr 3 | BE2: Yr 4 | BF2: Yr 5 | BG2: Yr 6 | BI2: LTV | BJ2: Rate | BK2: Rate - Base Case | BL2: Rate - High | BM2: Rate - Low | BN2: Non-Core | BO2: Fee Drag | BQ2: 3 YR Rank | BR2: SI | BS2: Min | BT2: Max | BU2: Port | BV2: Test | BX2: 6 YR Rank | BY2: SI | BZ2: Min | CA2: Max | CB2: Port | CC2: Test | CF2: Prop unlev ret over 10 Yr Spread | CG2: Prop unlev ret over 10 Yr Spread - Base | CH2: Prop unlev ret over 10 Yr Spread - High | CI2: Prop unlev ret over 10 Yr Spread - Low | CJ2: Target unlev prop return 3 YR | CK2: Target unlev prop return 6 YR | CL2: Over/ undervalued | CM2: Yr 1 | CN2: Yr 2 | CO2: Yr 3 | CP2: Yr 4 | CQ2: Yr 5 | CR2: Yr 6 | CU2: Rent Gr expect 3 YR | CV2: Rent Gr expect 6 YR | CX2: Eco Cap Rate 3 YR | CY2: Eco Cap Rate 6 YR | DA2: Nom Cap Rate 3 YR | DB2: Nom Cap Rate 6 YR
A3: 1 | B3: US | C3: Core - Res | D3: 0.047 | E3: 0.159 | F3: =+D3*(1-E3) -> 0.039527 | H3: =CX3 -> 0.025 | I3: =CY3 -> 0.04 | K3: =+H3/(1-$E3) -> 0.029726516 | L3: =+I3/(1-$E3) -> 0.047562426 | N3: =+AH3+(D$29-D$34) -> -0.012 | O3: =+AI3+(E$29-E$34) -> 0.01 | P3: =+AJ3+(F$29-F$34) -> 0.024 | Q3: =+AK3+(G$29-G$34) -> 0.04 | R3: =+AL3+(H$29-H$34) -> 0.05 | S3: =+AM3+(I$29-I$34) -> 0.025 | T3: {=+PRODUCT(1+N3:P3)^(0.333333333333333)-1} -> 0.0072240606 | U3: {=+PRODUCT(1+N3:S3)^(1/6)-1} -> 0.022635339 | V3: =+IRR(AV3:AY3) -> 0.20748801 | W3: =+IRR(BA3:BG3) -> 0.060137777 | Y3: =+(V3-BI3*BJ3)/(1-BI3) -> 0.25228963 | Z3: =+(W3-BI3*BJ3)/(1-BI3) -> 0.060925684 | AB3: =V3+$BN3 -> 0.21248801 | AC3: =Z3+$BN3 -> 0.065925684 | AE3: =AB3-$BO3 -> 0.20248801 | AF3: =AC3-$BO3 -> 0.055925684 | AH3: -0.012 | AI3: 0.01 | AJ3: 0.024 | AK3: 0.04 | AL3: 0.05 | AM3: 0.025 | AN3: {=+PRODUCT(1+AH3:AJ3)^(0.333333333333333)-1} -> 0.0072240606 | AO3: {=+PRODUCT(1+AH3:AM3)^(1/6)-1} -> 0.022635339 | AQ3: -0.003314 | AR3: -0.005 | AT3: 0.01 | AV3: =-1 -> -1 | AW3: =+F3*(1+N3) -> 0.039052676 | AX3: =+AW3*(1+O3) -> 0.039443203 | AY3: =+AX3*(1+P3)+(AX3*(1+P3))/H3 -> 1.6559834 | BA3: -1 | BB3: =+F3*(1+N3) -> 0.039052676 | BC3: =+BB3*(1+O3) -> 0.039443203 | BD3: =+BC3*(1+P3) -> 0.04038984 | BE3: =+BD3*(1+Q3) -> 0.042005433 | BF3: =+BE3*(1+R3) -> 0.044105705 | BG3: =+BF3*(1+S3)+BF3*(1+S3)/I3 -> 1.175417 | BI3: 0.23 | BJ3: =IF($D$25="Base",BK3,IF($D$25="High",BL3,IF($D$25="Low",BM3,"ERR"))) -> 0.0575 | BK3: 0.0575 | BL3: 0.06 | BM3: 0.055 | BN3: 0.005 | BO3: 0.01 | BQ3: =RANK(AE3,AE$3:AE$21) -> 5 | BR3: =+$A3 -> 1 | BS3: 0 | BT3: 0.3 | BX3: =RANK(AF3,AF$3:AF$21) -> 15 | BY3: =+$A3 -> 1 | BZ3: 0 | CA3: 0.3 | CF3: =IF($D$25="Base",CG3,IF($D$25="High",CH3,IF($D$25="Low",CI3,"ERR"))) -> 0.025 | CG3: 0.025 | CH3: 0.0275 | CI3: 0.0225 | CJ3: =+$F$30+CF3 -> 0.065 | CK3: =$I$30+CF3 -> 0.065 | CL3: =+NPV(CJ3,CM3:CR3) -> 0.97527844 | CM3: =+BB3 -> 0.039052676 | CN3: =+BC3 -> 0.039443203 | CO3: =+BD3 -> 0.04038984 | CP3: =+BE3 -> 0.042005433 | CQ3: =+BF3 -> 0.044105705 | CR3: =+BG3 -> 1.175417 | CU3: =Q3 -> 0.04 | CV3: =S3 -> 0.025 | CX3: =CJ3-CU3 -> 0.025 | CY3: =+CK3-CV3 -> 0.04 | DA3: =+CX3/(1-$E3) -> 0.029726516 | DB3: =+CY3/(1-$E3) -> 0.047562426
A4: =+A3+1 -> 2 | B4: US | C4: Core - Ind | D4: 0.045 | E4: 0.138 | F4: =+D4*(1-E4) -> 0.03879 | H4: =CX4 -> 0.03 | I4: =CY4 -> 0.04 | K4: =+H4/(1-$E4) -> 0.034802784 | L4: =+I4/(1-$E4) -> 0.046403712 | N4: =+AH4+(D$29-D$34) -> 0.061 | O4: =+AI4+(E$29-E$34) -> 0.05 | P4: =+AJ4+(F$29-F$34) -> 0.043 | Q4: =+AK4+(G$29-G$34) -> 0.04 | R4: =+AL4+(H$29-H$34) -> 0.035 | S4: =+AM4+(I$29-I$34) -> 0.03 | T4: {=+PRODUCT(1+N4:P4)^(0.333333333333333)-1} -> 0.051307261 | U4: {=+PRODUCT(1+N4:S4)^(1/6)-1} -> 0.043117707 | V4: =+IRR(AV4:AY4) -> 0.18314864 | W4: =+IRR(BA4:BG4) -> 0.079436337 | Y4: =+(V4-BI4*BJ4)/(1-BI4) -> 0.1971096 | Z4: =+(W4-BI4*BJ4)/(1-BI4) -> 0.081873708 | AB4: =V4+$BN4 -> 0.19064864 | AC4: =Z4+$BN4 -> 0.089373708 | AE4: =AB4-$BO4 -> 0.18064864 | AF4: =AC4-$BO4 -> 0.079373708 | AH4: 0.061 | AI4: 0.05 | AJ4: 0.043 | AK4: 0.04 | AL4: 0.035 | AM4: 0.03 | AN4: {=+PRODUCT(1+AH4:AJ4)^(0.333333333333333)-1} -> 0.051307261 | AO4: {=+PRODUCT(1+AH4:AM4)^(1/6)-1} -> 0.043117707 | AQ4: -0.006606 | AR4: 0 | AT4: 0.015 | AV4: =-1 -> -1 | AW4: =+F4*(1+N4) -> 0.04115619 | AX4: =+AW4*(1+O4) -> 0.043213999 | AY4: =+AX4*(1+P4)+(AX4*(1+P4))/H4 -> 1.5474789 | BA4: =+BA3 -> -1 | BB4: =+F4*(1+N4) -> 0.04115619 | BC4: =+BB4*(1+O4) -> 0.043213999 | BD4: =+BC4*(1+P4) -> 0.045072201 | BE4: =+BD4*(1+Q4) -> 0.04687509 | BF4: =+BE4*(1+R4) -> 0.048515718 | BG4: =+BF4*(1+S4)+BF4*(1+S4)/I4 -> 1.2992509 | BI4: 0.1 | BJ4: =IF($D$25="Base",BK4,IF(D$25="High",BL4,IF(D$25="Low",BM4,"ERR"))) -> 0.0575 | BK4: 0.0575 | BL4: 0.06 | BM4: 0.055 | BN4: 0.0075 | BO4: 0.01 | BQ4: =RANK(AE4,AE$3:AE$21) -> 6 | BR4: =+$A4 -> 2 | BS4: 0 | BT4: 0.3 | BX4: =RANK(AF4,AF$3:AF$21) -> 8 | BY4: =+$A4 -> 2 | BZ4: 0 | CA4: 0.3 | CF4: =IF($D$25="Base",CG4,IF($D$25="High",CH4,IF($D$25="Low",CI4,"ERR"))) -> 0.03 | CG4: 0.03 | CH4: 0.0325 | CI4: 0.0275 | CJ4: =+$F$30+CF4 -> 0.07 | CK4: =$I$30+CF4 -> 0.07 | CL4: =+NPV(CJ4,CM4:CR4) -> 1.0490984 | CM4: =+BB4 -> 0.04115619 | CN4: =+BC4 -> 0.043213999 | CO4: =+BD4 -> 0.045072201 | CP4: =+BE4 -> 0.04687509 | CQ4: =+BF4 -> 0.048515718 | CR4: =+BG4 -> 1.2992509 | CU4: =Q4 -> 0.04 | CV4: =S4 -> 0.03 | CX4: =CJ4-CU4 -> 0.03 | CY4: =+CK4-CV4 -> 0.04 | DA4: =+CX4/(1-$E4) -> 0.034802784 | DB4: =+CY4/(1-$E4) -> 0.046403712
A5: =+A4+1 -> 3 | B5: US | C5: Core - Off | D5: 0.085 | E5: 0.294 | F5: =+D5*(1-E5) -> 0.06001 | H5: =CX5 -> 0.07 | I5: =CY5 -> 0.055 | K5: =+H5/(1-$E5) -> 0.099150142 | L5: =+I5/(1-$E5) -> 0.077903683 | N5: =+AH5+(D$29-D$34) -> -0.018 | O5: =+AI5+(E$29-E$34) -> -0.011 | P5: =+AJ5+(F$29-F$34) -> -0.008 | Q5: =+AK5+(G$29-G$34) -> 0.005 | R5: =+AL5+(H$29-H$34) -> 0.01 | S5: =+AM5+(I$29-I$34) -> 0.02 | T5: {=+PRODUCT(1+N5:P5)^(0.333333333333333)-1} -> -0.012342232 | U5: {=+PRODUCT(1+N5:S5)^(1/6)-1} -> -0.00041934372 | V5: =+IRR(AV5:AY5) -> 0.00033989985 | W5: =+IRR(BA5:BG5) -> 0.070903743 | Y5: =+(V5-BI5*BJ5)/(1-BI5) -> -0.017075125 | Z5: =+(W5-BI5*BJ5)/(1-BI5) -> 0.071129678 | AB5: =V5+$BN5 -> 0.00033989985 | AC5: =Z5+$BN5 -> 0.071129678 | AE5: =AB5-$BO5 -> -0.0096601002 | AF5: =AC5-$BO5 -> 0.061129678 | AH5: -0.018 | AI5: -0.011 | AJ5: -0.008 | AK5: 0.005 | AL5: 0.01 | AM5: 0.02 | AN5: {=+PRODUCT(1+AH5:AJ5)^(0.333333333333333)-1} -> -0.012342232 | AO5: {=+PRODUCT(1+AH5:AM5)^(1/6)-1} -> -0.00041934372 | AQ5: 0.009536 | AR5: 0.009536 | AT5: 0.03 | AV5: =-1 -> -1 | AW5: =+F5*(1+N5) -> 0.05892982 | AX5: =+AW5*(1+O5) -> 0.058281592 | AY5: =+AX5*(1+P5)+(AX5*(1+P5))/H5 -> 0.88374876 | BA5: =+BA4 -> -1 | BB5: =+F5*(1+N5) -> 0.05892982 | BC5: =+BB5*(1+O5) -> 0.058281592 | BD5: =+BC5*(1+P5) -> 0.057815339 | BE5: =+BD5*(1+Q5) -> 0.058104416 | BF5: =+BE5*(1+R5) -> 0.05868546 | BG5: =+BF5*(1+S5)+BF5*(1+S5)/I5 -> 1.1482077 | BI5: 0.2 | BJ5: =IF($D$25="Base",BK5,IF(D$25="High",BL5,IF(D$25="Low",BM5,"ERR"))) -> 0.07 | BK5: 0.07 | BL5: 0.0725 | BM5: 0.0675 | BN5: 0 | BO5: 0.01 | BQ5: =RANK(AE5,AE$3:AE$21) -> 19 | BR5: =+$A5 -> 3 | BS5: 0 | BT5: 0.15 | BX5: =RANK(AF5,AF$3:AF$21) -> 13 | BY5: =+$A5 -> 3 | BZ5: 0 | CA5: 0.15 | CF5: =IF($D$25="Base",CG5,IF($D$25="High",CH5,IF($D$25="Low",CI5,"ERR"))) -> 0.035 | CG5: 0.035 | CH5: 0.0375 | CI5: 0.0325 | CJ5: =+$F$30+CF5 -> 0.075 | CK5: =$I$30+CF5 -> 0.075 | CL5: =+NPV(CJ5,CM5:CR5) -> 0.98017136 | CM5: =+BB5 -> 0.05892982 | CN5: =+BC5 -> 0.058281592 | CO5: =+BD5 -> 0.057815339 | CP5: =+BE5 -> 0.058104416 | CQ5: =+BF5 -> 0.05868546 | CR5: =+BG5 -> 1.1482077 | CU5: =Q5 -> 0.005 | CV5: =S5 -> 0.02 | CX5: =CJ5-CU5 -> 0.07 | CY5: =+CK5-CV5 -> 0.055 | DA5: =+CX5/(1-$E5) -> 0.099150142 | DB5: =+CY5/(1-$E5) -> 0.077903683
A6: =+A5+1 -> 4 | B6: US | C6: Core - Retail | D6: 0.06 | E6: 0.188 | F6: =+D6*(1-E6) -> 0.04872 | H6: =CX6 -> 0.05 | I6: =CY6 -> 0.045 | K6: =+H6/(1-$E6) -> 0.061576355 | L6: =+I6/(1-$E6) -> 0.055418719 | N6: =+AH6+(D$29-D$34) -> 0.01 | O6: =+AI6+(E$29-E$34) -> 0.02 | P6: =+AJ6+(F$29-F$34) -> 0.02 | Q6: =+AK6+(G$29-G$34) -> 0.02 | R6: =+AL6+(H$29-H$34) -> 0.02 | S6: =+AM6+(I$29-I$34) -> 0.025 | T6: {=+PRODUCT(1+N6:P6)^(0.333333333333333)-1} -> 0.016655714 | U6: {=+PRODUCT(1+N6:S6)^(1/6)-1} -> 0.019156756 | V6: =+IRR(AV6:AY6) -> 0.057686114 | W6: =+IRR(BA6:BG6) -> 0.080564252 | Y6: =+(V6-BI6*BJ6)/(1-BI6) -> 0.057277781 | Z6: =+(W6-BI6*BJ6)/(1-BI6) -> 0.084193238 | AB6: =V6+$BN6 -> 0.060186114 | AC6: =Z6+$BN6 -> 0.086693238 | AE6: =AB6-$BO6 -> 0.050186114 | AF6: =AC6-$BO6 -> 0.076693238 | AH6: 0.01 | AI6: 0.02 | AJ6: 0.02 | AK6: 0.02 | AL6: 0.02 | AM6: 0.025 | AN6: {=+PRODUCT(1+AH6:AJ6)^(0.333333333333333)-1} -> 0.016655714 | AO6: {=+PRODUCT(1+AH6:AM6)^(1/6)-1} -> 0.019156756 | AQ6: 0.00466 | AR6: 0.00466 | AT6: 0.02 | AV6: =-1 -> -1 | AW6: =+F6*(1+N6) -> 0.0492072 | AX6: =+AW6*(1+O6) -> 0.050191344 | AY6: =+AX6*(1+P6)+(AX6*(1+P6))/H6 -> 1.0750986 | BA6: =+BA5 -> -1 | BB6: =+F6*(1+N6) -> 0.0492072 | BC6: =+BB6*(1+O6) -> 0.050191344 | BD6: =+BC6*(1+P6) -> 0.051195171 | BE6: =+BD6*(1+Q6) -> 0.052219074 | BF6: =+BE6*(1+R6) -> 0.053263456 | BG6: =+BF6*(1+S6)+BF6*(1+S6)/I6 -> 1.2678182 | BI6: 0.15 | BJ6: =IF($D$25="Base",BK6,IF(D$25="High",BL6,IF(D$25="Low",BM6,"ERR"))) -> 0.06 | BK6: 0.06 | BL6: 0.0625 | BM6: 0.0575 | BN6: 0.0025 | BO6: 0.01 | BQ6: =RANK(AE6,AE$3:AE$21) -> 14 | BR6: =+$A6 -> 4 | BS6: 0 | BT6: 0.15 | BX6: =RANK(AF6,AF$3:AF$21) -> 11 | BY6: =+$A6 -> 4 | BZ6: 0 | CA6: 0.15 | CF6: =IF($D$25="Base",CG6,IF($D$25="High",CH6,IF($D$25="Low",CI6,"ERR"))) -> 0.03 | CG6: 0.03 | CH6: 0.0325 | CI6: 0.0275 | CJ6: =+$F$30+CF6 -> 0.07 | CK6: =$I$30+CF6 -> 0.07 | CL6: =+NPV(CJ6,CM6:CR6) -> 1.0542322 | CM6: =+BB6 -> 0.0492072 | CN6: =+BC6 -> 0.050191344 | CO6: =+BD6 -> 0.051195171 | CP6: =+BE6 -> 0.052219074 | CQ6: =+BF6 -> 0.053263456 | CR6: =+BG6 -> 1.2678182 | CU6: =Q6 -> 0.02 | CV6: =S6 -> 0.025 | CX6: =CJ6-CU6 -> 0.05 | CY6: =+CK6-CV6 -> 0.045 | DA6: =+CX6/(1-$E6) -> 0.061576355 | DB6: =+CY6/(1-$E6) -> 0.055418719
A7: =+A6+1 -> 5 | B7: US | C7: Core-Plus - Res | D7: 0.05 | E7: 0.159 | F7: =+D7*(1-E7) -> 0.04205 | H7: =CX7 -> 0.025 | I7: =CY7 -> 0.04 | K7: =+H7/(1-$E7) -> 0.029726516 | L7: =+I7/(1-$E7) -> 0.047562426 | N7: =+AH7+(D$29-D$34) -> -0.016 | O7: =+AI7+(E$29-E$34) -> 0.006 | P7: =+AJ7+(F$29-F$34) -> 0.023 | Q7: =+AK7+(G$29-G$34) -> 0.04 | R7: =+AL7+(H$29-H$34) -> 0.05 | S7: =+AM7+(I$29-I$34) -> 0.025 | T7: {=+PRODUCT(1+N7:P7)^(0.333333333333333)-1} -> 0.0042062136 | U7: {=+PRODUCT(1+N7:S7)^(1/6)-1} -> 0.021102179 | V7: =+IRR(AV7:AY7) -> 0.22973345 | W7: =+IRR(BA7:BG7) -> 0.070486563 | Y7: =+(V7-BI7*BJ7)/(1-BI7) -> 0.35966394 | Z7: =+(W7-BI7*BJ7)/(1-BI7) -> 0.080283443 | AB7: =V7+$BN7 -> 0.23973345 | AC7: =Z7+$BN7 -> 0.090283443 | AE7: =AB7-$BO7 -> 0.22723345 | AF7: =AC7-$BO7 -> 0.077783443 | AH7: -0.016 | AI7: 0.006 | AJ7: 0.023 | AK7: 0.04 | AL7: 0.05 | AM7: 0.025 | AN7: {=+PRODUCT(1+AH7:AJ7)^(0.333333333333333)-1} -> 0.0042062136 | AO7: {=+PRODUCT(1+AH7:AM7)^(1/6)-1} -> 0.021102179 | AQ7: -0.001632 | AR7: -0.005 | AT7: 0.0125 | AV7: =-1 -> -1 | AW7: =+F7*(1+N7) -> 0.0413772 | AX7: =+AW7*(1+O7) -> 0.041625463 | AY7: =+AX7*(1+P7)+(AX7*(1+P7))/H7 -> 1.7458968 | BA7: =+BA6 -> -1 | BB7: =+F7*(1+N7) -> 0.0413772 | BC7: =+BB7*(1+O7) -> 0.041625463 | BD7: =+BC7*(1+P7) -> 0.042582849 | BE7: =+BD7*(1+Q7) -> 0.044286163 | BF7: =+BE7*(1+R7) -> 0.046500471 | BG7: =+BF7*(1+S7)+BF7*(1+S7)/I7 -> 1.2392376 | BI7: 0.43 | BJ7: =IF($D$25="Base",BK7,IF(D$25="High",BL7,IF(D$25="Low",BM7,"ERR"))) -> 0.0575 | BK7: 0.0575 | BL7: 0.06 | BM7: 0.055 | BN7: 0.01 | BO7: 0.0125 | BQ7: =RANK(AE7,AE$3:AE$21) -> 3 | BR7: =+$A7 -> 5 | BS7: 0.15 | BT7: 0.3 | BX7: =RANK(AF7,AF$3:AF$21) -> 9 | BY7: =+$A7 -> 5 | BZ7: 0.2 | CA7: 0.3 | CF7: =IF($D$25="Base",CG7,IF($D$25="High",CH7,IF($D$25="Low",CI7,"ERR"))) -> 0.025 | CG7: 0.025 | CH7: 0.0275 | CI7: 0.0225 | CJ7: =+$F$30+CF7 -> 0.065 | CK7: =$I$30+CF7 -> 0.065 | CL7: =+NPV(CJ7,CM7:CR7) -> 1.0284597 | CM7: =+BB7 -> 0.0413772 | CN7: =+BC7 -> 0.041625463 | CO7: =+BD7 -> 0.042582849 | CP7: =+BE7 -> 0.044286163 | CQ7: =+BF7 -> 0.046500471 | CR7: =+BG7 -> 1.2392376 | CU7: =Q7 -> 0.04 | CV7: =S7 -> 0.025 | CX7: =CJ7-CU7 -> 0.025 | CY7: =+CK7-CV7 -> 0.04 | DA7: =+CX7/(1-$E7) -> 0.029726516 | DB7: =+CY7/(1-$E7) -> 0.047562426
A8: =+A7+1 -> 6 | B8: US | C8: Core-Plus - Ind | D8: 0.045 | E8: 0.138 | F8: =+D8*(1-E8) -> 0.03879 | H8: =CX8 -> 0.035 | I8: =CY8 -> 0.045 | K8: =+H8/(1-$E8) -> 0.040603248 | L8: =+I8/(1-$E8) -> 0.052204176 | N8: =+AH8+(D$29-D$34) -> 0.066 | O8: =+AI8+(E$29-E$34) -> 0.059 | P8: =+AJ8+(F$29-F$34) -> 0.05 | Q8: =+AK8+(G$29-G$34) -> 0.035 | R8: =+AL8+(H$29-H$34) -> 0.03 | S8: =+AM8+(I$29-I$34) -> 0.025 | T8: {=+PRODUCT(1+N8:P8)^(0.333333333333333)-1} -> 0.058313058 | U8: {=+PRODUCT(1+N8:S8)^(1/6)-1} -> 0.044056458 | V8: =+IRR(AV8:AY8) -> 0.13513617 | W8: =+IRR(BA8:BG8) -> 0.062603802 | Y8: =+(V8-BI8*BJ8)/(1-BI8) -> 0.14473165 | Z8: =+(W8-BI8*BJ8)/(1-BI8) -> 0.063234609 | AB8: =V8+$BN8 -> 0.14263617 | AC8: =Z8+$BN8 -> 0.070734609 | AE8: =AB8-$BO8 -> 0.13013617 | AF8: =AC8-$BO8 -> 0.058234609 | AH8: 0.066 | AI8: 0.059 | AJ8: 0.05 | AK8: 0.035 | AL8: 0.03 | AM8: 0.025 | AN8: {=+PRODUCT(1+AH8:AJ8)^(0.333333333333333)-1} -> 0.058313058 | AO8: {=+PRODUCT(1+AH8:AM8)^(1/6)-1} -> 0.044056458 | AQ8: -0.003158 | AR8: 0 | AT8: 0.0175 | AV8: =-1 -> -1 | AW8: =+F8*(1+N8) -> 0.04135014 | AX8: =+AW8*(1+O8) -> 0.043789798 | AY8: =+AX8*(1+P8)+(AX8*(1+P8))/H8 -> 1.3596732 | BA8: =+BA7 -> -1 | BB8: =+F8*(1+N8) -> 0.04135014 | BC8: =+BB8*(1+O8) -> 0.043789798 | BD8: =+BC8*(1+P8) -> 0.045979288 | BE8: =+BD8*(1+Q8) -> 0.047588563 | BF8: =+BE8*(1+R8) -> 0.04901622 | BG8: =+BF8*(1+S8)+BF8*(1+S8)/I8 -> 1.1667222 | BI8: 0.11 | BJ8: =IF($D$25="Base",BK8,IF(D$25="High",BL8,IF(D$25="Low",BM8,"ERR"))) -> 0.0575 | BK8: 0.0575 | BL8: 0.06 | BM8: 0.055 | BN8: 0.0075 | BO8: 0.0125 | BQ8: =RANK(AE8,AE$3:AE$21) -> 10 | BR8: =+$A8 -> 6 | BS8: 0.15 | BT8: 0.3 | BX8: =RANK(AF8,AF$3:AF$21) -> 14 | BY8: =+$A8 -> 6 | BZ8: 0.2 | CA8: 0.3 | CF8: =IF($D$25="Base",CG8,IF($D$25="High",CH8,IF($D$25="Low",CI8,"ERR"))) -> 0.03 | CG8: 0.03 | CH8: 0.0325 | CI8: 0.0275 | CJ8: =+$F$30+CF8 -> 0.07 | CK8: =$I$30+CF8 -> 0.07 | CL8: =+NPV(CJ8,CM8:CR8) -> 0.96311473 | CM8: =+BB8 -> 0.04135014 | CN8: =+BC8 -> 0.043789798 | CO8: =+BD8 -> 0.045979288 | CP8: =+BE8 -> 0.047588563 | CQ8: =+BF8 -> 0.04901622 | CR8: =+BG8 -> 1.1667222 | CU8: =Q8 -> 0.035 | CV8: =S8 -> 0.025 | CX8: =CJ8-CU8 -> 0.035 | CY8: =+CK8-CV8 -> 0.045 | DA8: =+CX8/(1-$E8) -> 0.040603248 | DB8: =+CY8/(1-$E8) -> 0.052204176
A9: =+A8+1 -> 7 | B9: US | C9: Core-Plus - Off | D9: 0.085 | E9: 0.294 | F9: =+D9*(1-E9) -> 0.06001 | H9: =CX9 -> 0.07 | I9: =CY9 -> 0.055 | K9: =+H9/(1-$E9) -> 0.099150142 | L9: =+I9/(1-$E9) -> 0.077903683 | N9: =+AH9+(D$29-D$34) -> -0.014 | O9: =+AI9+(E$29-E$34) -> -0.007 | P9: =+AJ9+(F$29-F$34) -> -0.003 | Q9: =+AK9+(G$29-G$34) -> 0.005 | R9: =+AL9+(H$29-H$34) -> 0.01 | S9: =+AM9+(I$29-I$34) -> 0.02 | T9: {=+PRODUCT(1+N9:P9)^(0.333333333333333)-1} -> -0.0080104269 | U9: {=+PRODUCT(1+N9:S9)^(1/6)-1} -> 0.001770307 | V9: =+IRR(AV9:AY9) -> 0.0047073123 | W9: =+IRR(BA9:BG9) -> 0.073431187 | Y9: =+(V9-BI9*BJ9)/(1-BI9) -> -0.020684289 | Z9: =+(W9-BI9*BJ9)/(1-BI9) -> 0.074765537 | AB9: =V9+$BN9 -> 0.0047073123 | AC9: =Z9+$BN9 -> 0.074765537 | AE9: =AB9-$BO9 -> -0.0077926877 | AF9: =AC9-$BO9 -> 0.062265537 | AH9: -0.014 | AI9: -0.007 | AJ9: -0.003 | AK9: 0.005 | AL9: 0.01 | AM9: 0.02 | AN9: {=+PRODUCT(1+AH9:AJ9)^(0.333333333333333)-1} -> -0.0080104269 | AO9: {=+PRODUCT(1+AH9:AM9)^(1/6)-1} -> 0.001770307 | AQ9: 0.008124 | AR9: 0.008124 | AT9: 0.035 | AV9: =-1 -> -1 | AW9: =+F9*(1+N9) -> 0.05916986 | AX9: =+AW9*(1+O9) -> 0.058755671 | AY9: =+AX9*(1+P9)+(AX9*(1+P9))/H9 -> 0.89542803 | BA9: =+BA8 -> -1 | BB9: =+F9*(1+N9) -> 0.05916986 | BC9: =+BB9*(1+O9) -> 0.058755671 | BD9: =+BC9*(1+P9) -> 0.058579404 | BE9: =+BD9*(1+Q9) -> 0.058872301 | BF9: =+BE9*(1+R9) -> 0.059461024 | BG9: =+BF9*(1+S9)+BF9*(1+S9)/I9 -> 1.163382 | BI9: 0.28 | BJ9: =IF($D$25="Base",BK9,IF(D$25="High",BL9,IF(D$25="Low",BM9,"ERR"))) -> 0.07 | BK9: 0.07 | BL9: 0.0725 | BM9: 0.0675 | BN9: 0 | BO9: 0.0125 | BQ9: =RANK(AE9,AE$3:AE$21) -> 18 | BR9: =+$A9 -> 7 | BS9: 0.05 | BT9: 0.15 | BX9: =RANK(AF9,AF$3:AF$21) -> 12 | BY9: =+$A9 -> 7 | BZ9: 0.05 | CA9: 0.15 | CF9: =IF($D$25="Base",CG9,IF($D$25="High",CH9,IF($D$25="Low",CI9,"ERR"))) -> 0.035 | CG9: 0.035 | CH9: 0.0375 | CI9: 0.0325 | CJ9: =+$F$30+CF9 -> 0.075 | CK9: =$I$30+CF9 -> 0.075 | CL9: =+NPV(CJ9,CM9:CR9) -> 0.99236748 | CM9: =+BB9 -> 0.05916986 | CN9: =+BC9 -> 0.058755671 | CO9: =+BD9 -> 0.058579404 | CP9: =+BE9 -> 0.058872301 | CQ9: =+BF9 -> 0.059461024 | CR9: =+BG9 -> 1.163382 | CU9: =Q9 -> 0.005 | CV9: =S9 -> 0.02 | CX9: =CJ9-CU9 -> 0.07 | CY9: =+CK9-CV9 -> 0.055 | DA9: =+CX9/(1-$E9) -> 0.099150142 | DB9: =+CY9/(1-$E9) -> 0.077903683
A10: =+A9+1 -> 8 | B10: US | C10: Core-Plus - Ret | D10: 0.06 | E10: 0.188 | F10: =+D10*(1-E10) -> 0.04872 | H10: =CX10 -> 0.05 | I10: =CY10 -> 0.045 | K10: =+H10/(1-$E10) -> 0.061576355 | L10: =+I10/(1-$E10) -> 0.055418719 | N10: =+AH10+(D$29-D$34) -> 0.01 | O10: =+AI10+(E$29-E$34) -> 0.02 | P10: =+AJ10+(F$29-F$34) -> 0.02 | Q10: =+AK10+(G$29-G$34) -> 0.02 | R10: =+AL10+(H$29-H$34) -> 0.02 | S10: =+AM10+(I$29-I$34) -> 0.025 | T10: {=+PRODUCT(1+N10:P10)^(0.333333333333333)-1} -> 0.016655714 | U10: {=+PRODUCT(1+N10:S10)^(1/6)-1} -> 0.019156756 | V10: =+IRR(AV10:AY10) -> 0.057686114 | W10: =+IRR(BA10:BG10) -> 0.080564252 | Y10: =+(V10-BI10*BJ10)/(1-BI10) -> 0.055634177 | Z10: =+(W10-BI10*BJ10)/(1-BI10) -> 0.098800476 | AB10: =V10+$BN10 -> 0.060186114 | AC10: =Z10+$BN10 -> 0.10130048 | AE10: =AB10-$BO10 -> 0.047686114 | AF10: =AC10-$BO10 -> 0.088800476 | AH10: 0.01 | AI10: 0.02 | AJ10: 0.02 | AK10: 0.02 | AL10: 0.02 | AM10: 0.025 | AN10: {=+PRODUCT(1+AH10:AJ10)^(0.333333333333333)-1} -> 0.016655714 | AO10: {=+PRODUCT(1+AH10:AM10)^(1/6)-1} -> 0.019156756 | AQ10: 0.007908 | AR10: 0.007908 | AT10: 0.025 | AV10: =-1 -> -1 | AW10: =+F10*(1+N10) -> 0.0492072 | AX10: =+AW10*(1+O10) -> 0.050191344 | AY10: =+AX10*(1+P10)+(AX10*(1+P10))/H10 -> 1.0750986 | BA10: =+BA9 -> -1 | BB10: =+F10*(1+N10) -> 0.0492072 | BC10: =+BB10*(1+O10) -> 0.050191344 | BD10: =+BC10*(1+P10) -> 0.051195171 | BE10: =+BD10*(1+Q10) -> 0.052219074 | BF10: =+BE10*(1+R10) -> 0.053263456 | BG10: =+BF10*(1+S10)+BF10*(1+S10)/I10 -> 1.2678182 | BI10: 0.47 | BJ10: =IF($D$25="Base",BK10,IF(D$25="High",BL10,IF(D$25="Low",BM10,"ERR"))) -> 0.06 | BK10: 0.06 | BL10: 0.0625 | BM10: 0.0575 | BN10: 0.0025 | BO10: 0.0125 | BQ10: =RANK(AE10,AE$3:AE$21) -> 15 | BR10: =+$A10 -> 8 | BS10: 0.05 | BT10: 0.15 | BX10: =RANK(AF10,AF$3:AF$21) -> 5 | BY10: =+$A10 -> 8 | BZ10: 0.05 | CA10: 0.15 | CF10: =IF($D$25="Base",CG10,IF($D$25="High",CH10,IF($D$25="Low",CI10,"ERR"))) -> 0.03 | CG10: 0.03 | CH10: 0.0325 | CI10: 0.0275 | CJ10: =+$F$30+CF10 -> 0.07 | CK10: =$I$30+CF10 -> 0.07 | CL10: =+NPV(CJ10,CM10:CR10) -> 1.0542322 | CM10: =+BB10 -> 0.0492072 | CN10: =+BC10 -> 0.050191344 | CO10: =+BD10 -> 0.051195171 | CP10: =+BE10 -> 0.052219074 | CQ10: =+BF10 -> 0.053263456 | CR10: =+BG10 -> 1.2678182 | CU10: =Q10 -> 0.02 | CV10: =S10 -> 0.025 | CX10: =CJ10-CU10 -> 0.05 | CY10: =+CK10-CV10 -> 0.045 | DA10: =+CX10/(1-$E10) -> 0.061576355 | DB10: =+CY10/(1-$E10) -> 0.055418719
A11: =+A10+1 -> 9 | B11: US | C11: Data Center | D11: 0.06 | E11: 0.191 | F11: =+D11*(1-E11) -> 0.04854 | H11: =CX11 -> 0.025 | I11: =CY11 -> 0.045 | K11: =+H11/(1-$E11) -> 0.030902349 | L11: =+I11/(1-$E11) -> 0.055624227 | N11: =+AH11+(D$29-D$34) -> 0.059 | O11: =+AI11+(E$29-E$34) -> 0.059 | P11: =+AJ11+(F$29-F$34) -> 0.051 | Q11: =+AK11+(G$29-G$34) -> 0.05 | R11: =+AL11+(H$29-H$34) -> 0.04 | S11: =+AM11+(I$29-I$34) -> 0.03 | T11: {=+PRODUCT(1+N11:P11)^(0.333333333333333)-1} -> 0.05632659 | U11: {=+PRODUCT(1+N11:S11)^(1/6)-1} -> 0.048115354 | V11: =+IRR(AV11:AY11) -> 0.35988528 | W11: =+IRR(BA11:BG11) -> 0.111638 | Y11: =+(V11-BI11*BJ11)/(1-BI11) -> 0.50882132 | Z11: =+(W11-BI11*BJ11)/(1-BI11) -> 0.13830298 | AB11: =V11+$BN11 -> 0.36988528 | AC11: =Z11+$BN11 -> 0.14830298 | AE11: =AB11-$BO11 -> 0.35738528 | AF11: =AC11-$BO11 -> 0.13580298 | AH11: 0.059 | AI11: 0.059 | AJ11: 0.051 | AK11: 0.05 | AL11: 0.04 | AM11: 0.03 | AN11: {=+PRODUCT(1+AH11:AJ11)^(0.333333333333333)-1} -> 0.05632659 | AO11: {=+PRODUCT(1+AH11:AM11)^(1/6)-1} -> 0.048115354 | AQ11: 0.003686 | AR11: 0.003686 | AT11: 0.015 | AV11: =-1 -> -1 | AW11: =+F11*(1+N11) -> 0.05140386 | AX11: =+AW11*(1+O11) -> 0.054436688 | AY11: =+AX11*(1+P11)+(AX11*(1+P11))/H11 -> 2.3457313 | BA11: =+BA10 -> -1 | BB11: =+F11*(1+N11) -> 0.05140386 | BC11: =+BB11*(1+O11) -> 0.054436688 | BD11: =+BC11*(1+P11) -> 0.057212959 | BE11: =+BD11*(1+Q11) -> 0.060073607 | BF11: =+BE11*(1+R11) -> 0.062476551 | BG11: =+BF11*(1+S11)+BF11*(1+S11)/I11 -> 1.4943697 | BI11: 0.33 | BJ11: =IF($D$25="Base",BK11,IF(D$25="High",BL11,IF(D$25="Low",BM11,"ERR"))) -> 0.0575 | BK11: 0.0575 | BL11: 0.06 | BM11: 0.055 | BN11: 0.01 | BO11: 0.0125 | BQ11: =RANK(AE11,AE$3:AE$21) -> 1 | BR11: =+$A11 -> 9 | BS11: 0.05 | BT11: 0.15 | BX11: =RANK(AF11,AF$3:AF$21) -> 2 | BY11: =+$A11 -> 9 | BZ11: 0.05 | CA11: 0.15 | CF11: =IF($D$25="Base",CG11,IF($D$25="High",CH11,IF($D$25="Low",CI11,"ERR"))) -> 0.035 | CG11: 0.035 | CH11: 0.0375 | CI11: 0.0325 | CJ11: 0.075 | CK11: =$I$30+CF11 -> 0.075 | CL11: =+NPV(CJ11,CM11:CR11) -> 1.1977733 | CM11: =+BB11 -> 0.05140386 | CN11: =+BC11 -> 0.054436688 | CO11: =+BD11 -> 0.057212959 | CP11: =+BE11 -> 0.060073607 | CQ11: =+BF11 -> 0.062476551 | CR11: =+BG11 -> 1.4943697 | CU11: =Q11 -> 0.05 | CV11: =S11 -> 0.03 | CX11: =CJ11-CU11 -> 0.025 | CY11: =+CK11-CV11 -> 0.045 | DA11: =+CX11/(1-$E11) -> 0.030902349 | DB11: =+CY11/(1-$E11) -> 0.055624227
A12: =+A11+1 -> 10 | B12: US | C12: Single-Family Rental | D12: 0.045 | E12: 0.136 | F12: =+D12*(1-E12) -> 0.03888 | H12: =CX12 -> 0.03 | I12: =CY12 -> 0.04 | K12: =+H12/(1-$E12) -> 0.034722222 | L12: =+I12/(1-$E12) -> 0.046296296 | N12: =+AH12+(D$29-D$34) -> 0.048 | O12: =+AI12+(E$29-E$34) -> 0.048 | P12: =+AJ12+(F$29-F$34) -> 0.049 | Q12: =+AK12+(G$29-G$34) -> 0.04 | R12: =+AL12+(H$29-H$34) -> 0.04 | S12: =+AM12+(I$29-I$34) -> 0.03 | T12: {=+PRODUCT(1+N12:P12)^(0.333333333333333)-1} -> 0.048333227 | U12: {=+PRODUCT(1+N12:S12)^(1/6)-1} -> 0.042478226 | V12: =+IRR(AV12:AY12) -> 0.18050361 | W12: =+IRR(BA12:BG12) -> 0.078957886 | Y12: =+(V12-BI12*BJ12)/(1-BI12) -> 0.21519694 | Z12: =+(W12-BI12*BJ12)/(1-BI12) -> 0.08501011 | AB12: =V12+$BN12 -> 0.18800361 | AC12: =Z12+$BN12 -> 0.09251011 | AE12: =AB12-$BO12 -> 0.17550361 | AF12: =AC12-$BO12 -> 0.08001011 | AH12: 0.048 | AI12: 0.048 | AJ12: 0.049 | AK12: 0.04 | AL12: 0.04 | AM12: 0.03 | AN12: {=+PRODUCT(1+AH12:AJ12)^(0.333333333333333)-1} -> 0.048333227 | AO12: {=+PRODUCT(1+AH12:AM12)^(1/6)-1} -> 0.042478226 | AQ12: -0.00362 | AR12: -0.00362 | AT12: 0.015 | AV12: =-1 -> -1 | AW12: =+F12*(1+N12) -> 0.04074624 | AX12: =+AW12*(1+O12) -> 0.04270206 | AY12: =+AX12*(1+P12)+(AX12*(1+P12))/H12 -> 1.5379431 | BA12: =+BA11 -> -1 | BB12: =+F12*(1+N12) -> 0.04074624 | BC12: =+BB12*(1+O12) -> 0.04270206 | BD12: =+BC12*(1+P12) -> 0.04479446 | BE12: =+BD12*(1+Q12) -> 0.046586239 | BF12: =+BE12*(1+R12) -> 0.048449688 | BG12: =+BF12*(1+S12)+BF12*(1+S12)/I12 -> 1.2974827 | BI12: 0.22 | BJ12: =IF($D$25="Base",BK12,IF(D$25="High",BL12,IF(D$25="Low",BM12,"ERR"))) -> 0.0575 | BK12: 0.0575 | BL12: 0.06 | BM12: 0.055 | BN12: 0.0075 | BO12: 0.0125 | BQ12: =RANK(AE12,AE$3:AE$21) -> 7 | BR12: =+$A12 -> 10 | BS12: 0.05 | BT12: 0.15 | BX12: =RANK(AF12,AF$3:AF$21) -> 7 | BY12: =+$A12 -> 10 | BZ12: 0.05 | CA12: 0.15 | CF12: =IF($D$25="Base",CG12,IF($D$25="High",CH12,IF($D$25="Low",CI12,"ERR"))) -> 0.03 | CG12: 0.03 | CH12: 0.0325 | CI12: 0.0275 | CJ12: =+$F$30+CF12 -> 0.07 | CK12: =$I$30+CF12 -> 0.07 | CL12: =+NPV(CJ12,CM12:CR12) -> 1.0465957 | CM12: =+BB12 -> 0.04074624 | CN12: =+BC12 -> 0.04270206 | CO12: =+BD12 -> 0.04479446 | CP12: =+BE12 -> 0.046586239 | CQ12: =+BF12 -> 0.048449688 | CR12: =+BG12 -> 1.2974827 | CU12: =Q12 -> 0.04 | CV12: =S12 -> 0.03 | CX12: =CJ12-CU12 -> 0.03 | CY12: =+CK12-CV12 -> 0.04 | DA12: =+CX12/(1-$E12) -> 0.034722222 | DB12: =+CY12/(1-$E12) -> 0.046296296
A13: =+A12+1 -> 11 | B13: US | C13: Cold Storage | D13: 0.047 | E13: 0.17 | F13: =+D13*(1-E13) -> 0.03901 | H13: =CX13 -> 0.035 | I13: =CY13 -> 0.055 | K13: =+H13/(1-$E13) -> 0.042168675 | L13: =+I13/(1-$E13) -> 0.06626506 | N13: =+AH13+(D$29-D$34) -> 0.1 | O13: =+AI13+(E$29-E$34) -> 0.08 | P13: =+AJ13+(F$29-F$34) -> 0.05 | Q13: =+AK13+(G$29-G$34) -> 0.04 | R13: =+AL13+(H$29-H$34) -> 0.03 | S13: =+AM13+(I$29-I$34) -> 0.02 | T13: {=+PRODUCT(1+N13:P13)^(0.333333333333333)-1} -> 0.076469956 | U13: {=+PRODUCT(1+N13:S13)^(1/6)-1} -> 0.052962115 | V13: =+IRR(AV13:AY13) -> 0.15731596 | W13: =+IRR(BA13:BG13) -> 0.043742501 | Y13: =+(V13-BI13*BJ13)/(1-BI13) -> 0.19058795 | Z13: =+(W13-BI13*BJ13)/(1-BI13) -> 0.039156669 | AB13: =V13+$BN13 -> 0.16231596 | AC13: =Z13+$BN13 -> 0.044156669 | AE13: =AB13-$BO13 -> 0.14981596 | AF13: =AC13-$BO13 -> 0.031656669 | AH13: 0.1 | AI13: 0.08 | AJ13: 0.05 | AK13: 0.04 | AL13: 0.03 | AM13: 0.02 | AN13: {=+PRODUCT(1+AH13:AJ13)^(0.333333333333333)-1} -> 0.076469956 | AO13: {=+PRODUCT(1+AH13:AM13)^(1/6)-1} -> 0.052962115 | AQ13: -0.00846 | AR13: -0.004 | AT13: 0.015 | AV13: =-1 -> -1 | AW13: =+F13*(1+N13) -> 0.042911 | AX13: =+AW13*(1+O13) -> 0.04634388 | AY13: =+AX13*(1+P13)+(AX13*(1+P13))/H13 -> 1.4389775 | BA13: =+BA12 -> -1 | BB13: =+F13*(1+N13) -> 0.042911 | BC13: =+BB13*(1+O13) -> 0.04634388 | BD13: =+BC13*(1+P13) -> 0.048661074 | BE13: =+BD13*(1+Q13) -> 0.050607517 | BF13: =+BE13*(1+R13) -> 0.052125742 | BG13: =+BF13*(1+S13)+BF13*(1+S13)/I13 -> 1.0198638 | BI13: 0.25 | BJ13: =IF($D$25="Base",BK13,IF(D$25="High",BL13,IF(D$25="Low",BM13,"ERR"))) -> 0.0575 | BK13: 0.0575 | BL13: 0.06 | BM13: 0.055 | BN13: 0.005 | BO13: 0.0125 | BQ13: =RANK(AE13,AE$3:AE$21) -> 9 | BR13: =+$A13 -> 11 | BS13: 0.02 | BT13: 0.1 | BX13: =RANK(AF13,AF$3:AF$21) -> 19 | BY13: =+$A13 -> 11 | BZ13: 0.02 | CA13: 0.1 | CF13: =IF($D$25="Base",CG13,IF($D$25="High",CH13,IF($D$25="Low",CI13,"ERR"))) -> 0.035 | CG13: 0.035 | CH13: 0.0375 | CI13: 0.0325 | CJ13: =+$F$30+CF13 -> 0.075 | CK13: =$I$30+CF13 -> 0.075 | CL13: =+NPV(CJ13,CM13:CR13) -> 0.85422642 | CM13: =+BB13 -> 0.042911 | CN13: =+BC13 -> 0.04634388 | CO13: =+BD13 -> 0.048661074 | CP13: =+BE13 -> 0.050607517 | CQ13: =+BF13 -> 0.052125742 | CR13: =+BG13 -> 1.0198638 | CU13: =Q13 -> 0.04 | CV13: =S13 -> 0.02 | CX13: =CJ13-CU13 -> 0.035 | CY13: =+CK13-CV13 -> 0.055 | DA13: =+CX13/(1-$E13) -> 0.042168675 | DB13: =+CY13/(1-$E13) -> 0.06626506
A14: =+A13+1 -> 12 | B14: US | C14: Senior Housing | D14: 0.052 | E14: 0.23 | F14: =+D14*(1-E14) -> 0.04004 | H14: =CX14 -> 0.03 | I14: =CY14 -> 0.04 | K14: =+H14/(1-$E14) -> 0.038961039 | L14: =+I14/(1-$E14) -> 0.051948052 | N14: =+AH14+(D$29-D$34) -> 0.085 | O14: =+AI14+(E$29-E$34) -> 0.061 | P14: =+AJ14+(F$29-F$34) -> 0.051 | Q14: =+AK14+(G$29-G$34) -> 0.04 | R14: =+AL14+(H$29-H$34) -> 0.04 | S14: =+AM14+(I$29-I$34) -> 0.03 | T14: {=+PRODUCT(1+N14:P14)^(0.333333333333333)-1} -> 0.06557154 | U14: {=+PRODUCT(1+N14:S14)^(1/6)-1} -> 0.051014296 | V14: =+IRR(AV14:AY14) -> 0.21260418 | W14: =+IRR(BA14:BG14) -> 0.094467705 | Y14: =+(V14-BI14*BJ14)/(1-BI14) -> 0.29612182 | Z14: =+(W14-BI14*BJ14)/(1-BI14) -> 0.11437339 | AB14: =V14+$BN14 -> 0.21760418 | AC14: =Z14+$BN14 -> 0.11937339 | AE14: =AB14-$BO14 -> 0.20510418 | AF14: =AC14-$BO14 -> 0.10687339 | AH14: 0.085 | AI14: 0.061 | AJ14: 0.051 | AK14: 0.04 | AL14: 0.04 | AM14: 0.03 | AN14: {=+PRODUCT(1+AH14:AJ14)^(0.333333333333333)-1} -> 0.06557154 | AO14: {=+PRODUCT(1+AH14:AM14)^(1/6)-1} -> 0.051014296 | AQ14: 4e-05 | AR14: 4e-05 | AT14: 0.0125 | AV14: =-1 -> -1 | AW14: =+F14*(1+N14) -> 0.0434434 | AX14: =+AW14*(1+O14) -> 0.046093447 | AY14: =+AX14*(1+P14)+(AX14*(1+P14))/H14 -> 1.6632513 | BA14: =+BA13 -> -1 | BB14: =+F14*(1+N14) -> 0.0434434 | BC14: =+BB14*(1+O14) -> 0.046093447 | BD14: =+BC14*(1+P14) -> 0.048444213 | BE14: =+BD14*(1+Q14) -> 0.050381982 | BF14: =+BE14*(1+R14) -> 0.052397261 | BG14: =+BF14*(1+S14)+BF14*(1+S14)/I14 -> 1.4031987 | BI14: 0.35 | BJ14: =IF($D$25="Base",BK14,IF(D$25="High",BL14,IF(D$25="Low",BM14,"ERR"))) -> 0.0575 | BK14: 0.0575 | BL14: 0.06 | BM14: 0.055 | BN14: 0.005 | BO14: 0.0125 | BQ14: =RANK(AE14,AE$3:AE$21) -> 4 | BR14: =+$A14 -> 12 | BS14: 0.02 | BT14: 0.1 | BX14: =RANK(AF14,AF$3:AF$21) -> 4 | BY14: =+$A14 -> 12 | BZ14: 0.02 | CA14: 0.1 | CF14: =IF($D$25="Base",CG14,IF($D$25="High",CH14,IF($D$25="Low",CI14,"ERR"))) -> 0.03 | CG14: 0.03 | CH14: 0.0325 | CI14: 0.0275 | CJ14: =+$F$30+CF14 -> 0.07 | CK14: =$I$30+CF14 -> 0.07 | CL14: =+NPV(CJ14,CM14:CR14) -> 1.1312112 | CM14: =+BB14 -> 0.0434434 | CN14: =+BC14 -> 0.046093447 | CO14: =+BD14 -> 0.048444213 | CP14: =+BE14 -> 0.050381982 | CQ14: =+BF14 -> 0.052397261 | CR14: =+BG14 -> 1.4031987 | CU14: =Q14 -> 0.04 | CV14: =S14 -> 0.03 | CX14: =CJ14-CU14 -> 0.03 | CY14: =+CK14-CV14 -> 0.04 | DA14: =+CX14/(1-$E14) -> 0.038961039 | DB14: =+CY14/(1-$E14) -> 0.051948052
A15: =+A14+1 -> 13 | B15: US | C15: Student Housing | D15: 0.0575 | E15: 0.11 | F15: =+D15*(1-E15) -> 0.051175 | H15: =CX15 -> 0.045 | I15: =CY15 -> 0.05 | K15: =+H15/(1-$E15) -> 0.050561798 | L15: =+I15/(1-$E15) -> 0.056179775 | N15: =+AH15+(D$29-D$34) -> 0.03 | O15: =+AI15+(E$29-E$34) -> 0.03 | P15: =+AJ15+(F$29-F$34) -> 0.03 | Q15: =+AK15+(G$29-G$34) -> 0.025 | R15: =+AL15+(H$29-H$34) -> 0.025 | S15: =+AM15+(I$29-I$34) -> 0.02 | T15: {=+PRODUCT(1+N15:P15)^(0.333333333333333)-1} -> 0.03 | U15: {=+PRODUCT(1+N15:S15)^(1/6)-1} -> 0.026659892 | V15: =+IRR(AV15:AY15) -> 0.12570457 | W15: =+IRR(BA15:BG15) -> 0.083006427 | Y15: =+(V15-BI15*BJ15)/(1-BI15) -> 0.15493511 | Z15: =+(W15-BI15*BJ15)/(1-BI15) -> 0.093937753 | AB15: =V15+$BN15 -> 0.13070457 | AC15: =Z15+$BN15 -> 0.098937753 | AE15: =AB15-$BO15 -> 0.11820457 | AF15: =AC15-$BO15 -> 0.086437753 | AH15: 0.03 | AI15: 0.03 | AJ15: 0.03 | AK15: 0.025 | AL15: 0.025 | AM15: 0.02 | AN15: {=+PRODUCT(1+AH15:AJ15)^(0.333333333333333)-1} -> 0.03 | AO15: {=+PRODUCT(1+AH15:AM15)^(1/6)-1} -> 0.026659892 | AQ15: 0.011175 | AR15: 0.011175 | AT15: 0.015 | AV15: =-1 -> -1 | AW15: =+F15*(1+N15) -> 0.05271025 | AX15: =+AW15*(1+O15) -> 0.054291558 | AY15: =+AX15*(1+P15)+(AX15*(1+P15))/H15 -> 1.2985937 | BA15: =+BA14 -> -1 | BB15: =+F15*(1+N15) -> 0.05271025 | BC15: =+BB15*(1+O15) -> 0.054291558 | BD15: =+BC15*(1+P15) -> 0.055920304 | BE15: =+BD15*(1+Q15) -> 0.057318312 | BF15: =+BE15*(1+R15) -> 0.05875127 | BG15: =+BF15*(1+S15)+BF15*(1+S15)/I15 -> 1.2584522 | BI15: 0.3 | BJ15: =IF($D$25="Base",BK15,IF(D$25="High",BL15,IF(D$25="Low",BM15,"ERR"))) -> 0.0575 | BK15: 0.0575 | BL15: 0.06 | BM15: 0.055 | BN15: 0.005 | BO15: 0.0125 | BQ15: =RANK(AE15,AE$3:AE$21) -> 11 | BR15: =+$A15 -> 13 | BS15: 0.02 | BT15: 0.1 | BX15: =RANK(AF15,AF$3:AF$21) -> 6 | BY15: =+$A15 -> 13 | BZ15: 0.02 | CA15: 0.1 | CF15: =IF($D$25="Base",CG15,IF($D$25="High",CH15,IF($D$25="Low",CI15,"ERR"))) -> 0.03 | CG15: 0.03 | CH15: 0.0325 | CI15: 0.0275 | CJ15: =+$F$30+CF15 -> 0.07 | CK15: =$I$30+CF15 -> 0.07 | CL15: =+NPV(CJ15,CM15:CR15) -> 1.0665064 | CM15: =+BB15 -> 0.05271025 | CN15: =+BC15 -> 0.054291558 | CO15: =+BD15 -> 0.055920304 | CP15: =+BE15 -> 0.057318312 | CQ15: =+BF15 -> 0.05875127 | CR15: =+BG15 -> 1.2584522 | CU15: =Q15 -> 0.025 | CV15: =S15 -> 0.02 | CX15: =CJ15-CU15 -> 0.045 | CY15: =+CK15-CV15 -> 0.05 | DA15: =+CX15/(1-$E15) -> 0.050561798 | DB15: =+CY15/(1-$E15) -> 0.056179775
A16: =+A15+1 -> 14 | B16: US | C16: Affordable Housing | D16: 0.056 | E16: 0.07 | F16: =+D16*(1-E16) -> 0.05208 | H16: =CX16 -> 0.04 | I16: =CY16 -> 0.04 | K16: =+H16/(1-$E16) -> 0.043010753 | L16: =+I16/(1-$E16) -> 0.043010753 | N16: =+AH16+(D$29-D$34) -> 0.03 | O16: =+AI16+(E$29-E$34) -> 0.035 | P16: =+AJ16+(F$29-F$34) -> 0.03 | Q16: =+AK16+(G$29-G$34) -> 0.03 | R16: =+AL16+(H$29-H$34) -> 0.03 | S16: =+AM16+(I$29-I$34) -> 0.03 | T16: {=+PRODUCT(1+N16:P16)^(0.333333333333333)-1} -> 0.031663977 | U16: {=+PRODUCT(1+N16:S16)^(1/6)-1} -> 0.030831653 | V16: =+IRR(AV16:AY16) -> 0.1759799 | W16: =+IRR(BA16:BG16) -> 0.12574668 | Y16: =+(V16-BI16*BJ16)/(1-BI16) -> 0.226757 | Z16: =+(W16-BI16*BJ16)/(1-BI16) -> 0.15499525 | AB16: =V16+$BN16 -> 0.1809799 | AC16: =Z16+$BN16 -> 0.15999525 | AE16: =AB16-$BO16 -> 0.1684799 | AF16: =AC16-$BO16 -> 0.14749525 | AH16: 0.03 | AI16: 0.035 | AJ16: 0.03 | AK16: 0.03 | AL16: 0.03 | AM16: 0.03 | AN16: {=+PRODUCT(1+AH16:AJ16)^(0.333333333333333)-1} -> 0.031663977 | AO16: {=+PRODUCT(1+AH16:AM16)^(1/6)-1} -> 0.030831653 | AQ16: 0.01208 | AR16: 0.01208 | AT16: 0.01 | AV16: =-1 -> -1 | AW16: =+F16*(1+N16) -> 0.0536424 | AX16: =+AW16*(1+O16) -> 0.055519884 | AY16: =+AX16*(1+P16)+(AX16*(1+P16))/H16 -> 1.4868225 | BA16: =+BA15 -> -1 | BB16: =+F16*(1+N16) -> 0.0536424 | BC16: =+BB16*(1+O16) -> 0.055519884 | BD16: =+BC16*(1+P16) -> 0.057185481 | BE16: =+BD16*(1+Q16) -> 0.058901045 | BF16: =+BE16*(1+R16) -> 0.060668076 | BG16: =+BF16*(1+S16)+BF16*(1+S16)/I16 -> 1.6246911 | BI16: 0.3 | BJ16: =IF($D$25="Base",BK16,IF(D$25="High",BL16,IF(D$25="Low",BM16,"ERR"))) -> 0.0575 | BK16: 0.0575 | BL16: 0.06 | BM16: 0.055 | BN16: 0.005 | BO16: 0.0125 | BQ16: =RANK(AE16,AE$3:AE$21) -> 8 | BR16: =+$A16 -> 14 | BS16: 0.01 | BT16: 0.07 | BX16: =RANK(AF16,AF$3:AF$21) -> 1 | BY16: =+$A16 -> 14 | BZ16: 0.01 | CA16: 0.07 | CF16: =IF($D$25="Base",CG16,IF($D$25="High",CH16,IF($D$25="Low",CI16,"ERR"))) -> 0.03 | CG16: 0.03 | CH16: 0.0325 | CI16: 0.0275 | CJ16: =+$F$30+CF16 -> 0.07 | CK16: =$I$30+CF16 -> 0.07 | CL16: =+NPV(CJ16,CM16:CR16) -> 1.3160978 | CM16: =+BB16 -> 0.0536424 | CN16: =+BC16 -> 0.055519884 | CO16: =+BD16 -> 0.057185481 | CP16: =+BE16 -> 0.058901045 | CQ16: =+BF16 -> 0.060668076 | CR16: =+BG16 -> 1.6246911 | CU16: =Q16 -> 0.03 | CV16: =S16 -> 0.03 | CX16: =CJ16-CU16 -> 0.04 | CY16: =+CK16-CV16 -> 0.04 | DA16: =+CX16/(1-$E16) -> 0.043010753 | DB16: =+CY16/(1-$E16) -> 0.043010753
A17: =+A16+1 -> 15 | B17: US | C17: Manufactured Home Park | D17: 0.04 | E17: 0.153 | F17: =+D17*(1-E17) -> 0.03388 | H17: =CX17 -> 0.04 | I17: =CY17 -> 0.04 | K17: =+H17/(1-$E17) -> 0.047225502 | L17: =+I17/(1-$E17) -> 0.047225502 | N17: =+AH17+(D$29-D$34) -> 0.05 | O17: =+AI17+(E$29-E$34) -> 0.05 | P17: =+AJ17+(F$29-F$34) -> 0.04 | Q17: =+AK17+(G$29-G$34) -> 0.03 | R17: =+AL17+(H$29-H$34) -> 0.03 | S17: =+AM17+(I$29-I$34) -> 0.03 | T17: {=+PRODUCT(1+N17:P17)^(0.333333333333333)-1} -> 0.046656028 | U17: {=+PRODUCT(1+N17:S17)^(1/6)-1} -> 0.038294616 | V17: =+IRR(AV17:AY17) -> 0.027880917 | W17: =+IRR(BA17:BG17) -> 0.048100608 | Y17: =+(V17-BI17*BJ17)/(1-BI17) -> 0.016925914 | Z17: =+(W17-BI17*BJ17)/(1-BI17) -> 0.044624121 | AB17: =V17+$BN17 -> 0.032880917 | AC17: =Z17+$BN17 -> 0.049624121 | AE17: =AB17-$BO17 -> 0.020380917 | AF17: =AC17-$BO17 -> 0.037124121 | AH17: 0.05 | AI17: 0.05 | AJ17: 0.04 | AK17: 0.03 | AL17: 0.03 | AM17: 0.03 | AN17: {=+PRODUCT(1+AH17:AJ17)^(0.333333333333333)-1} -> 0.046656028 | AO17: {=+PRODUCT(1+AH17:AM17)^(1/6)-1} -> 0.038294616 | AQ17: -0.00612 | AR17: -0.003 | AT17: 0.0125 | AV17: =-1 -> -1 | AW17: =+F17*(1+N17) -> 0.035574 | AX17: =+AW17*(1+O17) -> 0.0373527 | AY17: =+AX17*(1+P17)+(AX17*(1+P17))/H17 -> 1.010017 | BA17: =+BA16 -> -1 | BB17: =+F17*(1+N17) -> 0.035574 | BC17: =+BB17*(1+O17) -> 0.0373527 | BD17: =+BC17*(1+P17) -> 0.038846808 | BE17: =+BD17*(1+Q17) -> 0.040012212 | BF17: =+BE17*(1+R17) -> 0.041212579 | BG17: =+BF17*(1+S17)+BF17*(1+S17)/I17 -> 1.1036729 | BI17: 0.27 | BJ17: =IF($D$25="Base",BK17,IF(D$25="High",BL17,IF(D$25="Low",BM17,"ERR"))) -> 0.0575 | BK17: 0.0575 | BL17: 0.06 | BM17: 0.055 | BN17: 0.005 | BO17: 0.0125 | BQ17: =RANK(AE17,AE$3:AE$21) -> 17 | BR17: =+$A17 -> 15 | BS17: 0.01 | BT17: 0.07 | BX17: =RANK(AF17,AF$3:AF$21) -> 18 | BY17: =+$A17 -> 15 | BZ17: 0.01 | CA17: 0.07 | CF17: =IF($D$25="Base",CG17,IF($D$25="High",CH17,IF($D$25="Low",CI17,"ERR"))) -> 0.03 | CG17: 0.03 | CH17: 0.0325 | CI17: 0.0275 | CJ17: =+$F$30+CF17 -> 0.07 | CK17: =$I$30+CF17 -> 0.07 | CL17: =+NPV(CJ17,CM17:CR17) -> 0.89291554 | CM17: =+BB17 -> 0.035574 | CN17: =+BC17 -> 0.0373527 | CO17: =+BD17 -> 0.038846808 | CP17: =+BE17 -> 0.040012212 | CQ17: =+BF17 -> 0.041212579 | CR17: =+BG17 -> 1.1036729 | CU17: =Q17 -> 0.03 | CV17: =S17 -> 0.03 | CX17: =CJ17-CU17 -> 0.04 | CY17: =+CK17-CV17 -> 0.04 | DA17: =+CX17/(1-$E17) -> 0.047225502 | DB17: =+CY17/(1-$E17) -> 0.047225502
A18: =+A17+1 -> 16 | B18: US | C18: Medical Office | D18: 0.056 | E18: 0.13 | F18: =+D18*(1-E18) -> 0.04872 | H18: =CX18 -> 0.045 | I18: =CY18 -> 0.048 | K18: =+H18/(1-$E18) -> 0.051724138 | L18: =+I18/(1-$E18) -> 0.055172414 | N18: =+AH18+(D$29-D$34) -> 0.025 | O18: =+AI18+(E$29-E$34) -> 0.025 | P18: =+AJ18+(F$29-F$34) -> 0.025 | Q18: =+AK18+(G$29-G$34) -> 0.025 | R18: =+AL18+(H$29-H$34) -> 0.023 | S18: =+AM18+(I$29-I$34) -> 0.022 | T18: {=+PRODUCT(1+N18:P18)^(0.333333333333333)-1} -> 0.025 | U18: {=+PRODUCT(1+N18:S18)^(1/6)-1} -> 0.024165947 | V18: =+IRR(AV18:AY18) -> 0.10118342 | W18: =+IRR(BA18:BG18) -> 0.076401793 | Y18: =+(V18-BI18*BJ18)/(1-BI18) -> 0.11990488 | Z18: =+(W18-BI18*BJ18)/(1-BI18) -> 0.084502561 | AB18: =V18+$BN18 -> 0.10618342 | AC18: =Z18+$BN18 -> 0.089502561 | AE18: =AB18-$BO18 -> 0.093683418 | AF18: =AC18-$BO18 -> 0.077002561 | AH18: 0.025 | AI18: 0.025 | AJ18: 0.025 | AK18: 0.025 | AL18: 0.023 | AM18: 0.022 | AN18: {=+PRODUCT(1+AH18:AJ18)^(0.333333333333333)-1} -> 0.025 | AO18: {=+PRODUCT(1+AH18:AM18)^(1/6)-1} -> 0.024165947 | AQ18: 0.00872 | AR18: 0.00872 | AT18: 0.015 | AV18: =-1 -> -1 | AW18: =+F18*(1+N18) -> 0.049938 | AX18: =+AW18*(1+O18) -> 0.05118645 | AY18: =+AX18*(1+P18)+(AX18*(1+P18))/H18 -> 1.2183797 | BA18: =+BA17 -> -1 | BB18: =+F18*(1+N18) -> 0.049938 | BC18: =+BB18*(1+O18) -> 0.05118645 | BD18: =+BC18*(1+P18) -> 0.052466111 | BE18: =+BD18*(1+Q18) -> 0.053777764 | BF18: =+BE18*(1+R18) -> 0.055014653 | BG18: =+BF18*(1+S18)+BF18*(1+S18)/I18 -> 1.2275786 | BI18: 0.3 | BJ18: =IF($D$25="Base",BK18,IF(D$25="High",BL18,IF(D$25="Low",BM18,"ERR"))) -> 0.0575 | BK18: 0.0575 | BL18: 0.06 | BM18: 0.055 | BN18: 0.005 | BO18: 0.0125 | BQ18: =RANK(AE18,AE$3:AE$21) -> 12 | BR18: =+$A18 -> 16 | BS18: 0.01 | BT18: 0.07 | BX18: =RANK(AF18,AF$3:AF$21) -> 10 | BY18: =+$A18 -> 16 | BZ18: 0.01 | CA18: 0.07 | CF18: =IF($D$25="Base",CG18,IF($D$25="High",CH18,IF($D$25="Low",CI18,"ERR"))) -> 0.03 | CG18: 0.03 | CH18: 0.0325 | CI18: 0.0275 | CJ18: =+$F$30+CF18 -> 0.07 | CK18: =$I$30+CF18 -> 0.07 | CL18: =+NPV(CJ18,CM18:CR18) -> 1.0324462 | CM18: =+BB18 -> 0.049938 | CN18: =+BC18 -> 0.05118645 | CO18: =+BD18 -> 0.052466111 | CP18: =+BE18 -> 0.053777764 | CQ18: =+BF18 -> 0.055014653 | CR18: =+BG18 -> 1.2275786 | CU18: =Q18 -> 0.025 | CV18: =S18 -> 0.022 | CX18: =CJ18-CU18 -> 0.045 | CY18: =+CK18-CV18 -> 0.048 | DA18: =+CX18/(1-$E18) -> 0.051724138 | DB18: =+CY18/(1-$E18) -> 0.055172414
A19: =+A18+1 -> 17 | B19: US | C19: Life Science | D19: 0.053 | E19: 0.14 | F19: =+D19*(1-E19) -> 0.04558 | H19: =CX19 -> 0.05 | I19: =CY19 -> 0.05 | K19: =+H19/(1-$E19) -> 0.058139535 | L19: =+I19/(1-$E19) -> 0.058139535 | N19: =+AH19+(D$29-D$34) -> 0.039 | O19: =+AI19+(E$29-E$34) -> 0.028 | P19: =+AJ19+(F$29-F$34) -> 0.024 | Q19: =+AK19+(G$29-G$34) -> 0.025 | R19: =+AL19+(H$29-H$34) -> 0.025 | S19: =+AM19+(I$29-I$34) -> 0.025 | T19: {=+PRODUCT(1+N19:P19)^(0.333333333333333)-1} -> 0.030313854 | U19: {=+PRODUCT(1+N19:S19)^(1/6)-1} -> 0.027653492 | V19: =+IRR(AV19:AY19) -> 0.047651536 | W19: =+IRR(BA19:BG19) -> 0.06083708 | Y19: =+(V19-BI19*BJ19)/(1-BI19) -> 0.041569457 | Z19: =+(W19-BI19*BJ19)/(1-BI19) -> 0.061249373 | AB19: =V19+$BN19 -> 0.050151536 | AC19: =Z19+$BN19 -> 0.063749373 | AE19: =AB19-$BO19 -> 0.037651536 | AF19: =AC19-$BO19 -> 0.051249373 | AH19: 0.039 | AI19: 0.028 | AJ19: 0.024 | AK19: 0.025 | AL19: 0.025 | AM19: 0.025 | AN19: {=+PRODUCT(1+AH19:AJ19)^(0.333333333333333)-1} -> 0.030313854 | AO19: {=+PRODUCT(1+AH19:AM19)^(1/6)-1} -> 0.027653492 | AQ19: 0.00558 | AR19: 0.00558 | AT19: 0.025 | AV19: =-1 -> -1 | AW19: =+F19*(1+N19) -> 0.04735762 | AX19: =+AW19*(1+O19) -> 0.048683633 | AY19: =+AX19*(1+P19)+(AX19*(1+P19))/H19 -> 1.0468929 | BA19: =+BA18 -> -1 | BB19: =+F19*(1+N19) -> 0.04735762 | BC19: =+BB19*(1+O19) -> 0.048683633 | BD19: =+BC19*(1+P19) -> 0.049852041 | BE19: =+BD19*(1+Q19) -> 0.051098342 | BF19: =+BE19*(1+R19) -> 0.0523758 | BG19: =+BF19*(1+S19)+BF19*(1+S19)/I19 -> 1.1273891 | BI19: 0.33 | BJ19: =IF($D$25="Base",BK19,IF(D$25="High",BL19,IF(D$25="Low",BM19,"ERR"))) -> 0.06 | BK19: 0.06 | BL19: 0.0625 | BM19: 0.0575 | BN19: 0.0025 | BO19: 0.0125 | BQ19: =RANK(AE19,AE$3:AE$21) -> 16 | BR19: =+$A19 -> 17 | BS19: 0.01 | BT19: 0.07 | BX19: =RANK(AF19,AF$3:AF$21) -> 17 | BY19: =+$A19 -> 17 | BZ19: 0.01 | CA19: 0.07 | CF19: =IF($D$25="Base",CG19,IF($D$25="High",CH19,IF($D$25="Low",CI19,"ERR"))) -> 0.035 | CG19: 0.035 | CH19: 0.0375 | CI19: 0.0325 | CJ19: =+$F$30+CF19 -> 0.075 | CK19: =$I$30+CF19 -> 0.075 | CL19: =+NPV(CJ19,CM19:CR19) -> 0.9315601 | CM19: =+BB19 -> 0.04735762 | CN19: =+BC19 -> 0.048683633 | CO19: =+BD19 -> 0.049852041 | CP19: =+BE19 -> 0.051098342 | CQ19: =+BF19 -> 0.0523758 | CR19: =+BG19 -> 1.1273891 | CU19: =Q19 -> 0.025 | CV19: =S19 -> 0.025 | CX19: =CJ19-CU19 -> 0.05 | CY19: =+CK19-CV19 -> 0.05 | DA19: =+CX19/(1-$E19) -> 0.058139535 | DB19: =+CY19/(1-$E19) -> 0.058139535
A20: =+A19+1 -> 18 | B20: US | C20: Self-Storage | D20: 0.055 | E20: 0.08 | F20: =+D20*(1-E20) -> 0.0506 | H20: =CX20 -> 0.0475 | I20: =CY20 -> 0.0525 | K20: =+H20/(1-$E20) -> 0.051630435 | L20: =+I20/(1-$E20) -> 0.057065217 | N20: =+AH20+(D$29-D$34) -> -0.015 | O20: =+AI20+(E$29-E$34) -> 0.023 | P20: =+AJ20+(F$29-F$34) -> 0.027 | Q20: =+AK20+(G$29-G$34) -> 0.025 | R20: =+AL20+(H$29-H$34) -> 0.02 | S20: =+AM20+(I$29-I$34) -> 0.02 | T20: {=+PRODUCT(1+N20:P20)^(0.333333333333333)-1} -> 0.01148808 | U20: {=+PRODUCT(1+N20:S20)^(1/6)-1} -> 0.016563283 | V20: =+IRR(AV20:AY20) -> 0.082464711 | W20: =+IRR(BA20:BG20) -> 0.061780197 | Y20: =+(V20-BI20*BJ20)/(1-BI20) -> 0.091200988 | Z20: =+(W20-BI20*BJ20)/(1-BI20) -> 0.062472496 | AB20: =V20+$BN20 -> 0.087464711 | AC20: =Z20+$BN20 -> 0.067472496 | AE20: =AB20-$BO20 -> 0.074964711 | AF20: =AC20-$BO20 -> 0.054972496 | AH20: -0.015 | AI20: 0.023 | AJ20: 0.027 | AK20: 0.025 | AL20: 0.02 | AM20: 0.02 | AN20: {=+PRODUCT(1+AH20:AJ20)^(0.333333333333333)-1} -> 0.01148808 | AO20: {=+PRODUCT(1+AH20:AM20)^(1/6)-1} -> 0.016563283 | AQ20: 0.00048 | AR20: 0.00048 | AT20: 0.02 | AV20: =-1 -> -1 | AW20: =+F20*(1+N20) -> 0.049841 | AX20: =+AW20*(1+O20) -> 0.050987343 | AY20: =+AX20*(1+P20)+(AX20*(1+P20))/H20 -> 1.154764 | BA20: =+BA19 -> -1 | BB20: =+F20*(1+N20) -> 0.049841 | BC20: =+BB20*(1+O20) -> 0.050987343 | BD20: =+BC20*(1+P20) -> 0.052364001 | BE20: =+BD20*(1+Q20) -> 0.053673101 | BF20: =+BE20*(1+R20) -> 0.054746563 | BG20: =+BF20*(1+S20)+BF20*(1+S20)/I20 -> 1.119489 | BI20: 0.28 | BJ20: =IF($D$25="Base",BK20,IF(D$25="High",BL20,IF(D$25="Low",BM20,"ERR"))) -> 0.06 | BK20: 0.06 | BL20: 0.0625 | BM20: 0.0575 | BN20: 0.005 | BO20: 0.0125 | BQ20: =RANK(AE20,AE$3:AE$21) -> 13 | BR20: =+$A20 -> 18 | BS20: 0.01 | BT20: 0.07 | BX20: =RANK(AF20,AF$3:AF$21) -> 16 | BY20: =+$A20 -> 18 | BZ20: 0.01 | CA20: 0.07 | CF20: =IF($D$25="Base",CG20,IF($D$25="High",CH20,IF($D$25="Low",CI20,"ERR"))) -> 0.0325 | CG20: 0.0325 | CH20: 0.035 | CI20: 0.03 | CJ20: =+$F$30+CF20 -> 0.0725 | CK20: =$I$30+CF20 -> 0.0725 | CL20: =+NPV(CJ20,CM20:CR20) -> 0.94798272 | CM20: =+BB20 -> 0.049841 | CN20: =+BC20 -> 0.050987343 | CO20: =+BD20 -> 0.052364001 | CP20: =+BE20 -> 0.053673101 | CQ20: =+BF20 -> 0.054746563 | CR20: =+BG20 -> 1.119489 | CU20: =Q20 -> 0.025 | CV20: =S20 -> 0.02 | CX20: =CJ20-CU20 -> 0.0475 | CY20: =+CK20-CV20 -> 0.0525 | DA20: =+CX20/(1-$E20) -> 0.051630435 | DB20: =+CY20/(1-$E20) -> 0.057065217
A21: =+A20+1 -> 19 | B21: US | C21: IOS | D21: 0.06 | E21: 0.07 | F21: =+D21*(1-E21) -> 0.0558 | H21: =CX21 -> 0.035 | I21: =CY21 -> 0.055 | K21: =+H21/(1-$E21) -> 0.037634409 | L21: =+I21/(1-$E21) -> 0.059139785 | N21: =+AH21+(D$29-D$34) -> 0.07 | O21: =+AI21+(E$29-E$34) -> 0.06 | P21: =+AJ21+(F$29-F$34) -> 0.05 | Q21: =+AK21+(G$29-G$34) -> 0.04 | R21: =+AL21+(H$29-H$34) -> 0.03 | S21: =+AM21+(I$29-I$34) -> 0.02 | T21: {=+PRODUCT(1+N21:P21)^(0.333333333333333)-1} -> 0.059968553 | U21: {=+PRODUCT(1+N21:S21)^(1/6)-1} -> 0.044860424 | V21: =+IRR(AV21:AY21) -> 0.28987712 | W21: =+IRR(BA21:BG21) -> 0.10704615 | Y21: =+(V21-BI21*BJ21)/(1-BI21) -> 0.36650283 | Z21: =+(W21-BI21*BJ21)/(1-BI21) -> 0.1227282 | AB21: =V21+$BN21 -> 0.29737712 | AC21: =Z21+$BN21 -> 0.1302282 | AE21: =AB21-$BO21 -> 0.28487712 | AF21: =AC21-$BO21 -> 0.1177282 | AH21: 0.07 | AI21: 0.06 | AJ21: 0.05 | AK21: 0.04 | AL21: 0.03 | AM21: 0.02 | AN21: {=+PRODUCT(1+AH21:AJ21)^(0.333333333333333)-1} -> 0.059968553 | AO21: {=+PRODUCT(1+AH21:AM21)^(1/6)-1} -> 0.044860424 | AQ21: -0.00559 | AR21: -0.003 | AT21: 0.0175 | AV21: =-1 -> -1 | AW21: =+F21*(1+N21) -> 0.059706 | AX21: =+AW21*(1+O21) -> 0.06328836 | AY21: =+AX21*(1+P21)+(AX21*(1+P21))/H21 -> 1.9651036 | BA21: =+BA20 -> -1 | BB21: =+F21*(1+N21) -> 0.059706 | BC21: =+BB21*(1+O21) -> 0.06328836 | BD21: =+BC21*(1+P21) -> 0.066452778 | BE21: =+BD21*(1+Q21) -> 0.069110889 | BF21: =+BE21*(1+R21) -> 0.071184216 | BG21: =+BF21*(1+S21)+BF21*(1+S21)/I21 -> 1.3927515 | BI21: 0.25 | BJ21: =IF($D$25="Base",BK21,IF(D$25="High",BL21,IF(D$25="Low",BM21,"ERR"))) -> 0.06 | BK21: 0.06 | BL21: 0.0625 | BM21: 0.0575 | BN21: 0.0075 | BO21: 0.0125 | BQ21: =RANK(AE21,AE$3:AE$21) -> 2 | BR21: =+$A21 -> 19 | BS21: 0.01 | BT21: 0.07 | BX21: =RANK(AF21,AF$3:AF$21) -> 3 | BY21: =+$A21 -> 19 | BZ21: 0.01 | CA21: 0.07 | CF21: =IF($D$25="Base",CG21,IF($D$25="High",CH21,IF($D$25="Low",CI21,"ERR"))) -> 0.035 | CG21: 0.035 | CH21: 0.0375 | CI21: 0.0325 | CJ21: =+$F$30+CF21 -> 0.075 | CK21: =$I$30+CF21 -> 0.075 | CL21: =+NPV(CJ21,CM21:CR21) -> 1.1675815 | CM21: =+BB21 -> 0.059706 | CN21: =+BC21 -> 0.06328836 | CO21: =+BD21 -> 0.066452778 | CP21: =+BE21 -> 0.069110889 | CQ21: =+BF21 -> 0.071184216 | CR21: =+BG21 -> 1.3927515 | CU21: =Q21 -> 0.04 | CV21: =S21 -> 0.02 | CX21: =CJ21-CU21 -> 0.035 | CY21: =+CK21-CV21 -> 0.055 | DA21: =+CX21/(1-$E21) -> 0.037634409 | DB21: =+CY21/(1-$E21) -> 0.059139785
B23: US | C23: Inflation | T23: {=+PRODUCT(1+D29:F29)^(0.333333333333333)-1} -> 0.022497963 | U23: {=+PRODUCT(1+D29:I29)^(1/6)-1} -> 0.021248218 | AH23: Rent Growth under base macro case | AQ23: Cap rate relative to 10 yr | BS23: =+SUM(BS3:BS21) -> 0.62 | BT23: =+SUM(BT3:BT21) -> 2.82 | BU23: 1 | BV23: =+SUM(BV3:BV21) -> 0 | BZ23: =+SUM(BZ3:BZ21) -> 0.72 | CA23: =+SUM(CA3:CA21) -> 2.82
C25: Scenario | D25: Base | F25: Scenarios | G25: Base | H25: High | I25: Low | AH25: 0.03 | AI25: 0.03 | AJ25: 0.03 | AK25: 0.03 | AL25: 0.03 | AM25: 0.03
AH26: 0.025 | AI26: 0.0225 | AJ26: 0.02 | AK26: 0.02 | AL26: 0.02 | AM26: 0.02
C27: Model Inputs | AH27: 0.01 | AI27: 0.01 | AJ27: 0.01 | AK27: 0.01 | AL27: 0.01 | AM27: 0.01
C28: GDP Growth
C29: Inflation | D29: =IF($D$25=$G$25,D35,IF($D$25=$H$25,D41,IF($D$25=$I$25,D47,"ERR"))) -> 0.025 | E29: =IF($D$25=$G$25,E35,IF($D$25=$H$25,E41,IF($D$25=$I$25,E47,"ERR"))) -> 0.0225 | F29: =IF($D$25=$G$25,F35,IF($D$25=$H$25,F41,IF($D$25=$I$25,F47,"ERR"))) -> 0.02 | G29: =IF($D$25=$G$25,G35,IF($D$25=$H$25,G41,IF($D$25=$I$25,G47,"ERR"))) -> 0.02 | H29: =IF($D$25=$G$25,H35,IF($D$25=$H$25,H41,IF($D$25=$I$25,H47,"ERR"))) -> 0.02 | I29: =IF($D$25=$G$25,I35,IF($D$25=$H$25,I41,IF($D$25=$I$25,I47,"ERR"))) -> 0.02 | AH29: =+D29 -> 0.025 | AI29: =+E29 -> 0.0225 | AJ29: =+F29 -> 0.02 | AK29: =+G29 -> 0.02 | AL29: =+H29 -> 0.02 | AM29: =+I29 -> 0.02
C30: 10 Year | D30: =IF($D$25=$G$25,D36,IF($D$25=$H$25,D42,IF($D$25=$I$25,D48,"ERR"))) -> 0.045 | E30: =IF($D$25=$G$25,E36,IF($D$25=$H$25,E42,IF($D$25=$I$25,E48,"ERR"))) -> 0.04 | F30: =IF($D$25=$G$25,F36,IF($D$25=$H$25,F42,IF($D$25=$I$25,F48,"ERR"))) -> 0.04 | G30: =IF($D$25=$G$25,G36,IF($D$25=$H$25,G42,IF($D$25=$I$25,G48,"ERR"))) -> 0.04 | H30: =IF($D$25=$G$25,H36,IF($D$25=$H$25,H42,IF($D$25=$I$25,H48,"ERR"))) -> 0.04 | I30: =IF($D$25=$G$25,I36,IF($D$25=$H$25,I42,IF($D$25=$I$25,I48,"ERR"))) -> 0.04
F32: =IF($D$25=$G$25,F37,IF($D$25=$H$25,F43,IF($D$25=$I$25,F49,"ERR"))) -> 0 | I32: =IF($D$25=$G$25,I37,IF($D$25=$H$25,I43,IF($D$25=$I$25,I49,"ERR"))) -> 0
C33: Base case
C34: GDP | D34: 0.025 | E34: 0.0225 | F34: 0.02 | G34: 0.02 | H34: 0.02 | I34: 0.02 | N34: 0.02
C35: Inflation baseline | D35: 0.025 | E35: 0.0225 | F35: 0.02 | G35: 0.02 | H35: 0.02 | I35: 0.02 | N35: 0.02
C36: 10 Year baseline | D36: =+E35+E34 -> 0.045 | E36: =+F35+F34 -> 0.04 | F36: =+G35+G34 -> 0.04 | G36: =+H35+H34 -> 0.04 | H36: =+I35+I34 -> 0.04 | I36: =+N35+N34 -> 0.04
C37: Cap rate adj to Treasury | F37: 0 | I37: 0
C39: High Interest Rate
C40: GDP | D40: 0.025 | E40: 0.0225 | F40: 0.02 | G40: 0.02 | H40: 0.02 | I40: 0.02 | N40: 0.02
C41: Inflation baseline | D41: 0.03 | E41: 0.03 | F41: 0.03 | G41: 0.03 | H41: 0.03 | I41: 0.03 | N41: 0.03
C42: 10 Year baseline | D42: =+E41+E40 -> 0.0525 | E42: =+F41+F40 -> 0.05 | F42: =+G41+G40 -> 0.05 | G42: =+H41+H40 -> 0.05 | H42: =+I41+I40 -> 0.05 | I42: =+N41+N40 -> 0.05
C43: Cap rate adj to Treasury | F43: -0.0025 | I43: -0.0025
C45: Low Interest Rate
C46: GDP | D46: 0.025 | E46: 0.0225 | F46: 0.02 | G46: 0.02 | H46: 0.02 | I46: 0.02 | N46: 0.02
C47: Inflation baseline | D47: 0.01 | E47: 0.01 | F47: 0.01 | G47: 0.01 | H47: 0.01 | I47: 0.01 | N47: 0.01
C48: 10 Year baseline | D48: =+E47+E46 -> 0.0325 | E48: =+F47+F46 -> 0.03 | F48: =+G47+G46 -> 0.03 | G48: =+H47+H46 -> 0.03 | H48: =+I47+I46 -> 0.03 | I48: =+N47+N46 -> 0.03
C49: Cap rate adj to Treasury | F49: 0.0025 | I49: 0.0025

Sheet CoreFunds
A1: SectorIdentifier | B1: Region | C1: Profile | D1: Fund1 | E1: Fund2 | F1: Fund3 | G1: Fund4 | H1: Fund5 | I1: Fund6 | J1: Fund7 | K1: Fund8 | L1: Fund9 | M1: Fund10 | N1: Fund11 | O1: Fund12 | P1: Fund13 | Q1: Fund14 | R1: Fund15 | S1: Fund16 | T1: Fund17 | U1: Fund18 | V1: Fund19 | W1: Fund20
A2: 1 | B2: US | C2: Core - Res | D2: 0.28 | E2: 0.4 | U2: 0.8 | V2: 0.4 | Y2: 0.1684007 | Z2: 0.17 | AA2: =+SUMPRODUCT(D2:W2,$D$25:$W$25) -> 0.17 | AB2: =tmp!L2 -> 0.17
A3: =+A2+1 -> 2 | B3: US | C3: Core - Ind | D3: 0.4 | E3: 0.28 | V3: 0.2 | Y3: 0.059329918 | Z3: 0.089489355 | AA3: =+SUMPRODUCT(D3:W3,$D$25:$W$25) -> 0.072 | AB3: =tmp!L3 -> 0.089489355
A4: =+A3+1 -> 3 | B4: US | C4: Core - Off | D4: 0.15 | E4: 0.1 | V4: 0.05 | Y4: 0.066221816 | Z4: 3.7160686e-18 | AA4: =+SUMPRODUCT(D4:W4,$D$25:$W$25) -> 0.0255 | AB4: =tmp!L4 -> 3.7160686e-18
A5: =+A4+1 -> 4 | B5: US | C5: Core - Retail | D5: 0.17 | E5: 0.22 | V5: 0.05 | Y5: 0.044816642 | Z5: 1.0249305e-17 | AA5: =+SUMPRODUCT(D5:W5,$D$25:$W$25) -> 0.0285 | AB5: =tmp!L5 -> 1.0249305e-17
A6: =+A5+1 -> 5 | B6: US | C6: Core-Plus - Res | F6: 1 | L6: 0.5 | M6: 0.5 | R6: 0.5 | U6: 0.2 | Y6: 0.17845266 | Z6: 0.17 | AA6: =+SUMPRODUCT(D6:W6,$D$25:$W$25) -> 0.166 | AB6: =tmp!L6 -> 0.17
A7: =+A6+1 -> 6 | B7: US | C7: Core-Plus - Ind | G7: 1 | P7: 0.5 | T7: 0.25 | W7: 0.3 | Y7: 0 | Z7: 0.1 | AA7: =+SUMPRODUCT(D7:W7,$D$25:$W$25) -> 0.1 | AB7: =tmp!L7 -> 0.1
A8: =+A7+1 -> 7 | B8: US | C8: Core-Plus - Off | Y8: 0 | Z8: 0.02 | AA8: =+SUMPRODUCT(D8:W8,$D$25:$W$25) -> 0 | AB8: =tmp!L8 -> 0.02
A9: =+A8+1 -> 8 | B9: US | C9: Core-Plus - Ret | Y9: 0.038549347 | Z9: 0.03 | AA9: =+SUMPRODUCT(D9:W9,$D$25:$W$25) -> 0 | AB9: =tmp!L9 -> 0.03
A10: =+A9+1 -> 9 | B10: US | C10: Data Center | H10: 1 | Y10: 0.078199066 | Z10: 0.07 | AA10: =+SUMPRODUCT(D10:W10,$D$25:$W$25) -> 0.07 | AB10: =tmp!L10 -> 0.07
A11: =+A10+1 -> 10 | B11: US | C11: Single-Family Rental | I11: 1 | R11: 0.25 | W11: 0.2 | Y11: 0.10868706 | Z11: 0.1 | AA11: =+SUMPRODUCT(D11:W11,$D$25:$W$25) -> 0.1 | AB11: =tmp!L11 -> 0.1
A12: =+A11+1 -> 11 | B12: US | C12: Cold Storage | J12: 1 | W12: 0.2 | Y12: 0.058530189 | Z12: 0.049999997 | AA12: =+SUMPRODUCT(D12:W12,$D$25:$W$25) -> 0.05 | AB12: =tmp!L12 -> 0.049999997
A13: =+A12+1 -> 12 | B13: US | C13: Senior Housing | K13: 0.5 | N13: 0.25 | Q13: 0.2 | Y13: 0.058530189 | Z13: 0.05 | AA13: =+SUMPRODUCT(D13:W13,$D$25:$W$25) -> 0.05 | AB13: =tmp!L13 -> 0.05
A14: =+A13+1 -> 13 | B14: US | C14: Student Housing | K14: 0.5 | N14: 0.25 | O14: 0.25 | Q14: 0.4 | Y14: 0.022408321 | Z14: 0.049999349 | AA14: =+SUMPRODUCT(D14:W14,$D$25:$W$25) -> 0.05 | AB14: =tmp!L14 -> 0.049999349
A15: =+A14+1 -> 14 | B15: US | C15: Affordable Housing | L15: 0.5 | M15: 0.25 | R15: 0.25 | Y15: 0.022408321 | Z15: 0.05 | AA15: =+SUMPRODUCT(D15:W15,$D$25:$W$25) -> 0.05 | AB15: =tmp!L15 -> 0.05
A16: =+A15+1 -> 15 | B16: US | C16: Manufactured Home Park | M16: 0.25 | Y16: 0.037802603 | Z16: 0.05 | AA16: =+SUMPRODUCT(D16:W16,$D$25:$W$25) -> 0.05 | AB16: =tmp!L16 -> 0.05
A17: =+A16+1 -> 16 | B17: US | C17: Medical Office | N17: 0.25 | S17: 0.55 | V17: 0.1 | Y17: 0.033707835 | Z17: 1.2525386e-17 | AA17: =+SUMPRODUCT(D17:W17,$D$25:$W$25) -> 0.006 | AB17: =tmp!L17 -> 1.2525386e-17
A18: =+A17+1 -> 17 | B18: US | C18: Life Science | N18: 0.25 | O18: 0.25 | S18: 0.45 | V18: 0.1 | Y18: 0.015281375 | Z18: 3.130171e-17 | AA18: =+SUMPRODUCT(D18:W18,$D$25:$W$25) -> 0.006 | AB18: =tmp!L18 -> 3.130171e-17
A19: =+A18+1 -> 18 | B19: US | C19: Self-Storage | O19: 0.5 | Q19: 0.4 | V19: 0.1 | W19: 0.2 | Y19: 0.0086739562 | Z19: 6.7611686e-18 | AA19: =+SUMPRODUCT(D19:W19,$D$25:$W$25) -> 0.006 | AB19: =tmp!L19 -> 6.7611686e-18
A20: =+A19+1 -> 19 | B20: US | C20: IOS | P20: 0.5 | T20: 0.75 | W20: 0.1 | Y20: 0 | Z20: 2.01688e-17 | AA20: =+SUMPRODUCT(D20:W20,$D$25:$W$25) -> 0 | AB20: =tmp!L20 -> 2.01688e-17
D22: =SUM(D2:D20) -> 1 | E22: =SUM(E2:E20) -> 1 | F22: =SUM(F2:F20) -> 1 | G22: =SUM(G2:G20) -> 1 | H22: =SUM(H2:H20) -> 1 | I22: =SUM(I2:I20) -> 1 | J22: =SUM(J2:J20) -> 1 | K22: =SUM(K2:K20) -> 1 | ... W22: =SUM(W2:W20) -> 1 | Y22: =SUM(Y2:Y20) -> 1 | Z22: =SUM(Z2:Z20) -> 0.9994887 | AA22: =SUM(AA2:AA20) -> 1 | AB22: =SUM(AB2:AB20) -> 0.9994887
D25: 0.15 | E25: 0 | F25: 0.04 | G25: 0.1 | H25: 0.07 | I25: 0.1 | J25: 0.05 | K25: 0.1 | L25: 0 | M25: 0.2 | N25: 0 | O25: 0 | P25: 0 | Q25: 0 | R25: 0 | S25: 0 | T25: 0 | U25: 0.13 | V25: 0.06 | W25: 0
C31: 0.014 | D31: 0.24810831 | E31: 0 | F31: 5.4481159e-18 | G31: 0.17271816 | H31: 0.038549347 | I31: 0.078199066 | J31: 0.10868706 | K31: 0.11706038 | L31: 1.8892223e-17 | M31: 0.089633285 | N31: 5.3139459e-17 | O31: 0 | P31: 0.0085295332 | Q31: 0 | R31: 0 | S31: 0.040947688 | T31: 0.0058789194 | U31: 0 | V31: 0.091688249 | W31: 0
D32: 0.15 | E32: 0 | F32: 0.04 | G32: 0.1 | H32: 0.07 | I32: 0.1 | J32: 0.05 | K32: 0.1 | L32: 0 | M32: 0.2 | N32: 0 | O32: 0 | P32: 0 | Q32: 0 | R32: 0 | S32: 0 | T32: 0 | U32: 0.13 | V32: 0.06 | W32: 0
A34: Worksheet | B34: Rating1 | D34: =IF(AND((D53>=$D71),(D55>=$D73),(D58>=$D76),(D59>=$D77),(D60>=$D78),(D61>=$D79),(D62>=$D80)),1,0) -> 0 | E34: =IF(AND((E53>=$D71),(E55>=$D73),(E58>=$D76),(E59>=$D77),(E60>=$D78),(E61>=$D79),(E62>=$D80)),1,0) -> 0 | F34: =IF(AND((F53>=$D71),(F55>=$D73),(F58>=$D76),(F59>=$D77),(F60>=$D78),(F61>=$D79),(F62>=$D80)),1,0) -> 0 | G34: =IF(AND((G53>=$D71),(G55>=$D73),(G58>=$D76),(G59>=$D77),(G60>=$D78),(G61>=$D79),(G62>=$D80)),1,0) -> 0 | H34: =IF(AND((H53>=$D71),(H55>=$D73),(H58>=$D76),(H59>=$D77),(H60>=$D78),(H61>=$D79),(H62>=$D80)),1,0) -> 0 | I34: =IF(AND((I53>=$D71),(I55>=$D73),(I58>=$D76),(I59>=$D77),(I60>=$D78),(I61>=$D79),(I62>=$D80)),1,0) -> 0 | J34: =IF(AND((J53>=$D71),(J55>=$D73),(J58>=$D76),(J59>=$D77),(J60>=$D78),(J61>=$D79),(J62>=$D80)),1,0) -> 0 | K34: =IF(AND((K53>=$D71),(K55>=$D73),(K58>=$D76),(K59>=$D77),(K60>=$D78),(K61>=$D79),(K62>=$D80)),1,0) -> 0 | ... W34: =IF(AND((W53>=$D71),(W55>=$D73),(W58>=$D76),(W59>=$D77),(W60>=$D78),(W61>=$D79),(W62>=$D80)),1,0) -> 0
B35: Rating2 | D35: =IF(AND((D53>=$E71),(D55>=$E73),(D58>=$E76),(D59>=$E77),(D60>=$E78),(D61>=$E79),(D62>=$E80)),1,0) -> 0 | E35: =IF(AND((E53>=$E71),(E55>=$E73),(E58>=$E76),(E59>=$E77),(E60>=$E78),(E61>=$E79),(E62>=$E80)),1,0) -> 0 | F35: =IF(AND((F53>=$E71),(F55>=$E73),(F58>=$E76),(F59>=$E77),(F60>=$E78),(F61>=$E79),(F62>=$E80)),1,0) -> 0 | G35: =IF(AND((G53>=$E71),(G55>=$E73),(G58>=$E76),(G59>=$E77),(G60>=$E78),(G61>=$E79),(G62>=$E80)),1,0) -> 0 | H35: =IF(AND((H53>=$E71),(H55>=$E73),(H58>=$E76),(H59>=$E77),(H60>=$E78),(H61>=$E79),(H62>=$E80)),1,0) -> 1 | I35: =IF(AND((I53>=$E71),(I55>=$E73),(I58>=$E76),(I59>=$E77),(I60>=$E78),(I61>=$E79),(I62>=$E80)),1,0) -> 1 | J35: =IF(AND((J53>=$E71),(J55>=$E73),(J58>=$E76),(J59>=$E77),(J60>=$E78),(J61>=$E79),(J62>=$E80)),1,0) -> 0 | K35: =IF(AND((K53>=$E71),(K55>=$E73),(K58>=$E76),(K59>=$E77),(K60>=$E78),(K61>=$E79),(K62>=$E80)),1,0) -> 0 | ... W35: =IF(AND((W53>=$E71),(W55>=$E73),(W58>=$E76),(W59>=$E77),(W60>=$E78),(W61>=$E79),(W62>=$E80)),1,0) -> 0
B36: Rating3 | D36: =IF(AND((D53>=$F71),(D55>=$F73),(D58>=$F76),(D59>=$F77),(D60>=$F78),(D61>=$F79),(D62>=$F80)),1,0) -> 1 | E36: =IF(AND((E53>=$F71),(E55>=$F73),(E58>=$F76),(E59>=$F77),(E60>=$F78),(E61>=$F79),(E62>=$F80)),1,0) -> 1 | F36: =IF(AND((F53>=$F71),(F55>=$F73),(F58>=$F76),(F59>=$F77),(F60>=$F78),(F61>=$F79),(F62>=$F80)),1,0) -> 0 | G36: =IF(AND((G53>=$F71),(G55>=$F73),(G58>=$F76),(G59>=$F77),(G60>=$F78),(G61>=$F79),(G62>=$F80)),1,0) -> 1 | H36: =IF(AND((H53>=$F71),(H55>=$F73),(H58>=$F76),(H59>=$F77),(H60>=$F78),(H61>=$F79),(H62>=$F80)),1,0) -> 1 | I36: =IF(AND((I53>=$F71),(I55>=$F73),(I58>=$F76),(I59>=$F77),(I60>=$F78),(I61>=$F79),(I62>=$F80)),1,0) -> 1 | J36: =IF(AND((J53>=$F71),(J55>=$F73),(J58>=$F76),(J59>=$F77),(J60>=$F78),(J61>=$F79),(J62>=$F80)),1,0) -> 1 | K36: =IF(AND((K53>=$F71),(K55>=$F73),(K58>=$F76),(K59>=$F77),(K60>=$F78),(K61>=$F79),(K62>=$F80)),1,0) -> 0 | ... W36: =IF(AND((W53>=$F71),(W55>=$F73),(W58>=$F76),(W59>=$F77),(W60>=$F78),(W61>=$F79),(W62>=$F80)),1,0) -> 1
B37: Rating4 | D37: =IF(AND((D53>=$G71),(D55>=$G73),(D58>=$G76),(D59>=$G77),(D60>=$G78),(D61>=$G79),(D62>=$G80)),1,0) -> 1 | E37: =IF(AND((E53>=$G71),(E55>=$G73),(E58>=$G76),(E59>=$G77),(E60>=$G78),(E61>=$G79),(E62>=$G80)),1,0) -> 1 | F37: =IF(AND((F53>=$G71),(F55>=$G73),(F58>=$G76),(F59>=$G77),(F60>=$G78),(F61>=$G79),(F62>=$G80)),1,0) -> 1 | G37: =IF(AND((G53>=$G71),(G55>=$G73),(G58>=$G76),(G59>=$G77),(G60>=$G78),(G61>=$G79),(G62>=$G80)),1,0) -> 1 | H37: =IF(AND((H53>=$G71),(H55>=$G73),(H58>=$G76),(H59>=$G77),(H60>=$G78),(H61>=$G79),(H62>=$G80)),1,0) -> 1 | I37: =IF(AND((I53>=$G71),(I55>=$G73),(I58>=$G76),(I59>=$G77),(I60>=$G78),(I61>=$G79),(I62>=$G80)),1,0) -> 1 | J37: =IF(AND((J53>=$G71),(J55>=$G73),(J58>=$G76),(J59>=$G77),(J60>=$G78),(J61>=$G79),(J62>=$G80)),1,0) -> 0 | K37: =IF(AND((K53>=$G71),(K55>=$G73),(K58>=$G76),(K59>=$G77),(K60>=$G78),(K61>=$G79),(K62>=$G80)),1,0) -> 1 | ... W37: =IF(AND((W53>=$G71),(W55>=$G73),(W58>=$G76),(W59>=$G77),(W60>=$G78),(W61>=$G79),(W62>=$G80)),1,0) -> 1
B38: Rating5 | D38: =+IF(SUM(D34:D37)=0,1,0) -> 0 | E38: =+IF(SUM(E34:E37)=0,1,0) -> 0 | F38: =+IF(SUM(F34:F37)=0,1,0) -> 0 | G38: =+IF(SUM(G34:G37)=0,1,0) -> 0 | H38: =+IF(SUM(H34:H37)=0,1,0) -> 0 | I38: =+IF(SUM(I34:I37)=0,1,0) -> 0 | J38: =+IF(SUM(J34:J37)=0,1,0) -> 0 | K38: =+IF(SUM(K34:K37)=0,1,0) -> 0 | ... W38: =+IF(SUM(W34:W37)=0,1,0) -> 0
A40: Final | B40: Rating1 | D40: =+D34 -> 0 | E40: =+E34 -> 0 | F40: =+F34 -> 0 | G40: =+G34 -> 0 | H40: =+H34 -> 0 | I40: =+I34 -> 0 | J40: =+J34 -> 0 | K40: =+K34 -> 0 | ... W40: =+W34 -> 0 | Y40: =COUNTIF(D40:W40,1) -> 1
B41: Rating2 | D41: =IF(SUM(D40)>0,0,D35) -> 0 | E41: =IF(SUM(E40)>0,0,E35) -> 0 | F41: =IF(SUM(F40)>0,0,F35) -> 0 | G41: =IF(SUM(G40)>0,0,G35) -> 0 | H41: =IF(SUM(H40)>0,0,H35) -> 1 | I41: =IF(SUM(I40)>0,0,I35) -> 1 | J41: =IF(SUM(J40)>0,0,J35) -> 0 | K41: =IF(SUM(K40)>0,0,K35) -> 0 | ... W41: =IF(SUM(W40)>0,0,W35) -> 0 | Y41: =COUNTIF(D41:W41,1) -> 3
B42: Rating3 | D42: =IF(SUM(D40:D41)>0,0,D36) -> 1 | E42: =IF(SUM(E40:E41)>0,0,E36) -> 1 | F42: =IF(SUM(F40:F41)>0,0,F36) -> 0 | G42: =IF(SUM(G40:G41)>0,0,G36) -> 1 | H42: =IF(SUM(H40:H41)>0,0,H36) -> 0 | I42: =IF(SUM(I40:I41)>0,0,I36) -> 0 | J42: =IF(SUM(J40:J41)>0,0,J36) -> 1 | K42: =IF(SUM(K40:K41)>0,0,K36) -> 0 | ... W42: =IF(SUM(W40:W41)>0,0,W36) -> 1 | Y42: =COUNTIF(D42:W42,1) -> 8
B43: Rating4 | D43: =IF(SUM(D40:D42)>0,0,D37) -> 0 | E43: =IF(SUM(E40:E42)>0,0,E37) -> 0 | F43: =IF(SUM(F40:F42)>0,0,F37) -> 1 | G43: =IF(SUM(G40:G42)>0,0,G37) -> 0 | H43: =IF(SUM(H40:H42)>0,0,H37) -> 0 | I43: =IF(SUM(I40:I42)>0,0,I37) -> 0 | J43: =IF(SUM(J40:J42)>0,0,J37) -> 0 | K43: =IF(SUM(K40:K42)>0,0,K37) -> 1 | ... W43: =IF(SUM(W40:W42)>0,0,W37) -> 0 | Y43: =COUNTIF(D43:W43,1) -> 7
B44: Rating5 | D44: =+IF(SUM(D40:D43)=0,1,0) -> 0 | E44: =+IF(SUM(E40:E43)=0,1,0) -> 0 | F44: =+IF(SUM(F40:F43)=0,1,0) -> 0 | G44: =+IF(SUM(G40:G43)=0,1,0) -> 0 | H44: =+IF(SUM(H40:H43)=0,1,0) -> 0 | I44: =+IF(SUM(I40:I43)=0,1,0) -> 0 | J44: =+IF(SUM(J40:J43)=0,1,0) -> 0 | K44: =+IF(SUM(K40:K43)=0,1,0) -> 0 | ... W44: =+IF(SUM(W40:W43)=0,1,0) -> 0 | Y44: =COUNTIF(D44:W44,1) -> 1
B46: Rating | D46: =IF(D40=1,1,IF(D41=1,2,IF(D42=1,3,IF(D43=1,4,5)))) -> 3 | E46: =IF(E40=1,1,IF(E41=1,2,IF(E42=1,3,IF(E43=1,4,5)))) -> 3 | F46: =IF(F40=1,1,IF(F41=1,2,IF(F42=1,3,IF(F43=1,4,5)))) -> 4 | G46: =IF(G40=1,1,IF(G41=1,2,IF(G42=1,3,IF(G43=1,4,5)))) -> 3 | H46: =IF(H40=1,1,IF(H41=1,2,IF(H42=1,3,IF(H43=1,4,5)))) -> 2 | I46: =IF(I40=1,1,IF(I41=1,2,IF(I42=1,3,IF(I43=1,4,5)))) -> 2 | J46: =IF(J40=1,1,IF(J41=1,2,IF(J42=1,3,IF(J43=1,4,5)))) -> 3 | K46: =IF(K40=1,1,IF(K41=1,2,IF(K42=1,3,IF(K43=1,4,5)))) -> 4 | ... W46: =IF(W40=1,1,IF(W41=1,2,IF(W42=1,3,IF(W43=1,4,5)))) -> 3
A48: Return | B48: Exp Ret 3 YR | C48: N | D48: =SUMPRODUCT(D2:D20,Base!$AI3:$AI21) -> 0.1310242 | E48: =SUMPRODUCT(E2:E20,Base!$AI3:$AI21) -> 0.15074639 | F48: =SUMPRODUCT(F2:F20,Base!$AI3:$AI21) -> 0.26802966 | G48: =SUMPRODUCT(G2:G20,Base!$AI3:$AI21) -> 0.13945853 | H48: =SUMPRODUCT(H2:H20,Base!$AI3:$AI21) -> 0.38329056 | I48: =SUMPRODUCT(I2:I20,Base!$AI3:$AI21) -> 0.22370484 | J48: =SUMPRODUCT(J2:J20,Base!$AI3:$AI21) -> 0.12203342 | K48: =SUMPRODUCT(K2:K20,Base!$AI3:$AI21) -> 0.22060602 | ... W48: =SUMPRODUCT(W2:W20,Base!$AI3:$AI21) -> 0.12547586
A49: Return | B49: Exp Ret 6 YR | C49: N | D49: =SUMPRODUCT(D2:D20,Base!$AJ3:$AJ21) -> 0.062251916 | E49: =SUMPRODUCT(E2:E20,Base!$AJ3:$AJ21) -> 0.068824545 | F49: =SUMPRODUCT(F2:F20,Base!$AJ3:$AJ21) -> 0.10449423 | G49: =SUMPRODUCT(G2:G20,Base!$AJ3:$AJ21) -> 0.060107893 | H49: =SUMPRODUCT(H2:H20,Base!$AJ3:$AJ21) -> 0.14494086 | I49: =SUMPRODUCT(I2:I20,Base!$AJ3:$AJ21) -> 0.10597116 | J49: =SUMPRODUCT(J2:J20,Base!$AJ3:$AJ21) -> 0.0081525848 | K49: =SUMPRODUCT(K2:K20,Base!$AJ3:$AJ21) -> 0.1339034 | ... W49: =SUMPRODUCT(W2:W20,Base!$AJ3:$AJ21) -> 0.043225187
A50: Return | B50: Std Dev | C50: N | D50: =SUMPRODUCT(D2:D20,Base!$AX3:$AX21) -> 0.0167 | E50: =SUMPRODUCT(E2:E20,Base!$AX3:$AX21) -> 0.0156 | F50: =SUMPRODUCT(F2:F20,Base!$AX3:$AX21) -> 0.0125 | G50: =SUMPRODUCT(G2:G20,Base!$AX3:$AX21) -> 0.0175 | H50: =SUMPRODUCT(H2:H20,Base!$AX3:$AX21) -> 0.015 | I50: =SUMPRODUCT(I2:I20,Base!$AX3:$AX21) -> 0.015 | J50: =SUMPRODUCT(J2:J20,Base!$AX3:$AX21) -> 0.015 | K50: =SUMPRODUCT(K2:K20,Base!$AX3:$AX21) -> 0.01375 | ... W50: =SUMPRODUCT(W2:W20,Base!$AX3:$AX21) -> 0.017
A51: Return | B51: Sharp Ratio 3 YR | C51: N | D51: =D48/D$50 -> 7.8457608 | E51: =E48/E$50 -> 9.6632302 | F51: =F48/F$50 -> 21.442373 | G51: =G48/G$50 -> 7.969059 | H51: =H48/H$50 -> 25.552704 | I51: =I48/I$50 -> 14.913656 | J51: =J48/J$50 -> 8.1355614 | K51: =K48/K$50 -> 16.044074 | ... W51: =W48/W$50 -> 7.3809329
A52: Return | B52: Sharp Ratio 5 YR | C52: N | D52: =D49/D$50 -> 3.7276596 | E52: =E49/E$50 -> 4.4118298 | F52: =F49/F$50 -> 8.3595386 | G52: =G49/G$50 -> 3.4347367 | H52: =H49/H$50 -> 9.6627242 | I52: =I49/I$50 -> 7.0647438 | J52: =J49/J$50 -> 0.54350566 | K52: =K49/K$50 -> 9.7384288 | ... W52: =W49/W$50 -> 2.5426581
A53: Return | B53: Exp Ret 3 YR Quart | C53: Q | D53: =IF(D48<=_xlfn.QUARTILE.EXC($D48:$W48,1),1,IF(D48<=_xlfn.QUARTILE.EXC($D48:$W48,2),2,IF(D48<=_xlfn.QUARTILE.EXC($D48:$W48,3),3,4))) -> 2 | E53: =IF(E48<=_xlfn.QUARTILE.EXC($D48:$W48,1),1,IF(E48<=_xlfn.QUARTILE.EXC($D48:$W48,2),2,IF(E48<=_xlfn.QUARTILE.EXC($D48:$W48,3),3,4))) -> 2 | F53: =IF(F48<=_xlfn.QUARTILE.EXC($D48:$W48,1),1,IF(F48<=_xlfn.QUARTILE.EXC($D48:$W48,2),2,IF(F48<=_xlfn.QUARTILE.EXC($D48:$W48,3),3,4))) -> 4 | G53: =IF(G48<=_xlfn.QUARTILE.EXC($D48:$W48,1),1,IF(G48<=_xlfn.QUARTILE.EXC($D48:$W48,2),2,IF(G48<=_xlfn.QUARTILE.EXC($D48:$W48,3),3,4))) -> 2 | H53: =IF(H48<=_xlfn.QUARTILE.EXC($D48:$W48,1),1,IF(H48<=_xlfn.QUARTILE.EXC($D48:$W48,2),2,IF(H48<=_xlfn.QUARTILE.EXC($D48:$W48,3),3,4))) -> 4 | I53: =IF(I48<=_xlfn.QUARTILE.EXC($D48:$W48,1),1,IF(I48<=_xlfn.QUARTILE.EXC($D48:$W48,2),2,IF(I48<=_xlfn.QUARTILE.EXC($D48:$W48,3),3,4))) -> 3 | J53: =IF(J48<=_xlfn.QUARTILE.EXC($D48:$W48,1),1,IF(J48<=_xlfn.QUARTILE.EXC($D48:$W48,2),2,IF(J48<=_xlfn.QUARTILE.EXC($D48:$W48,3),3,4))) -> 1 | K53: =IF(K48<=_xlfn.QUARTILE.EXC($D48:$W48,1),1,IF(K48<=_xlfn.QUARTILE.EXC($D48:$W48,2),2,IF(K48<=_xlfn.QUARTILE.EXC($D48:$W48,3),3,4))) -> 3 | ... W53: =IF(W48<=_xlfn.QUARTILE.EXC($D48:$W48,1),1,IF(W48<=_xlfn.QUARTILE.EXC($D48:$W48,2),2,IF(W48<=_xlfn.QUARTILE.EXC($D48:$W48,3),3,4))) -> 2
A54: Return | B54: Exp Ret 6 YR Quart | C54: Q | D54: =IF(D49<=_xlfn.QUARTILE.EXC($D49:$W49,1),1,IF(D49<=_xlfn.QUARTILE.EXC($D49:$W49,2),2,IF(D49<=_xlfn.QUARTILE.EXC($D49:$W49,3),3,4))) -> 2 | E54: =IF(E49<=_xlfn.QUARTILE.EXC($D49:$W49,1),1,IF(E49<=_xlfn.QUARTILE.EXC($D49:$W49,2),2,IF(E49<=_xlfn.QUARTILE.EXC($D49:$W49,3),3,4))) -> 2 | F54: =IF(F49<=_xlfn.QUARTILE.EXC($D49:$W49,1),1,IF(F49<=_xlfn.QUARTILE.EXC($D49:$W49,2),2,IF(F49<=_xlfn.QUARTILE.EXC($D49:$W49,3),3,4))) -> 3 | G54: =IF(G49<=_xlfn.QUARTILE.EXC($D49:$W49,1),1,IF(G49<=_xlfn.QUARTILE.EXC($D49:$W49,2),2,IF(G49<=_xlfn.QUARTILE.EXC($D49:$W49,3),3,4))) -> 2 | H54: =IF(H49<=_xlfn.QUARTILE.EXC($D49:$W49,1),1,IF(H49<=_xlfn.QUARTILE.EXC($D49:$W49,2),2,IF(H49<=_xlfn.QUARTILE.EXC($D49:$W49,3),3,4))) -> 4 | I54: =IF(I49<=_xlfn.QUARTILE.EXC($D49:$W49,1),1,IF(I49<=_xlfn.QUARTILE.EXC($D49:$W49,2),2,IF(I49<=_xlfn.QUARTILE.EXC($D49:$W49,3),3,4))) -> 3 | J54: =IF(J49<=_xlfn.QUARTILE.EXC($D49:$W49,1),1,IF(J49<=_xlfn.QUARTILE.EXC($D49:$W49,2),2,IF(J49<=_xlfn.QUARTILE.EXC($D49:$W49,3),3,4))) -> 1 | K54: =IF(K49<=_xlfn.QUARTILE.EXC($D49:$W49,1),1,IF(K49<=_xlfn.QUARTILE.EXC($D49:$W49,2),2,IF(K49<=_xlfn.QUARTILE.EXC($D49:$W49,3),3,4))) -> 4 | ... W54: =IF(W49<=_xlfn.QUARTILE.EXC($D49:$W49,1),1,IF(W49<=_xlfn.QUARTILE.EXC($D49:$W49,2),2,IF(W49<=_xlfn.QUARTILE.EXC($D49:$W49,3),3,4))) -> 1
A55: Volatility | B55: Std Dev Quart | C55: Q | D55: =IF(D50<=_xlfn.QUARTILE.EXC($D50:$W50,1),1,IF(D50<=_xlfn.QUARTILE.EXC($D50:$W50,2),2,IF(D50<=_xlfn.QUARTILE.EXC($D50:$W50,3),3,4))) -> 3 | E55: =IF(E50<=_xlfn.QUARTILE.EXC($D50:$W50,1),1,IF(E50<=_xlfn.QUARTILE.EXC($D50:$W50,2),2,IF(E50<=_xlfn.QUARTILE.EXC($D50:$W50,3),3,4))) -> 3 | F55: =IF(F50<=_xlfn.QUARTILE.EXC($D50:$W50,1),1,IF(F50<=_xlfn.QUARTILE.EXC($D50:$W50,2),2,IF(F50<=_xlfn.QUARTILE.EXC($D50:$W50,3),3,4))) -> 1 | G55: =IF(G50<=_xlfn.QUARTILE.EXC($D50:$W50,1),1,IF(G50<=_xlfn.QUARTILE.EXC($D50:$W50,2),2,IF(G50<=_xlfn.QUARTILE.EXC($D50:$W50,3),3,4))) -> 4 | H55: =IF(H50<=_xlfn.QUARTILE.EXC($D50:$W50,1),1,IF(H50<=_xlfn.QUARTILE.EXC($D50:$W50,2),2,IF(H50<=_xlfn.QUARTILE.EXC($D50:$W50,3),3,4))) -> 2 | I55: =IF(I50<=_xlfn.QUARTILE.EXC($D50:$W50,1),1,IF(I50<=_xlfn.QUARTILE.EXC($D50:$W50,2),2,IF(I50<=_xlfn.QUARTILE.EXC($D50:$W50,3),3,4))) -> 2 | J55: =IF(J50<=_xlfn.QUARTILE.EXC($D50:$W50,1),1,IF(J50<=_xlfn.QUARTILE.EXC($D50:$W50,2),2,IF(J50<=_xlfn.QUARTILE.EXC($D50:$W50,3),3,4))) -> 2 | K55: =IF(K50<=_xlfn.QUARTILE.EXC($D50:$W50,1),1,IF(K50<=_xlfn.QUARTILE.EXC($D50:$W50,2),2,IF(K50<=_xlfn.QUARTILE.EXC($D50:$W50,3),3,4))) -> 2 | ... W55: =IF(W50<=_xlfn.QUARTILE.EXC($D50:$W50,1),1,IF(W50<=_xlfn.QUARTILE.EXC($D50:$W50,2),2,IF(W50<=_xlfn.QUARTILE.EXC($D50:$W50,3),3,4))) -> 3
A56: Volatility | B56: Sharp Ratio 3 YR Quart | C56: Q | D56: =IF(D51<=_xlfn.QUARTILE.EXC($D51:$W51,1),1,IF(D51<=_xlfn.QUARTILE.EXC($D51:$W51,2),2,IF(D51<=_xlfn.QUARTILE.EXC($D51:$W51,3),3,4))) -> 2 | E56: =IF(E51<=_xlfn.QUARTILE.EXC($D51:$W51,1),1,IF(E51<=_xlfn.QUARTILE.EXC($D51:$W51,2),2,IF(E51<=_xlfn.QUARTILE.EXC($D51:$W51,3),3,4))) -> 2 | F56: =IF(F51<=_xlfn.QUARTILE.EXC($D51:$W51,1),1,IF(F51<=_xlfn.QUARTILE.EXC($D51:$W51,2),2,IF(F51<=_xlfn.QUARTILE.EXC($D51:$W51,3),3,4))) -> 4 | G56: =IF(G51<=_xlfn.QUARTILE.EXC($D51:$W51,1),1,IF(G51<=_xlfn.QUARTILE.EXC($D51:$W51,2),2,IF(G51<=_xlfn.QUARTILE.EXC($D51:$W51,3),3,4))) -> 2 | H56: =IF(H51<=_xlfn.QUARTILE.EXC($D51:$W51,1),1,IF(H51<=_xlfn.QUARTILE.EXC($D51:$W51,2),2,IF(H51<=_xlfn.QUARTILE.EXC($D51:$W51,3),3,4))) -> 4 | I56: =IF(I51<=_xlfn.QUARTILE.EXC($D51:$W51,1),1,IF(I51<=_xlfn.QUARTILE.EXC($D51:$W51,2),2,IF(I51<=_xlfn.QUARTILE.EXC($D51:$W51,3),3,4))) -> 3 | J56: =IF(J51<=_xlfn.QUARTILE.EXC($D51:$W51,1),1,IF(J51<=_xlfn.QUARTILE.EXC($D51:$W51,2),2,IF(J51<=_xlfn.QUARTILE.EXC($D51:$W51,3),3,4))) -> 2 | K56: =IF(K51<=_xlfn.QUARTILE.EXC($D51:$W51,1),1,IF(K51<=_xlfn.QUARTILE.EXC($D51:$W51,2),2,IF(K51<=_xlfn.QUARTILE.EXC($D51:$W51,3),3,4))) -> 3 | ... W56: =IF(W51<=_xlfn.QUARTILE.EXC($D51:$W51,1),1,IF(W51<=_xlfn.QUARTILE.EXC($D51:$W51,2),2,IF(W51<=_xlfn.QUARTILE.EXC($D51:$W51,3),3,4))) -> 1
A57: Volatility | B57: Sharp Ratio 5 YR Quart | C57: Q | D57: =IF(D52<=_xlfn.QUARTILE.EXC($D52:$W52,1),1,IF(D52<=_xlfn.QUARTILE.EXC($D52:$W52,2),2,IF(D52<=_xlfn.QUARTILE.EXC($D52:$W52,3),3,4))) -> 2 | E57: =IF(E52<=_xlfn.QUARTILE.EXC($D52:$W52,1),1,IF(E52<=_xlfn.QUARTILE.EXC($D52:$W52,2),2,IF(E52<=_xlfn.QUARTILE.EXC($D52:$W52,3),3,4))) -> 2 | F57: =IF(F52<=_xlfn.QUARTILE.EXC($D52:$W52,1),1,IF(F52<=_xlfn.QUARTILE.EXC($D52:$W52,2),2,IF(F52<=_xlfn.QUARTILE.EXC($D52:$W52,3),3,4))) -> 3 | G57: =IF(G52<=_xlfn.QUARTILE.EXC($D52:$W52,1),1,IF(G52<=_xlfn.QUARTILE.EXC($D52:$W52,2),2,IF(G52<=_xlfn.QUARTILE.EXC($D52:$W52,3),3,4))) -> 2 | H57: =IF(H52<=_xlfn.QUARTILE.EXC($D52:$W52,1),1,IF(H52<=_xlfn.QUARTILE.EXC($D52:$W52,2),2,IF(H52<=_xlfn.QUARTILE.EXC($D52:$W52,3),3,4))) -> 4 | I57: =IF(I52<=_xlfn.QUARTILE.EXC($D52:$W52,1),1,IF(I52<=_xlfn.QUARTILE.EXC($D52:$W52,2),2,IF(I52<=_xlfn.QUARTILE.EXC($D52:$W52,3),3,4))) -> 3 | J57: =IF(J52<=_xlfn.QUARTILE.EXC($D52:$W52,1),1,IF(J52<=_xlfn.QUARTILE.EXC($D52:$W52,2),2,IF(J52<=_xlfn.QUARTILE.EXC($D52:$W52,3),3,4))) -> 1 | K57: =IF(K52<=_xlfn.QUARTILE.EXC($D52:$W52,1),1,IF(K52<=_xlfn.QUARTILE.EXC($D52:$W52,2),2,IF(K52<=_xlfn.QUARTILE.EXC($D52:$W52,3),3,4))) -> 4 | ... W57: =IF(W52<=_xlfn.QUARTILE.EXC($D52:$W52,1),1,IF(W52<=_xlfn.QUARTILE.EXC($D52:$W52,2),2,IF(W52<=_xlfn.QUARTILE.EXC($D52:$W52,3),3,4))) -> 1
B58: Platform quality | C58: D4 | D58: 4 | E58: 4 | F58: 3 | G58: 3 | H58: 4 | I58: 4 | J58: 4 | K58: 2 | L58: 2 | M58: 4 | N58: 3 | O58: 3 | P58: 3 | Q58: 4 | R58: 2 | S58: 1 | T58: 3 | U58: 3 | V58: 3 | W58: 4
B59: Fee Structure | C59: D4 | D59: 2 | E59: 2 | F59: 3 | G59: 3 | H59: 4 | I59: 4 | J59: 4 | K59: 3 | L59: 2 | M59: 1 | N59: 4 | O59: 3 | P59: 3 | Q59: 4 | R59: 4 | S59: 3 | T59: 3 | U59: 4 | V59: 3 | W59: 4
B60: Governance Str | C60: D4 | D60: 4 | E60: 4 | F60: 3 | G60: 3 | H60: 4 | I60: 3 | J60: 3 | K60: 3 | L60: 4 | M60: 4 | N60: 4 | O60: 3 | P60: 3 | Q60: 2 | R60: 4 | S60: 4 | T60: 4 | U60: 4 | V60: 3 | W60: 3
B61: Prior Experience | C61: D4 | D61: 1 | E61: 1 | F61: 1 | G61: 0 | H61: 0 | I61: 1 | J61: 0 | K61: 1 | L61: 0 | M61: 0 | N61: 1 | O61: 1 | P61: 1 | Q61: 0 | R61: 0 | S61: 0 | T61: 1 | U61: 1 | V61: 0 | W61: 1
B62: Track Record | C62: D | D62: 3 | E62: 3 | F62: 3 | G62: 4 | H62: 4 | I62: 3 | J62: 2 | K62: 2 | L62: 4 | M62: 4 | N62: 3 | O62: 3 | P62: 4 | Q62: 3 | R62: 4 | S62: 3 | T62: 4 | U62: 4 | V62: 4 | W62: 3
D65: Rating1 | E65: Rating2 | F65: Rating3 | G65: Rating4 | H65: Rating5
B66: Exp Ret 3 YR
B67: Exp Ret 6 YR
B68: Std Dev
B69: Sharp Ratio 3 YR
B70: Sharp Ratio 5 YR
B71: Exp Ret 3 YR Quart | D71: 3 | E71: 3 | F71: 1 | G71: 2
B72: Exp Ret 6 YR Quart
B73: Std Dev Quart | D73: 3 | E73: 2 | F73: 2 | G73: 1
B74: Sharp Ratio 3 YR Quart
B75: Sharp Ratio 5 YR Quart
B76: Platform quality | D76: 3 | E76: 3 | F76: 3 | G76: 2
B77: Fee Structure | D77: 2 | E77: 2 | F77: 2 | G77: 1
B78: Governance Str | D78: 3 | E78: 2 | F78: 3 | G78: 2
B79: Prior Experience | D79: 0 | E79: 0 | F79: 0 | G79: 0
B80: Track Record | D80: 3 | E80: 2 | F80: 2 | G80: 2

Sheet Base
H1: Exit Cap | N1: Rent Growth | W1: Cap Rate Changes | Z1: Unlevered Prop Level | AC1: Tot Unlevered Ret | AF1: Gr Fund Lev Level Ret | AI1: Net Fund Level Ret | AL1: Rent Growth | AU1: Exit Cap vs. 10 YR | BU1: 3 YR Portfolio | CB1: 6 YR Portfolio | CY1: Exit cap rate caln
A2: SectorIdentifier | B2: Region | C2: Profile | D2: Nom Cap Rate | E2: Capex (Recc) | F2: Econ Cap Rate | H2: YR 3 Eco Exit Cap | I2: YR 6 Eco Exit Cap | K2: YR 3 Nom Exit Cap | L2: YR 6 Nom Exit Cap | N2: Yr 1 | O2: Yr 2 | P2: Yr 3 | Q2: Yr 4 | R2: Yr 5 | S2: Yr 6 | T2: Rent 3 YR CAGR | U2: Rent 6 YR CAGR | W2: 3 YR | X2: 6 YR | Z2: 3 YR IRR | AA2: 6 YR IRR | AC2: 3 YR Lev IRR | AD2: 6 YR Lev IRR | AF2: 3 YR IRR | AG2: 6 YR IRR | AI2: 3 YR IRR | AJ2: 6 YR IRR | AL2: Yr 1 | AM2: Yr 2 | AN2: Yr 3 | AO2: Yr 4 | AP2: Yr 5 | AQ2: Yr 6 | AR2: 3 YR CAGR | AS2: 6 YR CAGR | AU2: YR 3 Exit Cap | AV2: YR 6 Exit Cap | AX2: Std Dev | BA2: Yr 1 | BB2: Yr 2 | BC2: Yr 3 | BF2: Yr 1 | BG2: Yr 2 | BH2: Yr 3 | BI2: Yr 4 | BJ2: Yr 5 | BK2: Yr 6 | BM2: LTV | BN2: Rate | BO2: Rate - Base Case | BP2: Rate - High | BQ2: Rate - Low | BR2: Other Return | BS2: Fee Drag | BU2: 3 YR Rank | BV2: SI | BW2: Min | BX2: Max | BY2: Port | BZ2: Test | CB2: 6 YR Rank | CC2: SI | CD2: Min | CE2: Max | CF2: Port | CG2: Test | CJ2: Prop unlev ret over 10 Yr Spread | CK2: Prop unlev ret over 10 Yr Spread - Base | CL2: Prop unlev ret over 10 Yr Spread - High | CM2: Prop unlev ret over 10 Yr Spread - Low | CN2: Target unlev prop return 3 YR | CO2: Target unlev prop return 6 YR | CP2: Over/ undervalued | CQ2: Yr 1 | CR2: Yr 2 | CS2: Yr 3 | CT2: Yr 4 | CU2: Yr 5 | CV2: Yr 6 | CY2: Rent Gr expect 3 YR | CZ2: Rent Gr expect 6 YR | DB2: Eco Cap Rate 3 YR | DC2: Eco Cap Rate 6 YR | DE2: Nom Cap Rate 3 YR | DF2: Nom Cap Rate 6 YR
A3: 1 | B3: US | C3: Core - Res | D3: 0.046 | E3: 0.159 | F3: =+D3*(1-E3) -> 0.038686 | H3: =DB3 -> 0.025 | I3: =DC3 -> 0.04 | K3: =+H3/(1-$E3) -> 0.029726516 | L3: =+I3/(1-$E3) -> 0.047562426 | N3: =+AL3+(D$29-D$34) -> -0.012 | O3: =+AM3+(E$29-E$34) -> 0.01 | P3: =+AN3+(F$29-F$34) -> 0.024 | Q3: =+AO3+(G$29-G$34) -> 0.04 | R3: =+AP3+(H$29-H$34) -> 0.05 | S3: =+AQ3+(I$29-I$34) -> 0.025 | T3: {=+PRODUCT(1+N3:P3)^(0.333333333333333)-1} -> 0.0072240606 | U3: {=+PRODUCT(1+N3:S3)^(1/6)-1} -> 0.022635339 | Z3: =+IRR(AZ3:BC3) -> 0.25590456 | AA3: =+IRR(BE3:BK3) -> 0.079066583 | AC3: =+(Z3-BM3*BN3)/(1-BM3) -> 0.31516826 | AD3: =+(AA3-BM3*BN3)/(1-BM3) -> 0.08550855 | AF3: =Z3+$BR3 -> 0.26090456 | AG3: =AD3+$BR3 -> 0.09050855 | AI3: =AF3-$BS3 -> 0.25090456 | AJ3: =AG3-$BS3 -> 0.08050855 | AL3: -0.012 | AM3: 0.01 | AN3: 0.024 | AO3: 0.04 | AP3: 0.05 | AQ3: 0.025 | AR3: {=+PRODUCT(1+AL3:AN3)^(0.333333333333333)-1} -> 0.0072240606 | AS3: {=+PRODUCT(1+AL3:AQ3)^(1/6)-1} -> 0.022635339 | AU3: -0.003314 | AV3: -0.005 | AX3: 0.01 | AZ3: =-1 -> -1 | BA3: =+F3*(1+N3) -> 0.038221768 | BB3: =+BA3*(1+O3) -> 0.038603986 | BC3: =+BB3*(1+P3)+(BB3*(1+P3))*(1+E3)/H3 -> 1.8721636 | BE3: -1 | BF3: =+F3*(1+N3) -> 0.038221768 | BG3: =+BF3*(1+O3) -> 0.038603986 | BH3: =+BG3*(1+P3) -> 0.039530481 | BI3: =+BH3*(1+Q3) -> 0.041111701 | BJ3: =+BI3*(1+R3) -> 0.043167286 | BK3: =+BJ3*(1+S3)+BJ3*(1+S3)*(1+E3)/I3 -> 1.3262879 | BM3: 0.23 | BN3: =IF($D$25="Base",BO3,IF($D$25="High",BP3,IF($D$25="Low",BQ3,"ERR"))) -> 0.0575 | BO3: 0.0575 | BP3: 0.06 | BQ3: 0.055 | BR3: 0.005 | BS3: 0.01 | BU3: =RANK(AI3,AI$3:AI$21) -> 4 | BV3: =+$A3 -> 1 | BW3: 0 | BX3: 0.3 | CB3: =RANK(AJ3,AJ$3:AJ$21) -> 11 | CC3: =+$A3 -> 1 | CD3: 0 | CE3: 0.3 | CJ3: =IF($D$25="Base",CK3,IF($D$25="High",CL3,IF($D$25="Low",CM3,"ERR"))) -> 0.025 | CK3: 0.025 | CL3: 0.0275 | CM3: 0.0225 | CN3: =+$F$30+CJ3 -> 0.065 | CO3: =$I$30+CJ3 -> 0.065 | CP3: =+NPV(CN3,CQ3:CV3) -> 1.0750642 | CQ3: =+BF3 -> 0.038221768 | CR3: =+BG3 -> 0.038603986 | CS3: =+BH3 -> 0.039530481 | CT3: =+BI3 -> 0.041111701 | CU3: =+BJ3 -> 0.043167286 | CV3: =+BK3 -> 1.3262879 | CY3: =Q3 -> 0.04 | CZ3: =S3 -> 0.025 | DB3: =CN3-CY3 -> 0.025 | DC3: =+CO3-CZ3 -> 0.04 | DE3: =+DB3/(1-$E3) -> 0.029726516 | DF3: =+DC3/(1-$E3) -> 0.047562426
A4: =+A3+1 -> 2 | B4: US | C4: Core - Ind | D4: 0.037 | E4: 0.138 | F4: =+D4*(1-E4) -> 0.031894 | H4: =DB4 -> 0.03 | I4: =DC4 -> 0.04 | K4: =+H4/(1-$E4) -> 0.034802784 | L4: =+I4/(1-$E4) -> 0.046403712 | N4: =+AL4+(D$29-D$34) -> 0.061 | O4: =+AM4+(E$29-E$34) -> 0.05 | P4: =+AN4+(F$29-F$34) -> 0.043 | Q4: =+AO4+(G$29-G$34) -> 0.04 | R4: =+AP4+(H$29-H$34) -> 0.035 | S4: =+AQ4+(I$29-I$34) -> 0.03 | T4: {=+PRODUCT(1+N4:P4)^(0.333333333333333)-1} -> 0.051307261 | U4: {=+PRODUCT(1+N4:S4)^(1/6)-1} -> 0.043117707 | Z4: =+IRR(AZ4:BC4) -> 0.15196424 | AA4: =+IRR(BE4:BK4) -> 0.061531554 | AC4: =+(Z4-BM4*BN4)/(1-BM4) -> 0.16246027 | AD4: =+(AA4-BM4*BN4)/(1-BM4) -> 0.061979505 | AF4: =Z4+$BR4 -> 0.15946424 | AG4: =AD4+$BR4 -> 0.069479505 | AI4: =AF4-$BS4 -> 0.14946424 | AJ4: =AG4-$BS4 -> 0.059479505 | AL4: 0.061 | AM4: 0.05 | AN4: 0.043 | AO4: 0.04 | AP4: 0.035 | AQ4: 0.03 | AR4: {=+PRODUCT(1+AL4:AN4)^(0.333333333333333)-1} -> 0.051307261 | AS4: {=+PRODUCT(1+AL4:AQ4)^(1/6)-1} -> 0.043117707 | AU4: -0.006606 | AV4: 0 | AX4: 0.015 | AZ4: =-1 -> -1 | BA4: =+F4*(1+N4) -> 0.033839534 | BB4: =+BA4*(1+O4) -> 0.035531511 | BC4: =+BB4*(1+P4)+(BB4*(1+P4))*(1+E4)/H4 -> 1.4428446 | BE4: -1 | BF4: =+F4*(1+N4) -> 0.033839534 | BG4: =+BF4*(1+O4) -> 0.035531511 | BH4: =+BG4*(1+P4) -> 0.037059366 | BI4: =+BH4*(1+Q4) -> 0.03854174 | BJ4: =+BI4*(1+R4) -> 0.039890701 | BK4: =+BJ4*(1+S4)+BJ4*(1+S4)*(1+E4)/I4 -> 1.2100246 | BM4: 0.1 | BN4: =IF($D$25="Base",BO4,IF(D$25="High",BP4,IF(D$25="Low",BQ4,"ERR"))) -> 0.0575 | BO4: 0.0575 | BP4: 0.06 | BQ4: 0.055 | BR4: 0.0075 | BS4: 0.01 | BU4: =RANK(AI4,AI$3:AI$21) -> 8 | BV4: =+$A4 -> 2 | BW4: 0 | BX4: 0.3 | CB4: =RANK(AJ4,AJ$3:AJ$21) -> 14 | CC4: =+$A4 -> 2 | CD4: 0 | CE4: 0.3 | CJ4: =IF($D$25="Base",CK4,IF($D$25="High",CL4,IF($D$25="Low",CM4,"ERR"))) -> 0.03 | CK4: 0.03 | CL4: 0.0325 | CM4: 0.0275 | CN4: =+$F$30+CJ4 -> 0.07 | CO4: =$I$30+CJ4 -> 0.07 | CP4: =+NPV(CN4,CQ4:CV4) -> 0.95704711 | CQ4: =+BF4 -> 0.033839534 | CR4: =+BG4 -> 0.035531511 | CS4: =+BH4 -> 0.037059366 | CT4: =+BI4 -> 0.03854174 | CU4: =+BJ4 -> 0.039890701 | CV4: =+BK4 -> 1.2100246 | CY4: =Q4 -> 0.04 | CZ4: =S4 -> 0.03 | DB4: =CN4-CY4 -> 0.03 | DC4: =+CO4-CZ4 -> 0.04 | DE4: =+DB4/(1-$E4) -> 0.034802784 | DF4: =+DC4/(1-$E4) -> 0.046403712
A5: =+A4+1 -> 3 | B5: US | C5: Core - Off | D5: 0.056 | E5: 0.294 | F5: =+D5*(1-E5) -> 0.039536 | H5: =DB5 -> 0.07 | I5: =DC5 -> 0.055 | K5: =+H5/(1-$E5) -> 0.099150142 | L5: =+I5/(1-$E5) -> 0.077903683 | N5: =+AL5+(D$29-D$34) -> -0.018 | O5: =+AM5+(E$29-E$34) -> -0.011 | P5: =+AN5+(F$29-F$34) -> -0.008 | Q5: =+AO5+(G$29-G$34) -> 0.005 | R5: =+AP5+(H$29-H$34) -> 0.01 | S5: =+AQ5+(I$29-I$34) -> 0.02 | T5: {=+PRODUCT(1+N5:P5)^(0.333333333333333)-1} -> -0.012342232 | U5: {=+PRODUCT(1+N5:S5)^(1/6)-1} -> -0.00041934372 | Z5: =+IRR(AZ5:BC5) -> -0.067132978 | AA5: =+IRR(BE5:BK5) -> 0.027376585 | AC5: =+(Z5-BM5*BN5)/(1-BM5) -> -0.10141622 | AD5: =+(AA5-BM5*BN5)/(1-BM5) -> 0.016720731 | AF5: =Z5+$BR5 -> -0.067132978 | AG5: =AD5+$BR5 -> 0.016720731 | AI5: =AF5-$BS5 -> -0.077132978 | AJ5: =AG5-$BS5 -> 0.006720731 | AL5: -0.018 | AM5: -0.011 | AN5: -0.008 | AO5: 0.005 | AP5: 0.01 | AQ5: 0.02 | AR5: {=+PRODUCT(1+AL5:AN5)^(0.333333333333333)-1} -> -0.012342232 | AS5: {=+PRODUCT(1+AL5:AQ5)^(1/6)-1} -> -0.00041934372 | AU5: 0.009536 | AV5: 0.009536 | AX5: 0.03 | AZ5: =-1 -> -1 | BA5: =+F5*(1+N5) -> 0.038824352 | BB5: =+BA5*(1+O5) -> 0.038397284 | BC5: =+BB5*(1+P5)+(BB5*(1+P5))*(1+E5)/H5 -> 0.74221292 | BE5: -1 | BF5: =+F5*(1+N5) -> 0.038824352 | BG5: =+BF5*(1+O5) -> 0.038397284 | BH5: =+BG5*(1+P5) -> 0.038090106 | BI5: =+BH5*(1+Q5) -> 0.038280556 | BJ5: =+BI5*(1+R5) -> 0.038663362 | BK5: =+BJ5*(1+S5)+BJ5*(1+S5)*(1+E5)/I5 -> 0.96727296 | BM5: 0.2 | BN5: =IF($D$25="Base",BO5,IF(D$25="High",BP5,IF(D$25="Low",BQ5,"ERR"))) -> 0.07 | BO5: 0.07 | BP5: 0.0725 | BQ5: 0.0675 | BR5: 0 | BS5: 0.01 | BU5: =RANK(AI5,AI$3:AI$21) -> 18 | BV5: =+$A5 -> 3 | BW5: 0 | BX5: 0.15 | CB5: =RANK(AJ5,AJ$3:AJ$21) -> 17 | CC5: =+$A5 -> 3 | CD5: 0 | CE5: 0.15 | CJ5: =IF($D$25="Base",CK5,IF($D$25="High",CL5,IF($D$25="Low",CM5,"ERR"))) -> 0.035 | CK5: 0.035 | CL5: 0.0375 | CM5: 0.0325 | CN5: =+$F$30+CJ5 -> 0.075 | CO5: =$I$30+CJ5 -> 0.075 | CP5: =+NPV(CN5,CQ5:CV5) -> 0.78235459 | CQ5: =+BF5 -> 0.038824352 | CR5: =+BG5 -> 0.038397284 | CS5: =+BH5 -> 0.038090106 | CT5: =+BI5 -> 0.038280556 | CU5: =+BJ5 -> 0.038663362 | CV5: =+BK5 -> 0.96727296 | CY5: =Q5 -> 0.005 | CZ5: =S5 -> 0.02 | DB5: =CN5-CY5 -> 0.07 | DC5: =+CO5-CZ5 -> 0.055 | DE5: =+DB5/(1-$E5) -> 0.099150142 | DF5: =+DC5/(1-$E5) -> 0.077903683
A6: =+A5+1 -> 4 | B6: US | C6: Core - Retail | D6: 0.055 | E6: 0.188 | F6: =+D6*(1-E6) -> 0.04466 | H6: =DB6 -> 0.05 | I6: =DC6 -> 0.045 | K6: =+H6/(1-$E6) -> 0.061576355 | L6: =+I6/(1-$E6) -> 0.055418719 | N6: =+AL6+(D$29-D$34) -> 0.01 | O6: =+AM6+(E$29-E$34) -> 0.02 | P6: =+AN6+(F$29-F$34) -> 0.02 | Q6: =+AO6+(G$29-G$34) -> 0.02 | R6: =+AP6+(H$29-H$34) -> 0.02 | S6: =+AQ6+(I$29-I$34) -> 0.025 | T6: {=+PRODUCT(1+N6:P6)^(0.333333333333333)-1} -> 0.016655714 | U6: {=+PRODUCT(1+N6:S6)^(1/6)-1} -> 0.019156756 | Z6: =+IRR(AZ6:BC6) -> 0.081353981 | AA6: =+IRR(BE6:BK6) -> 0.089923054 | AC6: =+(Z6-BM6*BN6)/(1-BM6) -> 0.085122331 | AD6: =+(AA6-BM6*BN6)/(1-BM6) -> 0.095203593 | AF6: =Z6+$BR6 -> 0.083853981 | AG6: =AD6+$BR6 -> 0.097703593 | AI6: =AF6-$BS6 -> 0.073853981 | AJ6: =AG6-$BS6 -> 0.087703593 | AL6: 0.01 | AM6: 0.02 | AN6: 0.02 | AO6: 0.02 | AP6: 0.02 | AQ6: 0.025 | AR6: {=+PRODUCT(1+AL6:AN6)^(0.333333333333333)-1} -> 0.016655714 | AS6: {=+PRODUCT(1+AL6:AQ6)^(1/6)-1} -> 0.019156756 | AU6: 0.00466 | AV6: 0.00466 | AX6: 0.02 | AZ6: =-1 -> -1 | BA6: =+F6*(1+N6) -> 0.0451066 | BB6: =+BA6*(1+O6) -> 0.046008732 | BC6: =+BB6*(1+P6)+(BB6*(1+P6))*(1+E6)/H6 -> 1.1619597 | BE6: -1 | BF6: =+F6*(1+N6) -> 0.0451066 | BG6: =+BF6*(1+O6) -> 0.046008732 | BH6: =+BG6*(1+P6) -> 0.046928907 | BI6: =+BH6*(1+Q6) -> 0.047867485 | BJ6: =+BI6*(1+R6) -> 0.048824834 | BK6: =+BJ6*(1+S6)+BJ6*(1+S6)*(1+E6)/I6 -> 1.3712455 | BM6: 0.15 | BN6: =IF($D$25="Base",BO6,IF(D$25="High",BP6,IF(D$25="Low",BQ6,"ERR"))) -> 0.06 | BO6: 0.06 | BP6: 0.0625 | BQ6: 0.0575 | BR6: 0.0025 | BS6: 0.01 | BU6: =RANK(AI6,AI$3:AI$21) -> 15 | BV6: =+$A6 -> 4 | BW6: 0 | BX6: 0.15 | CB6: =RANK(AJ6,AJ$3:AJ$21) -> 9 | CC6: =+$A6 -> 4 | CD6: 0 | CE6: 0.15 | CJ6: =IF($D$25="Base",CK6,IF($D$25="High",CL6,IF($D$25="Low",CM6,"ERR"))) -> 0.03 | CK6: 0.03 | CL6: 0.0325 | CM6: 0.0275 | CN6: =+$F$30+CJ6 -> 0.07 | CO6: =$I$30+CJ6 -> 0.07 | CP6: =+NPV(CN6,CQ6:CV6) -> 1.1056975 | CQ6: =+BF6 -> 0.0451066 | CR6: =+BG6 -> 0.046008732 | CS6: =+BH6 -> 0.046928907 | CT6: =+BI6 -> 0.047867485 | CU6: =+BJ6 -> 0.048824834 | CV6: =+BK6 -> 1.3712455 | CY6: =Q6 -> 0.02 | CZ6: =S6 -> 0.025 | DB6: =CN6-CY6 -> 0.05 | DC6: =+CO6-CZ6 -> 0.045 | DE6: =+DB6/(1-$E6) -> 0.061576355 | DF6: =+DC6/(1-$E6) -> 0.055418719
A7: =+A6+1 -> 5 | B7: US | C7: Core-Plus - Res | D7: 0.048 | E7: 0.159 | F7: =+D7*(1-E7) -> 0.040368 | H7: =DB7 -> 0.025 | I7: =DC7 -> 0.04 | K7: =+H7/(1-$E7) -> 0.029726516 | L7: =+I7/(1-$E7) -> 0.047562426 | N7: =+AL7+(D$29-D$34) -> -0.016 | O7: =+AM7+(E$29-E$34) -> 0.006 | P7: =+AN7+(F$29-F$34) -> 0.023 | Q7: =+AO7+(G$29-G$34) -> 0.04 | R7: =+AP7+(H$29-H$34) -> 0.05 | S7: =+AQ7+(I$29-I$34) -> 0.025 | T7: {=+PRODUCT(1+N7:P7)^(0.333333333333333)-1} -> 0.0042062136 | U7: {=+PRODUCT(1+N7:S7)^(1/6)-1} -> 0.021102179 | Z7: =+IRR(AZ7:BC7) -> 0.27052966 | AA7: =+IRR(BE7:BK7) -> 0.085711713 | AC7: =+(Z7-BM7*BN7)/(1-BM7) -> 0.43123625 | AD7: =+(AA7-BM7*BN7)/(1-BM7) -> 0.10699423 | AF7: =Z7+$BR7 -> 0.28052966 | AG7: =AD7+$BR7 -> 0.11699423 | AI7: =AF7-$BS7 -> 0.26802966 | AJ7: =AG7-$BS7 -> 0.10449423 | AL7: -0.016 | AM7: 0.006 | AN7: 0.023 | AO7: 0.04 | AP7: 0.05 | AQ7: 0.025 | AR7: {=+PRODUCT(1+AL7:AN7)^(0.333333333333333)-1} -> 0.0042062136 | AS7: {=+PRODUCT(1+AL7:AQ7)^(1/6)-1} -> 0.021102179 | AU7: -0.001632 | AV7: -0.005 | AX7: 0.0125 | AZ7: =-1 -> -1 | BA7: =+F7*(1+N7) -> 0.039722112 | BB7: =+BA7*(1+O7) -> 0.039960445 | BC7: =+BB7*(1+P7)+(BB7*(1+P7))*(1+E7)/H7 -> 1.9360548 | BE7: -1 | BF7: =+F7*(1+N7) -> 0.039722112 | BG7: =+BF7*(1+O7) -> 0.039960445 | BH7: =+BG7*(1+P7) -> 0.040879535 | BI7: =+BH7*(1+Q7) -> 0.042514716 | BJ7: =+BI7*(1+R7) -> 0.044640452 | BK7: =+BJ7*(1+S7)+BJ7*(1+S7)*(1+E7)/I7 -> 1.37155 | BM7: 0.43 | BN7: =IF($D$25="Base",BO7,IF(D$25="High",BP7,IF(D$25="Low",BQ7,"ERR"))) -> 0.0575 | BO7: 0.0575 | BP7: 0.06 | BQ7: 0.055 | BR7: 0.01 | BS7: 0.0125 | BU7: =RANK(AI7,AI$3:AI$21) -> 3 | BV7: =+$A7 -> 5 | BW7: 0.15 | BX7: 0.3 | CB7: =RANK(AJ7,AJ$3:AJ$21) -> 7 | CC7: =+$A7 -> 5 | CD7: 0.2 | CE7: 0.3 | CJ7: =IF($D$25="Base",CK7,IF($D$25="High",CL7,IF($D$25="Low",CM7,"ERR"))) -> 0.025 | CK7: 0.025 | CL7: 0.0275 | CM7: 0.0225 | CN7: =+$F$30+CJ7 -> 0.065 | CO7: =$I$30+CJ7 -> 0.065 | CP7: =+NPV(CN7,CQ7:CV7) -> 1.1119712 | CQ7: =+BF7 -> 0.039722112 | CR7: =+BG7 -> 0.039960445 | CS7: =+BH7 -> 0.040879535 | CT7: =+BI7 -> 0.042514716 | CU7: =+BJ7 -> 0.044640452 | CV7: =+BK7 -> 1.37155 | CY7: =Q7 -> 0.04 | CZ7: =S7 -> 0.025 | DB7: =CN7-CY7 -> 0.025 | DC7: =+CO7-CZ7 -> 0.04 | DE7: =+DB7/(1-$E7) -> 0.029726516 | DF7: =+DC7/(1-$E7) -> 0.047562426
A8: =+A7+1 -> 6 | B8: US | C8: Core-Plus - Ind | D8: 0.041 | E8: 0.138 | F8: =+D8*(1-E8) -> 0.035342 | H8: =DB8 -> 0.035 | I8: =DC8 -> 0.045 | K8: =+H8/(1-$E8) -> 0.040603248 | L8: =+I8/(1-$E8) -> 0.052204176 | N8: =+AL8+(D$29-D$34) -> 0.066 | O8: =+AM8+(E$29-E$34) -> 0.059 | P8: =+AN8+(F$29-F$34) -> 0.05 | Q8: =+AO8+(G$29-G$34) -> 0.035 | R8: =+AP8+(H$29-H$34) -> 0.03 | S8: =+AQ8+(I$29-I$34) -> 0.025 | T8: {=+PRODUCT(1+N8:P8)^(0.333333333333333)-1} -> 0.058313058 | U8: {=+PRODUCT(1+N8:S8)^(1/6)-1} -> 0.044056458 | Z8: =+IRR(AZ8:BC8) -> 0.14445853 | AA8: =+IRR(BE8:BK8) -> 0.064271025 | AC8: =+(Z8-BM8*BN8)/(1-BM8) -> 0.15520622 | AD8: =+(AA8-BM8*BN8)/(1-BM8) -> 0.065107893 | AF8: =Z8+$BR8 -> 0.15195853 | AG8: =AD8+$BR8 -> 0.072607893 | AI8: =AF8-$BS8 -> 0.13945853 | AJ8: =AG8-$BS8 -> 0.060107893 | AL8: 0.066 | AM8: 0.059 | AN8: 0.05 | AO8: 0.035 | AP8: 0.03 | AQ8: 0.025 | AR8: {=+PRODUCT(1+AL8:AN8)^(0.333333333333333)-1} -> 0.058313058 | AS8: {=+PRODUCT(1+AL8:AQ8)^(1/6)-1} -> 0.044056458 | AU8: -0.003158 | AV8: 0 | AX8: 0.0175 | AZ8: =-1 -> -1 | BA8: =+F8*(1+N8) -> 0.037674572 | BB8: =+BA8*(1+O8) -> 0.039897372 | BC8: =+BB8*(1+P8)+(BB8*(1+P8))*(1+E8)/H8 -> 1.4039885 | BE8: -1 | BF8: =+F8*(1+N8) -> 0.037674572 | BG8: =+BF8*(1+O8) -> 0.039897372 | BH8: =+BG8*(1+P8) -> 0.04189224 | BI8: =+BH8*(1+Q8) -> 0.043358469 | BJ8: =+BI8*(1+R8) -> 0.044659223 | BK8: =+BJ8*(1+S8)+BJ8*(1+S8)*(1+E8)/I8 -> 1.2033924 | BM8: 0.11 | BN8: =IF($D$25="Base",BO8,IF(D$25="High",BP8,IF(D$25="Low",BQ8,"ERR"))) -> 0.0575 | BO8: 0.0575 | BP8: 0.06 | BQ8: 0.055 | BR8: 0.0075 | BS8: 0.0125 | BU8: =RANK(AI8,AI$3:AI$21) -> 9 | BV8: =+$A8 -> 6 | BW8: 0.15 | BX8: 0.3 | CB8: =RANK(AJ8,AJ$3:AJ$21) -> 13 | CC8: =+$A8 -> 6 | CD8: 0.2 | CE8: 0.3 | CJ8: =IF($D$25="Base",CK8,IF($D$25="High",CL8,IF($D$25="Low",CM8,"ERR"))) -> 0.03 | CK8: 0.03 | CL8: 0.0325 | CM8: 0.0275 | CN8: =+$F$30+CJ8 -> 0.07 | CO8: =$I$30+CJ8 -> 0.07 | CP8: =+NPV(CN8,CQ8:CV8) -> 0.97104487 | CQ8: =+BF8 -> 0.037674572 | CR8: =+BG8 -> 0.039897372 | CS8: =+BH8 -> 0.04189224 | CT8: =+BI8 -> 0.043358469 | CU8: =+BJ8 -> 0.044659223 | CV8: =+BK8 -> 1.2033924 | CY8: =Q8 -> 0.035 | CZ8: =S8 -> 0.025 | DB8: =CN8-CY8 -> 0.035 | DC8: =+CO8-CZ8 -> 0.045 | DE8: =+DB8/(1-$E8) -> 0.040603248 | DF8: =+DC8/(1-$E8) -> 0.052204176
A9: =+A8+1 -> 7 | B9: US | C9: Core-Plus - Off | D9: 0.054 | E9: 0.294 | F9: =+D9*(1-E9) -> 0.038124 | H9: =DB9 -> 0.07 | I9: =DC9 -> 0.055 | K9: =+H9/(1-$E9) -> 0.099150142 | L9: =+I9/(1-$E9) -> 0.077903683 | N9: =+AL9+(D$29-D$34) -> -0.014 | O9: =+AM9+(E$29-E$34) -> -0.007 | P9: =+AN9+(F$29-F$34) -> -0.003 | Q9: =+AO9+(G$29-G$34) -> 0.005 | R9: =+AP9+(H$29-H$34) -> 0.01 | S9: =+AQ9+(I$29-I$34) -> 0.02 | T9: {=+PRODUCT(1+N9:P9)^(0.333333333333333)-1} -> -0.0080104269 | U9: {=+PRODUCT(1+N9:S9)^(1/6)-1} -> 0.001770307 | Z9: =+IRR(AZ9:BC9) -> -0.074836844 | AA9: =+IRR(BE9:BK9) -> 0.02291798 | AC9: =+(Z9-BM9*BN9)/(1-BM9) -> -0.13116228 | AD9: =+(AA9-BM9*BN9)/(1-BM9) -> 0.0046083057 | AF9: =Z9+$BR9 -> -0.074836844 | AG9: =AD9+$BR9 -> 0.0046083057 | AI9: =AF9-$BS9 -> -0.087336844 | AJ9: =AG9-$BS9 -> -0.0078916943 | AL9: -0.014 | AM9: -0.007 | AN9: -0.003 | AO9: 0.005 | AP9: 0.01 | AQ9: 0.02 | AR9: {=+PRODUCT(1+AL9:AN9)^(0.333333333333333)-1} -> -0.0080104269 | AS9: {=+PRODUCT(1+AL9:AQ9)^(1/6)-1} -> 0.001770307 | AU9: 0.008124 | AV9: 0.008124 | AX9: 0.035 | AZ9: =-1 -> -1 | BA9: =+F9*(1+N9) -> 0.037590264 | BB9: =+BA9*(1+O9) -> 0.037327132 | BC9: =+BB9*(1+P9)+(BB9*(1+P9))*(1+E9)/H9 -> 0.72516379 | BE9: -1 | BF9: =+F9*(1+N9) -> 0.037590264 | BG9: =+BF9*(1+O9) -> 0.037327132 | BH9: =+BG9*(1+P9) -> 0.037215151 | BI9: =+BH9*(1+Q9) -> 0.037401227 | BJ9: =+BI9*(1+R9) -> 0.037775239 | BK9: =+BJ9*(1+S9)+BJ9*(1+S9)*(1+E9)/I9 -> 0.94505406 | BM9: 0.28 | BN9: =IF($D$25="Base",BO9,IF(D$25="High",BP9,IF(D$25="Low",BQ9,"ERR"))) -> 0.07 | BO9: 0.07 | BP9: 0.0725 | BQ9: 0.0675 | BR9: 0 | BS9: 0.0125 | BU9: =RANK(AI9,AI$3:AI$21) -> 19 | BV9: =+$A9 -> 7 | BW9: 0.05 | BX9: 0.15 | CB9: =RANK(AJ9,AJ$3:AJ$21) -> 19 | CC9: =+$A9 -> 7 | CD9: 0.05 | CE9: 0.15 | CJ9: =IF($D$25="Base",CK9,IF($D$25="High",CL9,IF($D$25="Low",CM9,"ERR"))) -> 0.035 | CK9: 0.035 | CL9: 0.0375 | CM9: 0.0325 | CN9: =+$F$30+CJ9 -> 0.075 | CO9: =$I$30+CJ9 -> 0.075 | CP9: =+NPV(CN9,CQ9:CV9) -> 0.76390219 | CQ9: =+BF9 -> 0.037590264 | CR9: =+BG9 -> 0.037327132 | CS9: =+BH9 -> 0.037215151 | CT9: =+BI9 -> 0.037401227 | CU9: =+BJ9 -> 0.037775239 | CV9: =+BK9 -> 0.94505406 | CY9: =Q9 -> 0.005 | CZ9: =S9 -> 0.02 | DB9: =CN9-CY9 -> 0.07 | DC9: =+CO9-CZ9 -> 0.055 | DE9: =+DB9/(1-$E9) -> 0.099150142 | DF9: =+DC9/(1-$E9) -> 0.077903683
A10: =+A9+1 -> 8 | B10: US | C10: Core-Plus - Ret | D10: 0.059 | E10: 0.188 | F10: =+D10*(1-E10) -> 0.047908 | H10: =DB10 -> 0.05 | I10: =DC10 -> 0.045 | K10: =+H10/(1-$E10) -> 0.061576355 | L10: =+I10/(1-$E10) -> 0.055418719 | N10: =+AL10+(D$29-D$34) -> 0.01 | O10: =+AM10+(E$29-E$34) -> 0.02 | P10: =+AN10+(F$29-F$34) -> 0.02 | Q10: =+AO10+(G$29-G$34) -> 0.02 | R10: =+AP10+(H$29-H$34) -> 0.02 | S10: =+AQ10+(I$29-I$34) -> 0.025 | T10: {=+PRODUCT(1+N10:P10)^(0.333333333333333)-1} -> 0.016655714 | U10: {=+PRODUCT(1+N10:S10)^(1/6)-1} -> 0.019156756 | Z10: =+IRR(AZ10:BC10) -> 0.10808575 | AA10: =+IRR(BE10:BK10) -> 0.10413809 | AC10: =+(Z10-BM10*BN10)/(1-BM10) -> 0.15072782 | AD10: =+(AA10-BM10*BN10)/(1-BM10) -> 0.14327941 | AF10: =Z10+$BR10 -> 0.11058575 | AG10: =AD10+$BR10 -> 0.14577941 | AI10: =AF10-$BS10 -> 0.098085745 | AJ10: =AG10-$BS10 -> 0.13327941 | AL10: 0.01 | AM10: 0.02 | AN10: 0.02 | AO10: 0.02 | AP10: 0.02 | AQ10: 0.025 | AR10: {=+PRODUCT(1+AL10:AN10)^(0.333333333333333)-1} -> 0.016655714 | AS10: {=+PRODUCT(1+AL10:AQ10)^(1/6)-1} -> 0.019156756 | AU10: 0.007908 | AV10: 0.007908 | AX10: 0.025 | AZ10: =-1 -> -1 | BA10: =+F10*(1+N10) -> 0.04838708 | BB10: =+BA10*(1+O10) -> 0.049354822 | BC10: =+BB10*(1+P10)+(BB10*(1+P10))*(1+E10)/H10 -> 1.2464659 | BE10: -1 | BF10: =+F10*(1+N10) -> 0.04838708 | BG10: =+BF10*(1+O10) -> 0.049354822 | BH10: =+BG10*(1+P10) -> 0.050341918 | BI10: =+BH10*(1+Q10) -> 0.051348756 | BJ10: =+BI10*(1+R10) -> 0.052375732 | BK10: =+BJ10*(1+S10)+BJ10*(1+S10)*(1+E10)/I10 -> 1.4709724 | BM10: 0.47 | BN10: =IF($D$25="Base",BO10,IF(D$25="High",BP10,IF(D$25="Low",BQ10,"ERR"))) -> 0.06 | BO10: 0.06 | BP10: 0.0625 | BQ10: 0.0575 | BR10: 0.0025 | BS10: 0.0125 | BU10: =RANK(AI10,AI$3:AI$21) -> 13 | BV10: =+$A10 -> 8 | BW10: 0.05 | BX10: 0.15 | CB10: =RANK(AJ10,AJ$3:AJ$21) -> 4 | CC10: =+$A10 -> 8 | CD10: 0.05 | CE10: 0.15 | CJ10: =IF($D$25="Base",CK10,IF($D$25="High",CL10,IF($D$25="Low",CM10,"ERR"))) -> 0.03 | CK10: 0.03 | CL10: 0.0325 | CM10: 0.0275 | CN10: =+$F$30+CJ10 -> 0.07 | CO10: =$I$30+CJ10 -> 0.07 | CP10: =+NPV(CN10,CQ10:CV10) -> 1.1861119 | CQ10: =+BF10 -> 0.04838708 | CR10: =+BG10 -> 0.049354822 | CS10: =+BH10 -> 0.050341918 | CT10: =+BI10 -> 0.051348756 | CU10: =+BJ10 -> 0.052375732 | CV10: =+BK10 -> 1.4709724 | CY10: =Q10 -> 0.02 | CZ10: =S10 -> 0.025 | DB10: =CN10-CY10 -> 0.05 | DC10: =+CO10-CZ10 -> 0.045 | DE10: =+DB10/(1-$E10) -> 0.061576355 | DF10: =+DC10/(1-$E10) -> 0.055418719
A11: =+A10+1 -> 9 | B11: US | C11: Data Center | D11: 0.054 | E11: 0.191 | F11: =+D11*(1-E11) -> 0.043686 | H11: =DB11 -> 0.025 | I11: =DC11 -> 0.045 | K11: =+H11/(1-$E11) -> 0.030902349 | L11: =+I11/(1-$E11) -> 0.055624227 | N11: =+AL11+(D$29-D$34) -> 0.059 | O11: =+AM11+(E$29-E$34) -> 0.059 | P11: =+AN11+(F$29-F$34) -> 0.051 | Q11: =+AO11+(G$29-G$34) -> 0.05 | R11: =+AP11+(H$29-H$34) -> 0.04 | S11: =+AQ11+(I$29-I$34) -> 0.03 | T11: {=+PRODUCT(1+N11:P11)^(0.333333333333333)-1} -> 0.05632659 | U11: {=+PRODUCT(1+N11:S11)^(1/6)-1} -> 0.048115354 | Z11: =+IRR(AZ11:BC11) -> 0.38579056 | AA11: =+IRR(BE11:BK11) -> 0.11776038 | AC11: =+(Z11-BM11*BN11)/(1-BM11) -> 0.54748591 | AD11: =+(AA11-BM11*BN11)/(1-BM11) -> 0.14744086 | AF11: =Z11+$BR11 -> 0.39579056 | AG11: =AD11+$BR11 -> 0.15744086 | AI11: =AF11-$BS11 -> 0.38329056 | AJ11: =AG11-$BS11 -> 0.14494086 | AL11: 0.059 | AM11: 0.059 | AN11: 0.051 | AO11: 0.05 | AP11: 0.04 | AQ11: 0.03 | AR11: {=+PRODUCT(1+AL11:AN11)^(0.333333333333333)-1} -> 0.05632659 | AS11: {=+PRODUCT(1+AL11:AQ11)^(1/6)-1} -> 0.048115354 | AU11: 0.003686 | AV11: 0.003686 | AX11: 0.015 | AZ11: =-1 -> -1 | BA11: =+F11*(1+N11) -> 0.046263474 | BB11: =+BA11*(1+O11) -> 0.048993019 | BC11: =+BB11*(1+P11)+(BB11*(1+P11))*(1+E11)/H11 -> 2.5045545 | BE11: -1 | BF11: =+F11*(1+N11) -> 0.046263474 | BG11: =+BF11*(1+O11) -> 0.048993019 | BH11: =+BG11*(1+P11) -> 0.051491663 | BI11: =+BH11*(1+Q11) -> 0.054066246 | BJ11: =+BI11*(1+R11) -> 0.056228896 | BK11: =+BJ11*(1+S11)+BJ11*(1+S11)*(1+E11)/I11 -> 1.590753 | BM11: 0.33 | BN11: =IF($D$25="Base",BO11,IF(D$25="High",BP11,IF(D$25="Low",BQ11,"ERR"))) -> 0.0575 | BO11: 0.0575 | BP11: 0.06 | BQ11: 0.055 | BR11: 0.01 | BS11: 0.0125 | BU11: =RANK(AI11,AI$3:AI$21) -> 1 | BV11: =+$A11 -> 9 | BW11: 0.05 | BX11: 0.15 | CB11: =RANK(AJ11,AJ$3:AJ$21) -> 3 | CC11: =+$A11 -> 9 | CD11: 0.05 | CE11: 0.15 | CJ11: =IF($D$25="Base",CK11,IF($D$25="High",CL11,IF($D$25="Low",CM11,"ERR"))) -> 0.035 | CK11: 0.035 | CL11: 0.0375 | CM11: 0.0325 | CN11: =+$F$30+CJ11 -> 0.075 | CO11: =$I$30+CJ11 -> 0.075 | CP11: =+NPV(CN11,CQ11:CV11) -> 1.2372781 | CQ11: =+BF11 -> 0.046263474 | CR11: =+BG11 -> 0.048993019 | CS11: =+BH11 -> 0.051491663 | CT11: =+BI11 -> 0.054066246 | CU11: =+BJ11 -> 0.056228896 | CV11: =+BK11 -> 1.590753 | CY11: =Q11 -> 0.05 | CZ11: =S11 -> 0.03 | DB11: =CN11-CY11 -> 0.025 | DC11: =+CO11-CZ11 -> 0.045 | DE11: =+DB11/(1-$E11) -> 0.030902349 | DF11: =+DC11/(1-$E11) -> 0.055624227
A12: =+A11+1 -> 10 | B12: US | C12: Single-Family Rental | D12: 0.045 | E12: 0.136 | F12: =+D12*(1-E12) -> 0.03888 | H12: =DB12 -> 0.03 | I12: =DC12 -> 0.04 | K12: =+H12/(1-$E12) -> 0.034722222 | L12: =+I12/(1-$E12) -> 0.046296296 | N12: =+AL12+(D$29-D$34) -> 0.048 | O12: =+AM12+(E$29-E$34) -> 0.048 | P12: =+AN12+(F$29-F$34) -> 0.049 | Q12: =+AO12+(G$29-G$34) -> 0.04 | R12: =+AP12+(H$29-H$34) -> 0.04 | S12: =+AQ12+(I$29-I$34) -> 0.03 | T12: {=+PRODUCT(1+N12:P12)^(0.333333333333333)-1} -> 0.048333227 | U12: {=+PRODUCT(1+N12:S12)^(1/6)-1} -> 0.042478226 | Z12: =+IRR(AZ12:BC12) -> 0.22870484 | AA12: =+IRR(BE12:BK12) -> 0.099207502 | AC12: =+(Z12-BM12*BN12)/(1-BM12) -> 0.27699338 | AD12: =+(AA12-BM12*BN12)/(1-BM12) -> 0.11097116 | AF12: =Z12+$BR12 -> 0.23620484 | AG12: =AD12+$BR12 -> 0.11847116 | AI12: =AF12-$BS12 -> 0.22370484 | AJ12: =AG12-$BS12 -> 0.10597116 | AL12: 0.048 | AM12: 0.048 | AN12: 0.049 | AO12: 0.04 | AP12: 0.04 | AQ12: 0.03 | AR12: {=+PRODUCT(1+AL12:AN12)^(0.333333333333333)-1} -> 0.048333227 | AS12: {=+PRODUCT(1+AL12:AQ12)^(1/6)-1} -> 0.042478226 | AU12: -0.00362 | AV12: -0.00362 | AX12: 0.015 | AZ12: =-1 -> -1 | BA12: =+F12*(1+N12) -> 0.04074624 | BB12: =+BA12*(1+O12) -> 0.04270206 | BC12: =+BB12*(1+P12)+(BB12*(1+P12))*(1+E12)/H12 -> 1.7410114 | BE12: -1 | BF12: =+F12*(1+N12) -> 0.04074624 | BG12: =+BF12*(1+O12) -> 0.04270206 | BH12: =+BG12*(1+P12) -> 0.04479446 | BI12: =+BH12*(1+Q12) -> 0.046586239 | BJ12: =+BI12*(1+R12) -> 0.048449688 | BK12: =+BJ12*(1+S12)+BJ12*(1+S12)*(1+E12)/I12 -> 1.4671535 | BM12: 0.22 | BN12: =IF($D$25="Base",BO12,IF(D$25="High",BP12,IF(D$25="Low",BQ12,"ERR"))) -> 0.0575 | BO12: 0.0575 | BP12: 0.06 | BQ12: 0.055 | BR12: 0.0075 | BS12: 0.0125 | BU12: =RANK(AI12,AI$3:AI$21) -> 5 | BV12: =+$A12 -> 10 | BW12: 0.05 | BX12: 0.15 | CB12: =RANK(AJ12,AJ$3:AJ$21) -> 6 | CC12: =+$A12 -> 10 | CD12: 0.05 | CE12: 0.15 | CJ12: =IF($D$25="Base",CK12,IF($D$25="High",CL12,IF($D$25="Low",CM12,"ERR"))) -> 0.03 | CK12: 0.03 | CL12: 0.0325 | CM12: 0.0275 | CN12: =+$F$30+CJ12 -> 0.07 | CO12: =$I$30+CJ12 -> 0.07 | CP12: =+NPV(CN12,CQ12:CV12) -> 1.1596545 | CQ12: =+BF12 -> 0.04074624 | CR12: =+BG12 -> 0.04270206 | CS12: =+BH12 -> 0.04479446 | CT12: =+BI12 -> 0.046586239 | CU12: =+BJ12 -> 0.048449688 | CV12: =+BK12 -> 1.4671535 | CY12: =Q12 -> 0.04 | CZ12: =S12 -> 0.03 | DB12: =CN12-CY12 -> 0.03 | DC12: =+CO12-CZ12 -> 0.04 | DE12: =+DB12/(1-$E12) -> 0.034722222 | DF12: =+DC12/(1-$E12) -> 0.046296296
A13: =+A12+1 -> 11 | B13: US | C13: Cold Storage | D13: 0.038 | E13: 0.17 | F13: =+D13*(1-E13) -> 0.03154 | H13: =DB13 -> 0.035 | I13: =DC13 -> 0.055 | K13: =+H13/(1-$E13) -> 0.042168675 | L13: =+I13/(1-$E13) -> 0.06626506 | N13: =+AL13+(D$29-D$34) -> 0.1 | O13: =+AM13+(E$29-E$34) -> 0.08 | P13: =+AN13+(F$29-F$34) -> 0.05 | Q13: =+AO13+(G$29-G$34) -> 0.04 | R13: =+AP13+(H$29-H$34) -> 0.03 | S13: =+AQ13+(I$29-I$34) -> 0.02 | T13: {=+PRODUCT(1+N13:P13)^(0.333333333333333)-1} -> 0.076469956 | U13: {=+PRODUCT(1+N13:S13)^(1/6)-1} -> 0.052962115 | Z13: =+IRR(AZ13:BC13) -> 0.12953342 | AA13: =+IRR(BE13:BK13) -> 0.026114439 | AC13: =+(Z13-BM13*BN13)/(1-BM13) -> 0.15354456 | AD13: =+(AA13-BM13*BN13)/(1-BM13) -> 0.015652585 | AF13: =Z13+$BR13 -> 0.13453342 | AG13: =AD13+$BR13 -> 0.020652585 | AI13: =AF13-$BS13 -> 0.12203342 | AJ13: =AG13-$BS13 -> 0.0081525848 | AL13: 0.1 | AM13: 0.08 | AN13: 0.05 | AO13: 0.04 | AP13: 0.03 | AQ13: 0.02 | AR13: {=+PRODUCT(1+AL13:AN13)^(0.333333333333333)-1} -> 0.076469956 | AS13: {=+PRODUCT(1+AL13:AQ13)^(1/6)-1} -> 0.052962115 | AU13: -0.00846 | AV13: -0.004 | AX13: 0.015 | AZ13: =-1 -> -1 | BA13: =+F13*(1+N13) -> 0.034694 | BB13: =+BA13*(1+O13) -> 0.03746952 | BC13: =+BB13*(1+P13)+(BB13*(1+P13))*(1+E13)/H13 -> 1.3545231 | BE13: -1 | BF13: =+F13*(1+N13) -> 0.034694 | BG13: =+BF13*(1+O13) -> 0.03746952 | BH13: =+BG13*(1+P13) -> 0.039342996 | BI13: =+BH13*(1+Q13) -> 0.040916716 | BJ13: =+BI13*(1+R13) -> 0.042144217 | BK13: =+BJ13*(1+S13)+BJ13*(1+S13)*(1+E13)/I13 -> 0.95743999 | BM13: 0.25 | BN13: =IF($D$25="Base",BO13,IF(D$25="High",BP13,IF(D$25="Low",BQ13,"ERR"))) -> 0.0575 | BO13: 0.0575 | BP13: 0.06 | BQ13: 0.055 | BR13: 0.005 | BS13: 0.0125 | BU13: =RANK(AI13,AI$3:AI$21) -> 11 | BV13: =+$A13 -> 11 | BW13: 0.02 | BX13: 0.1 | CB13: =RANK(AJ13,AJ$3:AJ$21) -> 16 | CC13: =+$A13 -> 11 | CD13: 0.02 | CE13: 0.1 | CJ13: =IF($D$25="Base",CK13,IF($D$25="High",CL13,IF($D$25="Low",CM13,"ERR"))) -> 0.035 | CK13: 0.035 | CL13: 0.0375 | CM13: 0.0325 | CN13: =+$F$30+CJ13 -> 0.075 | CO13: =$I$30+CJ13 -> 0.075 | CP13: =+NPV(CN13,CQ13:CV13) -> 0.77674529 | CQ13: =+BF13 -> 0.034694 | CR13: =+BG13 -> 0.03746952 | CS13: =+BH13 -> 0.039342996 | CT13: =+BI13 -> 0.040916716 | CU13: =+BJ13 -> 0.042144217 | CV13: =+BK13 -> 0.95743999 | CY13: =Q13 -> 0.04 | CZ13: =S13 -> 0.02 | DB13: =CN13-CY13 -> 0.035 | DC13: =+CO13-CZ13 -> 0.055 | DE13: =+DB13/(1-$E13) -> 0.042168675 | DF13: =+DC13/(1-$E13) -> 0.06626506
A14: =+A13+1 -> 12 | B14: US | C14: Senior Housing | D14: 0.052 | E14: 0.23 | F14: =+D14*(1-E14) -> 0.04004 | H14: =DB14 -> 0.03 | I14: =DC14 -> 0.04 | K14: =+H14/(1-$E14) -> 0.038961039 | L14: =+I14/(1-$E14) -> 0.051948052 | N14: =+AL14+(D$29-D$34) -> 0.085 | O14: =+AM14+(E$29-E$34) -> 0.061 | P14: =+AN14+(F$29-F$34) -> 0.051 | Q14: =+AO14+(G$29-G$34) -> 0.04 | R14: =+AP14+(H$29-H$34) -> 0.04 | S14: =+AQ14+(I$29-I$34) -> 0.03 | T14: {=+PRODUCT(1+N14:P14)^(0.333333333333333)-1} -> 0.06557154 | U14: {=+PRODUCT(1+N14:S14)^(1/6)-1} -> 0.051014296 | Z14: =+IRR(AZ14:BC14) -> 0.29406678 | AA14: =+IRR(BE14:BK14) -> 0.12802797 | AC14: =+(Z14-BM14*BN14)/(1-BM14) -> 0.42144889 | AD14: =+(AA14-BM14*BN14)/(1-BM14) -> 0.16600457 | AF14: =Z14+$BR14 -> 0.29906678 | AG14: =AD14+$BR14 -> 0.17100457 | AI14: =AF14-$BS14 -> 0.28656678 | AJ14: =AG14-$BS14 -> 0.15850457 | AL14: 0.085 | AM14: 0.061 | AN14: 0.051 | AO14: 0.04 | AP14: 0.04 | AQ14: 0.03 | AR14: {=+PRODUCT(1+AL14:AN14)^(0.333333333333333)-1} -> 0.06557154 | AS14: {=+PRODUCT(1+AL14:AQ14)^(1/6)-1} -> 0.051014296 | AU14: 4e-05 | AV14: 4e-05 | AX14: 0.0125 | AZ14: =-1 -> -1 | BA14: =+F14*(1+N14) -> 0.0434434 | BB14: =+BA14*(1+O14) -> 0.046093447 | BC14: =+BB14*(1+P14)+(BB14*(1+P14))*(1+E14)/H14 -> 2.034657 | BE14: -1 | BF14: =+F14*(1+N14) -> 0.0434434 | BG14: =+BF14*(1+O14) -> 0.046093447 | BH14: =+BG14*(1+P14) -> 0.048444213 | BI14: =+BH14*(1+Q14) -> 0.050381982 | BJ14: =+BI14*(1+R14) -> 0.052397261 | BK14: =+BJ14*(1+S14)+BJ14*(1+S14)*(1+E14)/I14 -> 1.7135214 | BM14: 0.35 | BN14: =IF($D$25="Base",BO14,IF(D$25="High",BP14,IF(D$25="Low",BQ14,"ERR"))) -> 0.0575 | BO14: 0.0575 | BP14: 0.06 | BQ14: 0.055 | BR14: 0.005 | BS14: 0.0125 | BU14: =RANK(AI14,AI$3:AI$21) -> 2 | BV14: =+$A14 -> 12 | BW14: 0.02 | BX14: 0.1 | CB14: =RANK(AJ14,AJ$3:AJ$21) -> 2 | CC14: =+$A14 -> 12 | CD14: 0.02 | CE14: 0.1 | CJ14: =IF($D$25="Base",CK14,IF($D$25="High",CL14,IF($D$25="Low",CM14,"ERR"))) -> 0.03 | CK14: 0.03 | CL14: 0.0325 | CM14: 0.0275 | CN14: =+$F$30+CJ14 -> 0.07 | CO14: =$I$30+CJ14 -> 0.07 | CP14: =+NPV(CN14,CQ14:CV14) -> 1.3379924 | CQ14: =+BF14 -> 0.0434434 | CR14: =+BG14 -> 0.046093447 | CS14: =+BH14 -> 0.048444213 | CT14: =+BI14 -> 0.050381982 | CU14: =+BJ14 -> 0.052397261 | CV14: =+BK14 -> 1.7135214 | CY14: =Q14 -> 0.04 | CZ14: =S14 -> 0.03 | DB14: =CN14-CY14 -> 0.03 | DC14: =+CO14-CZ14 -> 0.04 | DE14: =+DB14/(1-$E14) -> 0.038961039 | DF14: =+DC14/(1-$E14) -> 0.051948052
A15: =+A14+1 -> 13 | B15: US | C15: Student Housing | D15: 0.0575 | E15: 0.11 | F15: =+D15*(1-E15) -> 0.051175 | H15: =DB15 -> 0.045 | I15: =DC15 -> 0.05 | K15: =+H15/(1-$E15) -> 0.050561798 | L15: =+I15/(1-$E15) -> 0.056179775 | N15: =+AL15+(D$29-D$34) -> 0.03 | O15: =+AM15+(E$29-E$34) -> 0.03 | P15: =+AN15+(F$29-F$34) -> 0.03 | Q15: =+AO15+(G$29-G$34) -> 0.025 | R15: =+AP15+(H$29-H$34) -> 0.025 | S15: =+AQ15+(I$29-I$34) -> 0.02 | T15: {=+PRODUCT(1+N15:P15)^(0.333333333333333)-1} -> 0.03 | U15: {=+PRODUCT(1+N15:S15)^(1/6)-1} -> 0.026659892 | Z15: =+IRR(AZ15:BC15) -> 0.16214525 | AA15: =+IRR(BE15:BK15) -> 0.099011553 | AC15: =+(Z15-BM15*BN15)/(1-BM15) -> 0.20699322 | AD15: =+(AA15-BM15*BN15)/(1-BM15) -> 0.11680222 | AF15: =Z15+$BR15 -> 0.16714525 | AG15: =AD15+$BR15 -> 0.12180222 | AI15: =AF15-$BS15 -> 0.15464525 | AJ15: =AG15-$BS15 -> 0.10930222 | AL15: 0.03 | AM15: 0.03 | AN15: 0.03 | AO15: 0.025 | AP15: 0.025 | AQ15: 0.02 | AR15: {=+PRODUCT(1+AL15:AN15)^(0.333333333333333)-1} -> 0.03 | AS15: {=+PRODUCT(1+AL15:AQ15)^(1/6)-1} -> 0.026659892 | AU15: 0.011175 | AV15: 0.011175 | AX15: 0.015 | AZ15: =-1 -> -1 | BA15: =+F15*(1+N15) -> 0.05271025 | BB15: =+BA15*(1+O15) -> 0.054291558 | BC15: =+BB15*(1+P15)+(BB15*(1+P15))*(1+E15)/H15 -> 1.4352878 | BE15: -1 | BF15: =+F15*(1+N15) -> 0.05271025 | BG15: =+BF15*(1+O15) -> 0.054291558 | BH15: =+BG15*(1+P15) -> 0.055920304 | BI15: =+BH15*(1+Q15) -> 0.057318312 | BJ15: =+BI15*(1+R15) -> 0.05875127 | BK15: =+BJ15*(1+S15)+BJ15*(1+S15)*(1+E15)/I15 -> 1.39029 | BM15: 0.3 | BN15: =IF($D$25="Base",BO15,IF(D$25="High",BP15,IF(D$25="Low",BQ15,"ERR"))) -> 0.0575 | BO15: 0.0575 | BP15: 0.06 | BQ15: 0.055 | BR15: 0.005 | BS15: 0.0125 | BU15: =RANK(AI15,AI$3:AI$21) -> 7 | BV15: =+$A15 -> 13 | BW15: 0.02 | BX15: 0.1 | CB15: =RANK(AJ15,AJ$3:AJ$21) -> 5 | CC15: =+$A15 -> 13 | CD15: 0.02 | CE15: 0.1 | CJ15: =IF($D$25="Base",CK15,IF($D$25="High",CL15,IF($D$25="Low",CM15,"ERR"))) -> 0.03 | CK15: 0.03 | CL15: 0.0325 | CM15: 0.0275 | CN15: =+$F$30+CJ15 -> 0.07 | CO15: =$I$30+CJ15 -> 0.07 | CP15: =+NPV(CN15,CQ15:CV15) -> 1.1543556 | CQ15: =+BF15 -> 0.05271025 | CR15: =+BG15 -> 0.054291558 | CS15: =+BH15 -> 0.055920304 | CT15: =+BI15 -> 0.057318312 | CU15: =+BJ15 -> 0.05875127 | CV15: =+BK15 -> 1.39029 | CY15: =Q15 -> 0.025 | CZ15: =S15 -> 0.02 | DB15: =CN15-CY15 -> 0.045 | DC15: =+CO15-CZ15 -> 0.05 | DE15: =+DB15/(1-$E15) -> 0.050561798 | DF15: =+DC15/(1-$E15) -> 0.056179775
... A21: =+A20+1 -> 19 | B21: US | C21: IOS | D21: 0.037 | E21: 0.07 | F21: =+D21*(1-E21) -> 0.03441 | H21: =DB21 -> 0.035 | I21: =DC21 -> 0.055 | K21: =+H21/(1-$E21) -> 0.037634409 | L21: =+I21/(1-$E21) -> 0.059139785 | N21: =+AL21+(D$29-D$34) -> 0.07 | O21: =+AM21+(E$29-E$34) -> 0.06 | P21: =+AN21+(F$29-F$34) -> 0.05 | Q21: =+AO21+(G$29-G$34) -> 0.04 | R21: =+AP21+(H$29-H$34) -> 0.03 | S21: =+AQ21+(I$29-I$34) -> 0.02 | T21: {=+PRODUCT(1+N21:P21)^(0.333333333333333)-1} -> 0.059968553 | U21: {=+PRODUCT(1+N21:S21)^(1/6)-1} -> 0.044860424 | Z21: =+IRR(AZ21:BC21) -> 0.11413092 | AA21: =+IRR(BE21:BK21) -> 0.020862224 | AC21: =+(Z21-BM21*BN21)/(1-BM21) -> 0.13217456 | AD21: =+(AA21-BM21*BN21)/(1-BM21) -> 0.007816298 | AF21: =Z21+$BR21 -> 0.12163092 | AG21: =AD21+$BR21 -> 0.015316298 | AI21: =AF21-$BS21 -> 0.10913092 | AJ21: =AG21-$BS21 -> 0.002816298 | AL21: 0.07 | AM21: 0.06 | AN21: 0.05 | AO21: 0.04 | AP21: 0.03 | AQ21: 0.02 | AR21: {=+PRODUCT(1+AL21:AN21)^(0.333333333333333)-1} -> 0.059968553 | AS21: {=+PRODUCT(1+AL21:AQ21)^(1/6)-1} -> 0.044860424 | AU21: -0.00559 | AV21: -0.003 | AX21: 0.0175 | AZ21: =-1 -> -1 | BA21: =+F21*(1+N21) -> 0.0368187 | BB21: =+BA21*(1+O21) -> 0.039027822 | BC21: =+BB21*(1+P21)+(BB21*(1+P21))*(1+E21)/H21 -> 1.2937723 | BE21: -1 | BF21: =+F21*(1+N21) -> 0.0368187 | BG21: =+BF21*(1+O21) -> 0.039027822 | BH21: =+BG21*(1+P21) -> 0.040979213 | BI21: =+BH21*(1+Q21) -> 0.042618382 | BJ21: =+BI21*(1+R21) -> 0.043896933 | BK21: =+BJ21*(1+S21)+BJ21*(1+S21)*(1+E21)/I21 -> 0.91584965 | BM21: 0.25 | BN21: =IF($D$25="Base",BO21,IF(D$25="High",BP21,IF(D$25="Low",BQ21,"ERR"))) -> 0.06 | BO21: 0.06 | BP21: 0.0625 | BQ21: 0.0575 | BR21: 0.0075 | BS21: 0.0125 | BU21: =RANK(AI21,AI$3:AI$21) -> 12 | BV21: =+$A21 -> 19 | BW21: 0.01 | BX21: 0.07 | CB21: =RANK(AJ21,AJ$3:AJ$21) -> 18 | CC21: =+$A21 -> 19 | CD21: 0.01 | CE21: 0.07 | CJ21: =IF($D$25="Base",CK21,IF($D$25="High",CL21,IF($D$25="Low",CM21,"ERR"))) -> 0.035 | CK21: 0.035 | CL21: 0.0375 | CM21: 0.0325 | CN21: =+$F$30+CJ21 -> 0.075 | CO21: =$I$30+CJ21 -> 0.075 | CP21: =+NPV(CN21,CQ21:CV21) -> 0.75693344 | CQ21: =+BF21 -> 0.0368187 | CR21: =+BG21 -> 0.039027822 | CS21: =+BH21 -> 0.040979213 | CT21: =+BI21 -> 0.042618382 | CU21: =+BJ21 -> 0.043896933 | CV21: =+BK21 -> 0.91584965 | CY21: =Q21 -> 0.04 | CZ21: =S21 -> 0.02 | DB21: =CN21-CY21 -> 0.035 | DC21: =+CO21-CZ21 -> 0.055 | DE21: =+DB21/(1-$E21) -> 0.037634409 | DF21: =+DC21/(1-$E21) -> 0.059139785
B23: US | C23: Inflation | T23: {=+PRODUCT(1+D29:F29)^(0.333333333333333)-1} -> 0.022497963 | U23: {=+PRODUCT(1+D29:I29)^(1/6)-1} -> 0.021248218 | AL23: Rent Growth under base macro case | AU23: Cap rate relative to 10 yr | BW23: =+SUM(BW3:BW21) -> 0.62 | BX23: =+SUM(BX3:BX21) -> 2.82 | BY23: 1 | BZ23: =+SUM(BZ3:BZ21) -> 0 | CD23: =+SUM(CD3:CD21) -> 0.72 | CE23: =+SUM(CE3:CE21) -> 2.82 | CJ23: VERIFY THIS
C25: Scenario | D25: Base | F25: Scenarios | G25: Base | H25: High | I25: Low | AL25: 0.03 | AM25: 0.03 | AN25: 0.03 | AO25: 0.03 | AP25: 0.03 | AQ25: 0.03
AL26: 0.025 | AM26: 0.0225 | AN26: 0.02 | AO26: 0.02 | AP26: 0.02 | AQ26: 0.02
C27: Model Inputs | AL27: 0.01 | AM27: 0.01 | AN27: 0.01 | AO27: 0.01 | AP27: 0.01 | AQ27: 0.01
C28: GDP Growth
C29: Inflation | D29: =IF($D$25=$G$25,D35,IF($D$25=$H$25,D41,IF($D$25=$I$25,D47,"ERR"))) -> 0.025 | E29: =IF($D$25=$G$25,E35,IF($D$25=$H$25,E41,IF($D$25=$I$25,E47,"ERR"))) -> 0.0225 | F29: =IF($D$25=$G$25,F35,IF($D$25=$H$25,F41,IF($D$25=$I$25,F47,"ERR"))) -> 0.02 | G29: =IF($D$25=$G$25,G35,IF($D$25=$H$25,G41,IF($D$25=$I$25,G47,"ERR"))) -> 0.02 | H29: =IF($D$25=$G$25,H35,IF($D$25=$H$25,H41,IF($D$25=$I$25,H47,"ERR"))) -> 0.02 | I29: =IF($D$25=$G$25,I35,IF($D$25=$H$25,I41,IF($D$25=$I$25,I47,"ERR"))) -> 0.02 | AL29: =+D29 -> 0.025 | AM29: =+E29 -> 0.0225 | AN29: =+F29 -> 0.02 | AO29: =+G29 -> 0.02 | AP29: =+H29 -> 0.02 | AQ29: =+I29 -> 0.02
C30: 10 Year | D30: =IF($D$25=$G$25,D36,IF($D$25=$H$25,D42,IF($D$25=$I$25,D48,"ERR"))) -> 0.045 | E30: =IF($D$25=$G$25,E36,IF($D$25=$H$25,E42,IF($D$25=$I$25,E48,"ERR"))) -> 0.04 | F30: =IF($D$25=$G$25,F36,IF($D$25=$H$25,F42,IF($D$25=$I$25,F48,"ERR"))) -> 0.04 | G30: =IF($D$25=$G$25,G36,IF($D$25=$H$25,G42,IF($D$25=$I$25,G48,"ERR"))) -> 0.04 | H30: =IF($D$25=$G$25,H36,IF($D$25=$H$25,H42,IF($D$25=$I$25,H48,"ERR"))) -> 0.04 | I30: =IF($D$25=$G$25,I36,IF($D$25=$H$25,I42,IF($D$25=$I$25,I48,"ERR"))) -> 0.04
F32: =IF($D$25=$G$25,F37,IF($D$25=$H$25,F43,IF($D$25=$I$25,F49,"ERR"))) -> 0 | I32: =IF($D$25=$G$25,I37,IF($D$25=$H$25,I43,IF($D$25=$I$25,I49,"ERR"))) -> 0
C33: Base case
C34: GDP | D34: 0.025 | E34: 0.0225 | F34: 0.02 | G34: 0.02 | H34: 0.02 | I34: 0.02 | N34: 0.02
C35: Inflation baseline | D35: 0.025 | E35: 0.0225 | F35: 0.02 | G35: 0.02 | H35: 0.02 | I35: 0.02 | N35: 0.02
C36: 10 Year baseline | D36: =+E35+E34 -> 0.045 | E36: =+F35+F34 -> 0.04 | F36: =+G35+G34 -> 0.04 | G36: =+H35+H34 -> 0.04 | H36: =+I35+I34 -> 0.04 | I36: =+N35+N34 -> 0.04
C37: Cap rate adj to Treasury | F37: 0 | I37: 0
C39: High Interest Rate
C40: GDP | D40: 0.025 | E40: 0.0225 | F40: 0.02 | G40: 0.02 | H40: 0.02 | I40: 0.02 | N40: 0.02
C41: Inflation baseline | D41: 0.03 | E41: 0.03 | F41: 0.03 | G41: 0.03 | H41: 0.03 | I41: 0.03 | N41: 0.03
C42: 10 Year baseline | D42: =+E41+E40 -> 0.0525 | E42: =+F41+F40 -> 0.05 | F42: =+G41+G40 -> 0.05 | G42: =+H41+H40 -> 0.05 | H42: =+I41+I40 -> 0.05 | I42: =+N41+N40 -> 0.05
C43: Cap rate adj to Treasury | F43: -0.0025 | I43: -0.0025
C45: Low Interest Rate
C46: GDP | D46: 0.025 | E46: 0.0225 | F46: 0.02 | G46: 0.02 | H46: 0.02 | I46: 0.02 | N46: 0.02
C47: Inflation baseline | D47: 0.01 | E47: 0.01 | F47: 0.01 | G47: 0.01 | H47: 0.01 | I47: 0.01 | N47: 0.01
C48: 10 Year baseline | D48: =+E47+E46 -> 0.0325 | E48: =+F47+F46 -> 0.03 | F48: =+G47+G46 -> 0.03 | G48: =+H47+H46 -> 0.03 | H48: =+I47+I46 -> 0.03 | I48: =+N47+N46 -> 0.03
C49: Cap rate adj to Treasury | F49: 0.0025 | I49: 0.0025
A62: =+A61+1 -> 1 | B62: US | C62: Core - Ind | D62: 0.047 | E62: 0.138 | F62: =+D62*(1-E62) -> 0.040514 | H62: =DB62 -> 0.028986565 | I62: =DC62 -> 0.05 | K62: =+H62/(1-$E62) -> 0.033627106 | L62: =+I62/(1-$E62) -> 0.05800464 | N62: =+AL62 -> 0.056154466 | O62: =+AM62 -> 0.050284018 | P62: =+AN62 -> 0.045634433 | Q62: =+AO62 -> 0.041013435 | R62: =+AP62 -> 0.037301905 | S62: =+AQ62 -> 0.034296903 | T62: {=+PRODUCT(1+N62:P62)^(0.333333333333333)-1} -> 0.050682159 | U62: {=+PRODUCT(1+N62:S62)^(1/6)-1} -> 0.044087271 | W62: =Z62-($F62+T62) -> 0.17227303 | X62: =AA62-($F62+U62) -> -0.010293439 | Z62: =+IRR(AZ62:BC62) -> 0.26346919 | AA62: =+IRR(BE62:BK62) -> 0.074307833 | AC62: =+Z62++$BR62 -> 0.27446919 | AD62: =+AA62++$BR62 -> 0.085307833 | AF62: =+(AC62-$BM62*$BN62)/(1-$BM62) -> 0.29857687 | AG62: =+(AD62-$BM62*$BN62)/(1-$BM62) -> 0.088397592 | AI62: =AF62-$BS62 -> 0.28857687 | AJ62: =AG62-$BS62 -> 0.078397592 | AL62: 0.056154466 | AM62: 0.050284018 | AN62: 0.045634433 | AO62: 0.041013435 | AP62: 0.037301905 | AQ62: 0.034296903 | AR62: {=+PRODUCT(1+AL62:AN62)^(0.333333333333333)-1} -> 0.050682159 | AS62: {=+PRODUCT(1+AL62:AQ62)^(1/6)-1} -> 0.044087271 | AU62: -0.006606 | AV62: 0 | AX62: 0.015 | AZ62: =-1 -> -1 | BA62: =+F62*(1+N62) -> 0.042789042 | BB62: =+BA62*(1+O62) -> 0.044940647 | BC62: =+BB62*(1+P62)+(BB62*(1+P62))*(1+E62)/H62 -> 1.891857 | BE62: -1 | BF62: =+F62*(1+N62) -> 0.042789042 | BG62: =+BF62*(1+O62) -> 0.044940647 | BH62: =+BG62*(1+P62) -> 0.046991488 | BI62: =+BH62*(1+Q62) -> 0.04891877 | BJ62: =+BI62*(1+R62) -> 0.050743534 | BK62: =+BJ62*(1+S62)+BJ62*(1+S62)*(1+E62)/I62 -> 1.247017 | BM62: 0.1 | BN62: =IF($D$25="Base",BO62,IF(D$25="High",BP62,IF(D$25="Low",BQ62,"ERR"))) -> 0.0575 | BO62: 0.0575 | BP62: 0.06 | BQ62: 0.055 | BR62: 0.011 | BS62: 0.01 | BU62: =RANK(AI62,AI$3:AI$21) -> #N/A | BV62: =+$A62 -> 1 | BW62: 0 | BX62: 0.3 | CB62: =RANK(AJ62,AJ$3:AJ$21) -> #N/A | CC62: =+$A62 -> 1 | CD62: 0 | CE62: 0.3 | CJ62: =IF($D$25="Base",CK62,IF($D$25="High",CL62,IF($D$25="Low",CM62,"ERR"))) -> 0.03 | CK62: 0.03 | CL62: 0.0325 | CM62: 0.0275 | CN62: =+$F$30+CJ62 -> 0.07 | CO62: =$I$30+CJ62 -> 0.07 | CP62: =+NPV(CN62,CQ62:CV62) -> 1.0220411 | CQ62: =+BF62 -> 0.042789042 | CR62: =+BG62 -> 0.044940647 | CS62: =+BH62 -> 0.046991488 | CT62: =+BI62 -> 0.04891877 | CU62: =+BJ62 -> 0.050743534 | CV62: =+BK62 -> 1.247017 | CY62: =Q62 -> 0.041013435 | CZ62: =S62 -> 0.034296903 | DB62: =CN62-CY62 -> 0.028986565 | DC62: 0.05 | DE62: =+DB62/(1-$E62) -> 0.033627106 | DF62: =+DC62/(1-$E62) -> 0.05800464

Sheet compare
D1: Low | E1: Base | F1: High | M1: Low | N1: Base | O1: High
A2: SectorIdentifier | B2: Region | C2: Profile | D2: =#REF! -> #REF! | E2: =Base!U23 -> 0.021248218 | F2: =#REF! -> #REF!
A3: 1 | B3: US | C3: Core - Res | D3: =#REF! -> #REF! | E3: =Base!U3 -> 0.022635339 | F3: =+#REF! -> #REF! | H3: =D3-E3 -> #REF! | I3: =F3-E3 -> #REF! | M3: =+#REF! -> #REF! | N3: =Base!AD3 -> 0.08550855 | O3: =+#REF! -> #REF!
A4: =+A3+1 -> 2 | B4: US | C4: Core - Ind | D4: =#REF! -> #REF! | E4: =Base!U4 -> 0.043117707 | F4: =+#REF! -> #REF! | H4: =D4-E4 -> #REF! | I4: =F4-E4 -> #REF!
A5: =+A4+1 -> 3 | B5: US | C5: Core - Off | D5: =#REF! -> #REF! | E5: =Base!U5 -> -0.00041934372 | F5: =+#REF! -> #REF! | H5: =D5-E5 -> #REF! | I5: =F5-E5 -> #REF!
A6: =+A5+1 -> 4 | B6: US | C6: Core - Retail | D6: =#REF! -> #REF! | E6: =Base!U6 -> 0.019156756 | F6: =+#REF! -> #REF! | H6: =D6-E6 -> #REF! | I6: =F6-E6 -> #REF!
A7: =+A6+1 -> 5 | B7: US | C7: Core-Plus - Res | D7: =#REF! -> #REF! | E7: =Base!U7 -> 0.021102179 | F7: =+#REF! -> #REF! | H7: =D7-E7 -> #REF! | I7: =F7-E7 -> #REF!
A8: =+A7+1 -> 6 | B8: US | C8: Core-Plus - Ind | D8: =#REF! -> #REF! | E8: =Base!U8 -> 0.044056458 | F8: =+#REF! -> #REF! | H8: =D8-E8 -> #REF! | I8: =F8-E8 -> #REF!
A9: =+A8+1 -> 7 | B9: US | C9: Core-Plus - Off | D9: =#REF! -> #REF! | E9: =Base!U9 -> 0.001770307 | F9: =+#REF! -> #REF! | H9: =D9-E9 -> #REF! | I9: =F9-E9 -> #REF!
A10: =+A9+1 -> 8 | B10: US | C10: Core-Plus - Ret | D10: =#REF! -> #REF! | E10: =Base!U10 -> 0.019156756 | F10: =+#REF! -> #REF! | H10: =D10-E10 -> #REF! | I10: =F10-E10 -> #REF!
A11: =+A10+1 -> 9 | B11: US | C11: Data Center | D11: =#REF! -> #REF! | E11: =Base!U11 -> 0.048115354 | F11: =+#REF! -> #REF! | H11: =D11-E11 -> #REF! | I11: =F11-E11 -> #REF!
A12: =+A11+1 -> 10 | B12: US | C12: Single-Family Rental | D12: =#REF! -> #REF! | E12: =Base!U12 -> 0.042478226 | F12: =+#REF! -> #REF! | H12: =D12-E12 -> #REF! | I12: =F12-E12 -> #REF!
A13: =+A12+1 -> 11 | B13: US | C13: Cold Storage | D13: =#REF! -> #REF! | E13: =Base!U13 -> 0.052962115 | F13: =+#REF! -> #REF! | H13: =D13-E13 -> #REF! | I13: =F13-E13 -> #REF!
A14: =+A13+1 -> 12 | B14: US | C14: Senior Housing | D14: =#REF! -> #REF! | E14: =Base!U14 -> 0.051014296 | F14: =+#REF! -> #REF! | H14: =D14-E14 -> #REF! | I14: =F14-E14 -> #REF!
A15: =+A14+1 -> 13 | B15: US | C15: Student Housing | D15: =#REF! -> #REF! | E15: =Base!U15 -> 0.026659892 | F15: =+#REF! -> #REF! | H15: =D15-E15 -> #REF! | I15: =F15-E15 -> #REF!
... A21: =+A20+1 -> 19 | B21: US | C21: IOS | D21: =#REF! -> #REF! | E21: =Base!U21 -> 0.044860424 | F21: =+#REF! -> #REF! | H21: =D21-E21 -> #REF! | I21: =F21-E21 -> #REF!

Sheet tmp
A1: SI | B1: =+Base!C2 -> Profile | C1: Std Dev | D1: =+Base!AI2 -> 3 YR IRR | E1: Min Wt | F1: Max Wt | G1: Sharp ratio | H1: Final Wt | I1: Pert IRR | J1: Pert Sharp
A2: =+Base!A3 -> 1 | B2: =+Base!C3 -> Core - Res | C2: =Base!AX3 -> 0.01 | D2: =+Base!AI3 -> 0.25090456 | E2: 0 | F2: 0.17 | G2: =+D2/C2 -> 25.090456 | H2: 0.17 | I2: =_xlfn.PERCENTRANK.INC($D$2:$D$20,D2) -> 0.833 | J2: =_xlfn.PERCENTRANK.INC($G$2:$G$20,G2) -> 0.944 | L2: 0.17 | M2: 4.2811786e-17
A3: =+Base!A4 -> 2 | B3: =+Base!C4 -> Core - Ind | C3: =Base!AX4 -> 0.015 | D3: =+Base!AI4 -> 0.14946424 | E3: 0 | F3: 0.17 | G3: =+D3/C3 -> 9.964283 | H3: 0.089489355 | I3: =_xlfn.PERCENTRANK.INC($D$2:$D$20,D3) -> 0.611 | J3: =_xlfn.PERCENTRANK.INC($G$2:$G$20,G3) -> 0.611 | L3: 0.089489355 | M3: 0.17
A4: =+Base!A5 -> 3 | B4: =+Base!C5 -> Core - Off | C4: =Base!AX5 -> 0.03 | D4: =+Base!AI5 -> -0.077132978 | E4: 0 | F4: 0.05 | G4: =+D4/C4 -> -2.5710993 | H4: 3.7160686e-18 | I4: =_xlfn.PERCENTRANK.INC($D$2:$D$20,D4) -> 0.055 | J4: =_xlfn.PERCENTRANK.INC($G$2:$G$20,G4) -> 0 | L4: 3.7160686e-18 | M4: 0
A5: =+Base!A6 -> 4 | B5: =+Base!C6 -> Core - Retail | C5: =Base!AX6 -> 0.02 | D5: =+Base!AI6 -> 0.073853981 | E5: 0 | F5: 0.07 | G5: =+D5/C5 -> 3.6926991 | H5: 1.0249305e-17 | I5: =_xlfn.PERCENTRANK.INC($D$2:$D$20,D5) -> 0.222 | J5: =_xlfn.PERCENTRANK.INC($G$2:$G$20,G5) -> 0.222 | L5: 1.0249305e-17 | M5: 1.5955716e-16
A6: =+Base!A7 -> 5 | B6: =+Base!C7 -> Core-Plus - Res | C6: =Base!AX7 -> 0.0125 | D6: =+Base!AI7 -> 0.26802966 | E6: 0.1 | F6: 0.17 | G6: =+D6/C6 -> 21.442373 | H6: 0.17 | I6: =_xlfn.PERCENTRANK.INC($D$2:$D$20,D6) -> 0.888 | J6: =_xlfn.PERCENTRANK.INC($G$2:$G$20,G6) -> 0.833 | L6: 0.17 | M6: 0.1
A7: =+Base!A8 -> 6 | B7: =+Base!C8 -> Core-Plus - Ind | C7: =Base!AX8 -> 0.0175 | D7: =+Base!AI8 -> 0.13945853 | E7: 0.1 | F7: 0.17 | G7: =+D7/C7 -> 7.969059 | H7: 0.1 | I7: =_xlfn.PERCENTRANK.INC($D$2:$D$20,D7) -> 0.555 | J7: =_xlfn.PERCENTRANK.INC($G$2:$G$20,G7) -> 0.444 | L7: 0.1 | M7: 0.17
A8: =+Base!A9 -> 7 | B8: =+Base!C9 -> Core-Plus - Off | C8: =Base!AX9 -> 0.035 | D8: =+Base!AI9 -> -0.087336844 | E8: 0.02 | F8: 0.05 | G8: =+D8/C8 -> -2.4953384 | H8: 0.02 | I8: =_xlfn.PERCENTRANK.INC($D$2:$D$20,D8) -> 0 | J8: =_xlfn.PERCENTRANK.INC($G$2:$G$20,G8) -> 0.055 | L8: 0.02 | M8: 0.02
A9: =+Base!A10 -> 8 | B9: =+Base!C10 -> Core-Plus - Ret | C9: =Base!AX10 -> 0.025 | D9: =+Base!AI10 -> 0.098085745 | E9: 0.03 | F9: 0.07 | G9: =+D9/C9 -> 3.9234298 | H9: 0.03 | I9: =_xlfn.PERCENTRANK.INC($D$2:$D$20,D9) -> 0.333 | J9: =_xlfn.PERCENTRANK.INC($G$2:$G$20,G9) -> 0.277 | L9: 0.03 | M9: 0.03
A10: =+Base!A11 -> 9 | B10: =+Base!C11 -> Data Center | C10: =Base!AX11 -> 0.015 | D10: =+Base!AI11 -> 0.38329056 | E10: 0 | F10: 0.07 | G10: =+D10/C10 -> 25.552704 | H10: 0.07 | I10: =_xlfn.PERCENTRANK.INC($D$2:$D$20,D10) -> 1 | J10: =_xlfn.PERCENTRANK.INC($G$2:$G$20,G10) -> 1 | L10: 0.07 | M10: 0.07
A11: =+Base!A12 -> 10 | B11: =+Base!C12 -> Single-Family Rental | C11: =Base!AX12 -> 0.015 | D11: =+Base!AI12 -> 0.22370484 | E11: 0 | F11: 0.1 | G11: =+D11/C11 -> 14.913656 | H11: 0.1 | I11: =_xlfn.PERCENTRANK.INC($D$2:$D$20,D11) -> 0.777 | J11: =_xlfn.PERCENTRANK.INC($G$2:$G$20,G11) -> 0.722 | L11: 0.1 | M11: 0.1
A12: =+Base!A13 -> 11 | B12: =+Base!C13 -> Cold Storage | C12: =Base!AX13 -> 0.015 | D12: =+Base!AI13 -> 0.12203342 | E12: 0 | F12: 0.05 | G12: =+D12/C12 -> 8.1355614 | H12: 0.049999997 | I12: =_xlfn.PERCENTRANK.INC($D$2:$D$20,D12) -> 0.444 | J12: =_xlfn.PERCENTRANK.INC($G$2:$G$20,G12) -> 0.5 | L12: 0.049999997 | M12: 0.05
A13: =+Base!A14 -> 12 | B13: =+Base!C14 -> Senior Housing | C13: =Base!AX14 -> 0.0125 | D13: =+Base!AI14 -> 0.28656678 | E13: 0 | F13: 0.05 | G13: =+D13/C13 -> 22.925342 | H13: 0.05 | I13: =_xlfn.PERCENTRANK.INC($D$2:$D$20,D13) -> 0.944 | J13: =_xlfn.PERCENTRANK.INC($G$2:$G$20,G13) -> 0.888 | L13: 0.05 | M13: 0.05
... A20: =+Base!A21 -> 19 | B20: =+Base!C21 -> IOS | C20: =Base!AX21 -> 0.0175 | D20: =+Base!AI21 -> 0.10913092 | E20: 0 | F20: 0.05 | G20: =+D20/C20 -> 6.2360524 | H20: 2.01688e-17 | I20: =_xlfn.PERCENTRANK.INC($D$2:$D$20,D20) -> 0.388 | J20: =_xlfn.PERCENTRANK.INC($G$2:$G$20,G20) -> 0.388 | L20: 2.01688e-17 | M20: 0.05
A22: =+COUNT(A2:A20) -> 19
D24: Port Ret | E24: =SUMPRODUCT(D2:D20,H2:H20) -> 0.20709617 | F24: 0.069779102
D25: Port Std | E25: 0.0175 | F25: 0.014167331 | L25: 0.014 | M25: 0.0175
D26: Count | E26: 8
D27: Smallest | E27: 0.03

Sheet port3YR
A1: 3 YR
A2: Rank | B2: SI | C2: Min | D2: Max | E2: Step1 | F2: Cum | G2: Step2 | I2: Port | J2: Test
A3: 1 | B3: =VLOOKUP(A3,Base!$BU$3:$BV$21,2,FALSE) -> 9 | C3: =+VLOOKUP(B3,Base!$BV$3:$BW$21,2,FALSE) -> 0.05 | D3: =+VLOOKUP(B3,Base!$BV$3:$BX$21,3,FALSE) -> 0.15 | E3: =+($E$26-1)*C3 -> 0.05 | F3: =+E3 -> 0.05 | G3: =+IF(F3<(1-$C$23),E3,IF(((1-$C$23)-F2)>0,((1-$C$23)-F2),0)) -> 0.05 | H3: =+VLOOKUP(B3,Base!$A$3:$C$21,3,FALSE) -> Data Center | I3: =+C3+G3 -> 0.1 | J3: =+IF(I3>D3,1,0) -> 0
A4: =+A3+1 -> 2 | B4: =VLOOKUP(A4,Base!$BU$3:$BV$21,2,FALSE) -> 12 | C4: =+VLOOKUP(B4,Base!$BV$3:$BW$21,2,FALSE) -> 0.02 | D4: =+VLOOKUP(B4,Base!$BV$3:$BX$21,3,FALSE) -> 0.1 | E4: =+($E$26-1)*C4 -> 0.02 | F4: =+F3+E4 -> 0.07 | G4: =+IF(F4<(1-$C$23),E4,IF(((1-$C$23)-F3)>0,((1-$C$23)-F3),0)) -> 0.02 | H4: =+VLOOKUP(B4,Base!$A$3:$C$21,3,FALSE) -> Senior Housing | I4: =+C4+G4 -> 0.04 | J4: =+IF(I4>D4,1,0) -> 0
A5: =+A4+1 -> 3 | B5: =VLOOKUP(A5,Base!$BU$3:$BV$21,2,FALSE) -> 5 | C5: =+VLOOKUP(B5,Base!$BV$3:$BW$21,2,FALSE) -> 0.15 | D5: =+VLOOKUP(B5,Base!$BV$3:$BX$21,3,FALSE) -> 0.3 | E5: =+($E$26-1)*C5 -> 0.15 | F5: =+F4+E5 -> 0.22 | G5: =+IF(F5<(1-$C$23),E5,IF(((1-$C$23)-F4)>0,((1-$C$23)-F4),0)) -> 0.15 | H5: =+VLOOKUP(B5,Base!$A$3:$C$21,3,FALSE) -> Core-Plus - Res | I5: =+C5+G5 -> 0.3 | J5: =+IF(I5>D5,1,0) -> 0
A6: =+A5+1 -> 4 | B6: =VLOOKUP(A6,Base!$BU$3:$BV$21,2,FALSE) -> 1 | C6: =+VLOOKUP(B6,Base!$BV$3:$BW$21,2,FALSE) -> 0 | D6: =+VLOOKUP(B6,Base!$BV$3:$BX$21,3,FALSE) -> 0.3 | E6: =+($E$26-1)*C6 -> 0 | F6: =+F5+E6 -> 0.22 | G6: =+IF(F6<(1-$C$23),E6,IF(((1-$C$23)-F5)>0,((1-$C$23)-F5),0)) -> 0 | H6: =+VLOOKUP(B6,Base!$A$3:$C$21,3,FALSE) -> Core - Res | I6: =+C6+G6 -> 0 | J6: =+IF(I6>D6,1,0) -> 0
A7: =+A6+1 -> 5 | B7: =VLOOKUP(A7,Base!$BU$3:$BV$21,2,FALSE) -> 10 | C7: =+VLOOKUP(B7,Base!$BV$3:$BW$21,2,FALSE) -> 0.05 | D7: =+VLOOKUP(B7,Base!$BV$3:$BX$21,3,FALSE) -> 0.15 | E7: =+($E$26-1)*C7 -> 0.05 | F7: =+F6+E7 -> 0.27 | G7: =+IF(F7<(1-$C$23),E7,IF(((1-$C$23)-F6)>0,((1-$C$23)-F6),0)) -> 0.05 | H7: =+VLOOKUP(B7,Base!$A$3:$C$21,3,FALSE) -> Single-Family Rental | I7: =+C7+G7 -> 0.1 | J7: =+IF(I7>D7,1,0) -> 0
A8: =+A7+1 -> 6 | B8: =VLOOKUP(A8,Base!$BU$3:$BV$21,2,FALSE) -> 14 | C8: =+VLOOKUP(B8,Base!$BV$3:$BW$21,2,FALSE) -> 0.01 | D8: =+VLOOKUP(B8,Base!$BV$3:$BX$21,3,FALSE) -> 0.07 | E8: =+($E$26-1)*C8 -> 0.01 | F8: =+F7+E8 -> 0.28 | G8: =+IF(F8<(1-$C$23),E8,IF(((1-$C$23)-F7)>0,((1-$C$23)-F7),0)) -> 0.01 | H8: =+VLOOKUP(B8,Base!$A$3:$C$21,3,FALSE) -> Affordable Housing | I8: =+C8+G8 -> 0.02 | J8: =+IF(I8>D8,1,0) -> 0
A9: =+A8+1 -> 7 | B9: =VLOOKUP(A9,Base!$BU$3:$BV$21,2,FALSE) -> 13 | C9: =+VLOOKUP(B9,Base!$BV$3:$BW$21,2,FALSE) -> 0.02 | D9: =+VLOOKUP(B9,Base!$BV$3:$BX$21,3,FALSE) -> 0.1 | E9: =+($E$26-1)*C9 -> 0.02 | F9: =+F8+E9 -> 0.3 | G9: =+IF(F9<(1-$C$23),E9,IF(((1-$C$23)-F8)>0,((1-$C$23)-F8),0)) -> 0.02 | H9: =+VLOOKUP(B9,Base!$A$3:$C$21,3,FALSE) -> Student Housing | I9: =+C9+G9 -> 0.04 | J9: =+IF(I9>D9,1,0) -> 0
A10: =+A9+1 -> 8 | B10: =VLOOKUP(A10,Base!$BU$3:$BV$21,2,FALSE) -> 2 | C10: =+VLOOKUP(B10,Base!$BV$3:$BW$21,2,FALSE) -> 0 | D10: =+VLOOKUP(B10,Base!$BV$3:$BX$21,3,FALSE) -> 0.3 | E10: =+($E$26-1)*C10 -> 0 | F10: =+F9+E10 -> 0.3 | G10: =+IF(F10<(1-$C$23),E10,IF(((1-$C$23)-F9)>0,((1-$C$23)-F9),0)) -> 0 | H10: =+VLOOKUP(B10,Base!$A$3:$C$21,3,FALSE) -> Core - Ind | I10: =+C10+G10 -> 0 | J10: =+IF(I10>D10,1,0) -> 0
A11: =+A10+1 -> 9 | B11: =VLOOKUP(A11,Base!$BU$3:$BV$21,2,FALSE) -> 6 | C11: =+VLOOKUP(B11,Base!$BV$3:$BW$21,2,FALSE) -> 0.15 | D11: =+VLOOKUP(B11,Base!$BV$3:$BX$21,3,FALSE) -> 0.3 | E11: =+($E$26-1)*C11 -> 0.15 | F11: =+F10+E11 -> 0.45 | G11: =+IF(F11<(1-$C$23),E11,IF(((1-$C$23)-F10)>0,((1-$C$23)-F10),0)) -> 0.08 | H11: =+VLOOKUP(B11,Base!$A$3:$C$21,3,FALSE) -> Core-Plus - Ind | I11: =+C11+G11 -> 0.23 | J11: =+IF(I11>D11,1,0) -> 0
A12: =+A11+1 -> 10 | B12: =VLOOKUP(A12,Base!$BU$3:$BV$21,2,FALSE) -> 16 | C12: =+VLOOKUP(B12,Base!$BV$3:$BW$21,2,FALSE) -> 0.01 | D12: =+VLOOKUP(B12,Base!$BV$3:$BX$21,3,FALSE) -> 0.07 | E12: =+($E$26-1)*C12 -> 0.01 | F12: =+F11+E12 -> 0.46 | G12: =+IF(F12<(1-$C$23),E12,IF(((1-$C$23)-F11)>0,((1-$C$23)-F11),0)) -> 0 | H12: =+VLOOKUP(B12,Base!$A$3:$C$21,3,FALSE) -> Medical Office | I12: =+C12+G12 -> 0.01 | J12: =+IF(I12>D12,1,0) -> 0
A13: =+A12+1 -> 11 | B13: =VLOOKUP(A13,Base!$BU$3:$BV$21,2,FALSE) -> 11 | C13: =+VLOOKUP(B13,Base!$BV$3:$BW$21,2,FALSE) -> 0.02 | D13: =+VLOOKUP(B13,Base!$BV$3:$BX$21,3,FALSE) -> 0.1 | E13: =+($E$26-1)*C13 -> 0.02 | F13: =+F12+E13 -> 0.48 | G13: =+IF(F13<(1-$C$23),E13,IF(((1-$C$23)-F12)>0,((1-$C$23)-F12),0)) -> 0 | H13: =+VLOOKUP(B13,Base!$A$3:$C$21,3,FALSE) -> Cold Storage | I13: =+C13+G13 -> 0.02 | J13: =+IF(I13>D13,1,0) -> 0
A14: =+A13+1 -> 12 | B14: =VLOOKUP(A14,Base!$BU$3:$BV$21,2,FALSE) -> 19 | C14: =+VLOOKUP(B14,Base!$BV$3:$BW$21,2,FALSE) -> 0.01 | D14: =+VLOOKUP(B14,Base!$BV$3:$BX$21,3,FALSE) -> 0.07 | E14: =+($E$26-1)*C14 -> 0.01 | F14: =+F13+E14 -> 0.49 | G14: =+IF(F14<(1-$C$23),E14,IF(((1-$C$23)-F13)>0,((1-$C$23)-F13),0)) -> 0 | H14: =+VLOOKUP(B14,Base!$A$3:$C$21,3,FALSE) -> IOS | I14: =+C14+G14 -> 0.01 | J14: =+IF(I14>D14,1,0) -> 0
A15: =+A14+1 -> 13 | B15: =VLOOKUP(A15,Base!$BU$3:$BV$21,2,FALSE) -> 8 | C15: =+VLOOKUP(B15,Base!$BV$3:$BW$21,2,FALSE) -> 0.05 | D15: =+VLOOKUP(B15,Base!$BV$3:$BX$21,3,FALSE) -> 0.15 | E15: =+($E$26-1)*C15 -> 0.05 | F15: =+F14+E15 -> 0.54 | G15: =+IF(F15<(1-$C$23),E15,IF(((1-$C$23)-F14)>0,((1-$C$23)-F14),0)) -> 0 | H15: =+VLOOKUP(B15,Base!$A$3:$C$21,3,FALSE) -> Core-Plus - Ret | I15: =+C15+G15 -> 0.05 | J15: =+IF(I15>D15,1,0) -> 0
... A21: =+A20+1 -> 19 | B21: =VLOOKUP(A21,Base!$BU$3:$BV$21,2,FALSE) -> 7 | C21: =+VLOOKUP(B21,Base!$BV$3:$BW$21,2,FALSE) -> 0.05 | D21: =+VLOOKUP(B21,Base!$BV$3:$BX$21,3,FALSE) -> 0.15 | E21: =+($E$26-1)*C21 -> 0.05 | F21: =+F20+E21 -> 0.62 | G21: =+IF(F21<(1-$C$23),E21,IF(((1-$C$23)-F20)>0,((1-$C$23)-F20),0)) -> 0 | H21: =+VLOOKUP(B21,Base!$A$3:$C$21,3,FALSE) -> Core-Plus - Off | I21: =+C21+G21 -> 0.05 | J21: =+IF(I21>D21,1,0) -> 0
C23: =SUM(C3:C21) -> 0.62 | I23: =SUM(I3:I21) -> 1 | J23: =+SUM(J3:J21) -> 0
D26: Diversification factor (higher means more concentrated) | E26: 2 | F26: =+IF(E26<E27,"ERROR",) -> 0
D27: Min value | E27: =1/C23 -> 1.6129032
B30: SI | D30: Port | E30: 3 YR IRR
B31: 1 | C31: =+VLOOKUP(B31,Base!$A$3:$C$21,3,FALSE) -> Core - Res | D31: =+VLOOKUP(B31,$B$3:$I$21,8,FALSE) -> 0 | E31: =+Base!Z3 -> 0.25590456
B32: =+B31+1 -> 2 | C32: =+VLOOKUP(B32,Base!$A$3:$C$21,3,FALSE) -> Core - Ind | D32: =+VLOOKUP(B32,$B$3:$I$21,8,FALSE) -> 0 | E32: =+Base!Z4 -> 0.15196424
B33: =+B32+1 -> 3 | C33: =+VLOOKUP(B33,Base!$A$3:$C$21,3,FALSE) -> Core - Off | D33: =+VLOOKUP(B33,$B$3:$I$21,8,FALSE) -> 0 | E33: =+Base!Z5 -> -0.067132978
B34: =+B33+1 -> 4 | C34: =+VLOOKUP(B34,Base!$A$3:$C$21,3,FALSE) -> Core - Retail | D34: =+VLOOKUP(B34,$B$3:$I$21,8,FALSE) -> 0 | E34: =+Base!Z6 -> 0.081353981
B35: =+B34+1 -> 5 | C35: =+VLOOKUP(B35,Base!$A$3:$C$21,3,FALSE) -> Core-Plus - Res | D35: =+VLOOKUP(B35,$B$3:$I$21,8,FALSE) -> 0.3 | E35: =+Base!Z7 -> 0.27052966
B36: =+B35+1 -> 6 | C36: =+VLOOKUP(B36,Base!$A$3:$C$21,3,FALSE) -> Core-Plus - Ind | D36: =+VLOOKUP(B36,$B$3:$I$21,8,FALSE) -> 0.23 | E36: =+Base!Z8 -> 0.14445853
B37: =+B36+1 -> 7 | C37: =+VLOOKUP(B37,Base!$A$3:$C$21,3,FALSE) -> Core-Plus - Off | D37: =+VLOOKUP(B37,$B$3:$I$21,8,FALSE) -> 0.05 | E37: =+Base!Z9 -> -0.074836844
B38: =+B37+1 -> 8 | C38: =+VLOOKUP(B38,Base!$A$3:$C$21,3,FALSE) -> Core-Plus - Ret | D38: =+VLOOKUP(B38,$B$3:$I$21,8,FALSE) -> 0.05 | E38: =+Base!Z10 -> 0.10808575
B39: =+B38+1 -> 9 | C39: =+VLOOKUP(B39,Base!$A$3:$C$21,3,FALSE) -> Data Center | D39: =+VLOOKUP(B39,$B$3:$I$21,8,FALSE) -> 0.1 | E39: =+Base!Z11 -> 0.38579056
B40: =+B39+1 -> 10 | C40: =+VLOOKUP(B40,Base!$A$3:$C$21,3,FALSE) -> Single-Family Rental | D40: =+VLOOKUP(B40,$B$3:$I$21,8,FALSE) -> 0.1 | E40: =+Base!Z12 -> 0.22870484
B41: =+B40+1 -> 11 | C41: =+VLOOKUP(B41,Base!$A$3:$C$21,3,FALSE) -> Cold Storage | D41: =+VLOOKUP(B41,$B$3:$I$21,8,FALSE) -> 0.02 | E41: =+Base!Z13 -> 0.12953342
B42: =+B41+1 -> 12 | C42: =+VLOOKUP(B42,Base!$A$3:$C$21,3,FALSE) -> Senior Housing | D42: =+VLOOKUP(B42,$B$3:$I$21,8,FALSE) -> 0.04 | E42: =+Base!Z14 -> 0.29406678
B43: =+B42+1 -> 13 | C43: =+VLOOKUP(B43,Base!$A$3:$C$21,3,FALSE) -> Student Housing | D43: =+VLOOKUP(B43,$B$3:$I$21,8,FALSE) -> 0.04 | E43: =+Base!Z15 -> 0.16214525
... B49: =+B48+1 -> 19 | C49: =+VLOOKUP(B49,Base!$A$3:$C$21,3,FALSE) -> IOS | D49: =+VLOOKUP(B49,$B$3:$I$21,8,FALSE) -> 0.01 | E49: =+Base!Z21 -> 0.11413092
E51: =+SUMPRODUCT(D31:D49,E31:E49) -> 0.20682023

Sheet port6YR
A1: 3 YR
A2: Rank | B2: SI | C2: Min | D2: Max | E2: Step1 | F2: Cum | G2: Step2 | I2: Port | J2: Test
A3: 1 | B3: =VLOOKUP(A3,Base!$CB$3:$CC$21,2,FALSE) -> 14 | C3: =+VLOOKUP(B3,Base!$CC$3:$CD$21,2,FALSE) -> 0.01 | D3: =+VLOOKUP(B3,Base!$CC$3:$CE$21,3,FALSE) -> 0.07 | E3: =+($E$26-1)*C3 -> 0.025 | F3: =+E3 -> 0.025 | G3: =+IF(F3<(1-$C$23),E3,IF(((1-$C$23)-F2)>0,((1-$C$23)-F2),0)) -> 0.025 | H3: =+VLOOKUP(B3,Base!$A$3:$C$21,3,FALSE) -> Affordable Housing | I3: =+C3+G3 -> 0.035 | J3: =+IF(I3>D3,1,0) -> 0
A4: =+A3+1 -> 2 | B4: =VLOOKUP(A4,Base!$CB$3:$CC$21,2,FALSE) -> 12 | C4: =+VLOOKUP(B4,Base!$CC$3:$CD$21,2,FALSE) -> 0.02 | D4: =+VLOOKUP(B4,Base!$CC$3:$CE$21,3,FALSE) -> 0.1 | E4: =+($E$26-1)*C4 -> 0.05 | F4: =+F3+E4 -> 0.075 | G4: =+IF(F4<(1-$C$23),E4,IF(((1-$C$23)-F3)>0,((1-$C$23)-F3),0)) -> 0.05 | H4: =+VLOOKUP(B4,Base!$A$3:$C$21,3,FALSE) -> Senior Housing | I4: =+C4+G4 -> 0.07 | J4: =+IF(I4>D4,1,0) -> 0
A5: =+A4+1 -> 3 | B5: =VLOOKUP(A5,Base!$CB$3:$CC$21,2,FALSE) -> 9 | C5: =+VLOOKUP(B5,Base!$CC$3:$CD$21,2,FALSE) -> 0.05 | D5: =+VLOOKUP(B5,Base!$CC$3:$CE$21,3,FALSE) -> 0.15 | E5: =+($E$26-1)*C5 -> 0.125 | F5: =+F4+E5 -> 0.2 | G5: =+IF(F5<(1-$C$23),E5,IF(((1-$C$23)-F4)>0,((1-$C$23)-F4),0)) -> 0.125 | H5: =+VLOOKUP(B5,Base!$A$3:$C$21,3,FALSE) -> Data Center | I5: =+C5+G5 -> 0.175 | J5: =+IF(I5>D5,1,0) -> 1
A6: =+A5+1 -> 4 | B6: =VLOOKUP(A6,Base!$CB$3:$CC$21,2,FALSE) -> 8 | C6: =+VLOOKUP(B6,Base!$CC$3:$CD$21,2,FALSE) -> 0.05 | D6: =+VLOOKUP(B6,Base!$CC$3:$CE$21,3,FALSE) -> 0.15 | E6: =+($E$26-1)*C6 -> 0.125 | F6: =+F5+E6 -> 0.325 | G6: =+IF(F6<(1-$C$23),E6,IF(((1-$C$23)-F5)>0,((1-$C$23)-F5),0)) -> 0.08 | H6: =+VLOOKUP(B6,Base!$A$3:$C$21,3,FALSE) -> Core-Plus - Ret | I6: =+C6+G6 -> 0.13 | J6: =+IF(I6>D6,1,0) -> 0
A7: =+A6+1 -> 5 | B7: =VLOOKUP(A7,Base!$CB$3:$CC$21,2,FALSE) -> 13 | C7: =+VLOOKUP(B7,Base!$CC$3:$CD$21,2,FALSE) -> 0.02 | D7: =+VLOOKUP(B7,Base!$CC$3:$CE$21,3,FALSE) -> 0.1 | E7: =+($E$26-1)*C7 -> 0.05 | F7: =+F6+E7 -> 0.375 | G7: =+IF(F7<(1-$C$23),E7,IF(((1-$C$23)-F6)>0,((1-$C$23)-F6),0)) -> 0 | H7: =+VLOOKUP(B7,Base!$A$3:$C$21,3,FALSE) -> Student Housing | I7: =+C7+G7 -> 0.02 | J7: =+IF(I7>D7,1,0) -> 0
A8: =+A7+1 -> 6 | B8: =VLOOKUP(A8,Base!$CB$3:$CC$21,2,FALSE) -> 10 | C8: =+VLOOKUP(B8,Base!$CC$3:$CD$21,2,FALSE) -> 0.05 | D8: =+VLOOKUP(B8,Base!$CC$3:$CE$21,3,FALSE) -> 0.15 | E8: =+($E$26-1)*C8 -> 0.125 | F8: =+F7+E8 -> 0.5 | G8: =+IF(F8<(1-$C$23),E8,IF(((1-$C$23)-F7)>0,((1-$C$23)-F7),0)) -> 0 | H8: =+VLOOKUP(B8,Base!$A$3:$C$21,3,FALSE) -> Single-Family Rental | I8: =+C8+G8 -> 0.05 | J8: =+IF(I8>D8,1,0) -> 0
A9: =+A8+1 -> 7 | B9: =VLOOKUP(A9,Base!$CB$3:$CC$21,2,FALSE) -> 5 | C9: =+VLOOKUP(B9,Base!$CC$3:$CD$21,2,FALSE) -> 0.2 | D9: =+VLOOKUP(B9,Base!$CC$3:$CE$21,3,FALSE) -> 0.3 | E9: =+($E$26-1)*C9 -> 0.5 | F9: =+F8+E9 -> 1 | G9: =+IF(F9<(1-$C$23),E9,IF(((1-$C$23)-F8)>0,((1-$C$23)-F8),0)) -> 0 | H9: =+VLOOKUP(B9,Base!$A$3:$C$21,3,FALSE) -> Core-Plus - Res | I9: =+C9+G9 -> 0.2 | J9: =+IF(I9>D9,1,0) -> 0
A10: =+A9+1 -> 8 | B10: =VLOOKUP(A10,Base!$CB$3:$CC$21,2,FALSE) -> 16 | C10: =+VLOOKUP(B10,Base!$CC$3:$CD$21,2,FALSE) -> 0.01 | D10: =+VLOOKUP(B10,Base!$CC$3:$CE$21,3,FALSE) -> 0.07 | E10: =+($E$26-1)*C10 -> 0.025 | F10: =+F9+E10 -> 1.025 | G10: =+IF(F10<(1-$C$23),E10,IF(((1-$C$23)-F9)>0,((1-$C$23)-F9),0)) -> 0 | H10: =+VLOOKUP(B10,Base!$A$3:$C$21,3,FALSE) -> Medical Office | I10: =+C10+G10 -> 0.01 | J10: =+IF(I10>D10,1,0) -> 0
A11: =+A10+1 -> 9 | B11: =VLOOKUP(A11,Base!$CB$3:$CC$21,2,FALSE) -> 4 | C11: =+VLOOKUP(B11,Base!$CC$3:$CD$21,2,FALSE) -> 0 | D11: =+VLOOKUP(B11,Base!$CC$3:$CE$21,3,FALSE) -> 0.15 | E11: =+($E$26-1)*C11 -> 0 | F11: =+F10+E11 -> 1.025 | G11: =+IF(F11<(1-$C$23),E11,IF(((1-$C$23)-F10)>0,((1-$C$23)-F10),0)) -> 0 | H11: =+VLOOKUP(B11,Base!$A$3:$C$21,3,FALSE) -> Core - Retail | I11: =+C11+G11 -> 0 | J11: =+IF(I11>D11,1,0) -> 0
A12: =+A11+1 -> 10 | B12: =VLOOKUP(A12,Base!$CB$3:$CC$21,2,FALSE) -> 17 | C12: =+VLOOKUP(B12,Base!$CC$3:$CD$21,2,FALSE) -> 0.01 | D12: =+VLOOKUP(B12,Base!$CC$3:$CE$21,3,FALSE) -> 0.07 | E12: =+($E$26-1)*C12 -> 0.025 | F12: =+F11+E12 -> 1.05 | G12: =+IF(F12<(1-$C$23),E12,IF(((1-$C$23)-F11)>0,((1-$C$23)-F11),0)) -> 0 | H12: =+VLOOKUP(B12,Base!$A$3:$C$21,3,FALSE) -> Life Science | I12: =+C12+G12 -> 0.01 | J12: =+IF(I12>D12,1,0) -> 0
A13: =+A12+1 -> 11 | B13: =VLOOKUP(A13,Base!$CB$3:$CC$21,2,FALSE) -> 1 | C13: =+VLOOKUP(B13,Base!$CC$3:$CD$21,2,FALSE) -> 0 | D13: =+VLOOKUP(B13,Base!$CC$3:$CE$21,3,FALSE) -> 0.3 | E13: =+($E$26-1)*C13 -> 0 | F13: =+F12+E13 -> 1.05 | G13: =+IF(F13<(1-$C$23),E13,IF(((1-$C$23)-F12)>0,((1-$C$23)-F12),0)) -> 0 | H13: =+VLOOKUP(B13,Base!$A$3:$C$21,3,FALSE) -> Core - Res | I13: =+C13+G13 -> 0 | J13: =+IF(I13>D13,1,0) -> 0
A14: =+A13+1 -> 12 | B14: =VLOOKUP(A14,Base!$CB$3:$CC$21,2,FALSE) -> 15 | C14: =+VLOOKUP(B14,Base!$CC$3:$CD$21,2,FALSE) -> 0.01 | D14: =+VLOOKUP(B14,Base!$CC$3:$CE$21,3,FALSE) -> 0.07 | E14: =+($E$26-1)*C14 -> 0.025 | F14: =+F13+E14 -> 1.075 | G14: =+IF(F14<(1-$C$23),E14,IF(((1-$C$23)-F13)>0,((1-$C$23)-F13),0)) -> 0 | H14: =+VLOOKUP(B14,Base!$A$3:$C$21,3,FALSE) -> Manufactured Home Park | I14: =+C14+G14 -> 0.01 | J14: =+IF(I14>D14,1,0) -> 0
A15: =+A14+1 -> 13 | B15: =VLOOKUP(A15,Base!$CB$3:$CC$21,2,FALSE) -> 6 | C15: =+VLOOKUP(B15,Base!$CC$3:$CD$21,2,FALSE) -> 0.2 | D15: =+VLOOKUP(B15,Base!$CC$3:$CE$21,3,FALSE) -> 0.3 | E15: =+($E$26-1)*C15 -> 0.5 | F15: =+F14+E15 -> 1.575 | G15: =+IF(F15<(1-$C$23),E15,IF(((1-$C$23)-F14)>0,((1-$C$23)-F14),0)) -> 0 | H15: =+VLOOKUP(B15,Base!$A$3:$C$21,3,FALSE) -> Core-Plus - Ind | I15: =+C15+G15 -> 0.2 | J15: =+IF(I15>D15,1,0) -> 0
... A21: =+A20+1 -> 19 | B21: =VLOOKUP(A21,Base!$CB$3:$CC$21,2,FALSE) -> 7 | C21: =+VLOOKUP(B21,Base!$CC$3:$CD$21,2,FALSE) -> 0.05 | D21: =+VLOOKUP(B21,Base!$CC$3:$CE$21,3,FALSE) -> 0.15 | E21: =+($E$26-1)*C21 -> 0.125 | F21: =+F20+E21 -> 1.8 | G21: =+IF(F21<(1-$C$23),E21,IF(((1-$C$23)-F20)>0,((1-$C$23)-F20),0)) -> 0 | H21: =+VLOOKUP(B21,Base!$A$3:$C$21,3,FALSE) -> Core-Plus - Off | I21: =+C21+G21 -> 0.05 | J21: =+IF(I21>D21,1,0) -> 0
C23: =SUM(C3:C21) -> 0.72 | I23: =SUM(I3:I21) -> 1 | J23: =+SUM(J3:J21) -> 1
D26: Diversification factor (higher means more concentrated) | E26: 3.5 | F26: =+IF(E26<E27,"ERROR",) -> 0
D27: Min value | E27: =1/C23 -> 1.3888889
B30: SI | D30: Port | E30: 6 YR IRR
B31: 1 | C31: =+VLOOKUP(B31,Base!$A$3:$C$21,3,FALSE) -> Core - Res | D31: =+VLOOKUP(B31,$B$3:$I$21,8,FALSE) -> 0 | E31: =+Base!AA3 -> 0.079066583
B32: =+B31+1 -> 2 | C32: =+VLOOKUP(B32,Base!$A$3:$C$21,3,FALSE) -> Core - Ind | D32: =+VLOOKUP(B32,$B$3:$I$21,8,FALSE) -> 0 | E32: =+Base!AA4 -> 0.061531554
B33: =+B32+1 -> 3 | C33: =+VLOOKUP(B33,Base!$A$3:$C$21,3,FALSE) -> Core - Off | D33: =+VLOOKUP(B33,$B$3:$I$21,8,FALSE) -> 0 | E33: =+Base!AA5 -> 0.027376585
B34: =+B33+1 -> 4 | C34: =+VLOOKUP(B34,Base!$A$3:$C$21,3,FALSE) -> Core - Retail | D34: =+VLOOKUP(B34,$B$3:$I$21,8,FALSE) -> 0 | E34: =+Base!AA6 -> 0.089923054
B35: =+B34+1 -> 5 | C35: =+VLOOKUP(B35,Base!$A$3:$C$21,3,FALSE) -> Core-Plus - Res | D35: =+VLOOKUP(B35,$B$3:$I$21,8,FALSE) -> 0.2 | E35: =+Base!AA7 -> 0.085711713
B36: =+B35+1 -> 6 | C36: =+VLOOKUP(B36,Base!$A$3:$C$21,3,FALSE) -> Core-Plus - Ind | D36: =+VLOOKUP(B36,$B$3:$I$21,8,FALSE) -> 0.2 | E36: =+Base!AA8 -> 0.064271025
B37: =+B36+1 -> 7 | C37: =+VLOOKUP(B37,Base!$A$3:$C$21,3,FALSE) -> Core-Plus - Off | D37: =+VLOOKUP(B37,$B$3:$I$21,8,FALSE) -> 0.05 | E37: =+Base!AA9 -> 0.02291798
B38: =+B37+1 -> 8 | C38: =+VLOOKUP(B38,Base!$A$3:$C$21,3,FALSE) -> Core-Plus - Ret | D38: =+VLOOKUP(B38,$B$3:$I$21,8,FALSE) -> 0.13 | E38: =+Base!AA10 -> 0.10413809
B39: =+B38+1 -> 9 | C39: =+VLOOKUP(B39,Base!$A$3:$C$21,3,FALSE) -> Data Center | D39: =+VLOOKUP(B39,$B$3:$I$21,8,FALSE) -> 0.175 | E39: =+Base!AA11 -> 0.11776038
B40: =+B39+1 -> 10 | C40: =+VLOOKUP(B40,Base!$A$3:$C$21,3,FALSE) -> Single-Family Rental | D40: =+VLOOKUP(B40,$B$3:$I$21,8,FALSE) -> 0.05 | E40: =+Base!AA12 -> 0.099207502
B41: =+B40+1 -> 11 | C41: =+VLOOKUP(B41,Base!$A$3:$C$21,3,FALSE) -> Cold Storage | D41: =+VLOOKUP(B41,$B$3:$I$21,8,FALSE) -> 0.02 | E41: =+Base!AA13 -> 0.026114439
B42: =+B41+1 -> 12 | C42: =+VLOOKUP(B42,Base!$A$3:$C$21,3,FALSE) -> Senior Housing | D42: =+VLOOKUP(B42,$B$3:$I$21,8,FALSE) -> 0.07 | E42: =+Base!AA14 -> 0.12802797
B43: =+B42+1 -> 13 | C43: =+VLOOKUP(B43,Base!$A$3:$C$21,3,FALSE) -> Student Housing | D43: =+VLOOKUP(B43,$B$3:$I$21,8,FALSE) -> 0.02 | E43: =+Base!AA15 -> 0.099011553
... B49: =+B48+1 -> 19 | C49: =+VLOOKUP(B49,Base!$A$3:$C$21,3,FALSE) -> IOS | D49: =+VLOOKUP(B49,$B$3:$I$21,8,FALSE) -> 0.01 | E49: =+Base!AA21 -> 0.020862224
E51: =+SUMPRODUCT(D31:D49,E31:E49) -> 0.089466593

Sheet 6 YR Sum
A2: SectorIdentifier | B2: Region | C2: Profile | D2: Nom Cap Rate | E2: Capex (Recc) | F2: Econ Cap Rate | G2: Rent 6 YR CAGR | H2: Cap Rate Changes | I2: Unlevered Prop Level | J2: Other Return | K2: Tot UnLev Ret | L2: Gr Fund Lev Level Ret | M2: Net Fund Level Ret
A3: 1 | B3: US | C3: Core - Res
A4: =+A3+1 -> 2 | B4: US | C4: Core - Ind
A5: =+A4+1 -> 3 | B5: US | C5: Core - Off
A6: =+A5+1 -> 4 | B6: US | C6: Core - Retail
A7: =+A6+1 -> 5 | B7: US | C7: Core-Plus - Res
A8: =+A7+1 -> 6 | B8: US | C8: Core-Plus - Ind
A9: =+A8+1 -> 7 | B9: US | C9: Core-Plus - Off
A10: =+A9+1 -> 8 | B10: US | C10: Core-Plus - Ret
A11: =+A10+1 -> 9 | B11: US | C11: Data Center
A12: =+A11+1 -> 10 | B12: US | C12: Single-Family Rental
A13: =+A12+1 -> 11 | B13: US | C13: Cold Storage
A14: =+A13+1 -> 12 | B14: US | C14: Senior Housing
A15: =+A14+1 -> 13 | B15: US | C15: Student Housing
... A21: =+A20+1 -> 19 | B21: US | C21: IOS
A24: =+A23+1 -> 1 | B24: US | C24: Core - Ind | D24: =+Base!D62 -> 0.047 | E24: =-D24*Base!E62 -> -0.006486 | F24: =+Base!F62 -> 0.040514 | G24: =+Base!U62 -> 0.044087271 | H24: =+Base!X62 -> -0.010293439 | I24: =+Base!AA62 -> 0.074307833 | J24: =+Base!BR62 -> 0.011 | K24: =+Base!AD62 -> 0.085307833 | L24: =+Base!AG62 -> 0.088397592 | M24: =+Base!AJ62 -> 0.078397592

Sheet 3 YR Sum
A2: SectorIdentifier | B2: Region | C2: Profile | D2: Nom Cap Rate | E2: Capex (Recc) | F2: Econ Cap Rate | G2: Rent 3 YR CAGR | H2: Cap Rate Changes | I2: Unlevered Prop Level | J2: Other Return | K2: Tot UnLev Ret | L2: Gr Fund Lev Level Ret | M2: Net Fund Level Ret
A3: 1 | B3: US | C3: Core - Res
A4: =+A3+1 -> 2 | B4: US | C4: Core - Ind
A5: =+A4+1 -> 3 | B5: US | C5: Core - Off
A6: =+A5+1 -> 4 | B6: US | C6: Core - Retail
A7: =+A6+1 -> 5 | B7: US | C7: Core-Plus - Res
A8: =+A7+1 -> 6 | B8: US | C8: Core-Plus - Ind
A9: =+A8+1 -> 7 | B9: US | C9: Core-Plus - Off
A10: =+A9+1 -> 8 | B10: US | C10: Core-Plus - Ret
A11: =+A10+1 -> 9 | B11: US | C11: Data Center
A12: =+A11+1 -> 10 | B12: US | C12: Single-Family Rental
A13: =+A12+1 -> 11 | B13: US | C13: Cold Storage
A14: =+A13+1 -> 12 | B14: US | C14: Senior Housing
A15: =+A14+1 -> 13 | B15: US | C15: Student Housing
... A21: =+A20+1 -> 19 | B21: US | C21: IOS
A24: =+A23+1 -> 1 | B24: US | C24: Core - Ind | D24: =+Base!D62 -> 0.047 | E24: =-D24*Base!E62 -> -0.006486 | F24: =+Base!F62 -> 0.040514 | G24: =+Base!T62 -> 0.050682159 | H24: =+Base!W62 -> 0.17227303 | I24: =+Base!Z62 -> 0.26346919 | J24: =+Base!BR62 -> 0.011 | K24: =+Base!AC62 -> 0.27446919 | L24: =+Base!AF62 -> 0.29857687 | M24: =+Base!AI62 -> 0.28857687
